Workbook
Name Z_BE54E0AD_3725_4423_92D7_4F1C045BE1BC_.wvu.Cols: 'Create Discount'!$E:$E
Name Z_BE54E0AD_3725_4423_92D7_4F1C045BE1BC_.wvu.Cols: Register!$E:$E
Name Z_6F1DCD5D_5DAC_4817_BF40_2B66F6F593E6_.wvu.Cols: 'ActivateDeactivate Shop'!$E:$E
Name Z_2C0D9096_8D85_462A_A9B5_0B488ADB4269_.wvu.Cols: 'View Reports (Operator)'!$E:$E
Name Z_BE54E0AD_3725_4423_92D7_4F1C045BE1BC_.wvu.Cols: 'View Report Detail (Operator)'!$E:$E
Name Z_2C0D9096_8D85_462A_A9B5_0B488ADB4269_.wvu.Cols: 'View Blog Reports'!$E:$E
Name Z_2C0D9096_8D85_462A_A9B5_0B488ADB4269_.wvu.Cols: EditProduct!$E:$E
Name Z_6F1DCD5D_5DAC_4817_BF40_2B66F6F593E6_.wvu.Cols: 'ApproveReject Shipper register'!$E:$E
Name Z_2C0D9096_8D85_462A_A9B5_0B488ADB4269_.wvu.Cols: 'View feedback list'!$E:$E
Name Z_6F1DCD5D_5DAC_4817_BF40_2B66F6F593E6_.wvu.Cols: 'Request Order return'!$E:$E
Name Z_BE54E0AD_3725_4423_92D7_4F1C045BE1BC_.wvu.Cols: 'ActivateDeactivate Shipper'!$E:$E
Name Z_6F1DCD5D_5DAC_4817_BF40_2B66F6F593E6_.wvu.Cols: 'ActivateDeactivate Shipper'!$E:$E
Name Z_BE54E0AD_3725_4423_92D7_4F1C045BE1BC_.wvu.Cols: 'Reject Order'!$E:$E
Name Z_2C0D9096_8D85_462A_A9B5_0B488ADB4269_.wvu.Cols: 'Apply Voucher'!$E:$E
Name Z_BE54E0AD_3725_4423_92D7_4F1C045BE1BC_.wvu.Cols: 'Accept Order'!$E:$E
Name Z_2C0D9096_8D85_462A_A9B5_0B488ADB4269_.wvu.Cols: 'View Shops revenue'!$E:$E
Name Z_BE54E0AD_3725_4423_92D7_4F1C045BE1BC_.wvu.Cols: 'View Shop Reports(Shopkeeper)'!$E:$E
Name Z_6F1DCD5D_5DAC_4817_BF40_2B66F6F593E6_.wvu.Cols: 'Auto count Rating for Shop'!$E:$E
Name Z_2C0D9096_8D85_462A_A9B5_0B488ADB4269_.wvu.PrintArea: Statistics!$A:$I
Name Z_2C0D9096_8D85_462A_A9B5_0B488ADB4269_.wvu.Cols: 'ActivateDeactivate Shipper'!$E:$E
Name Z_BE54E0AD_3725_4423_92D7_4F1C045BE1BC_.wvu.Cols: 'Get location from google Map'!$E:$E
Name Z_6F1DCD5D_5DAC_4817_BF40_2B66F6F593E6_.wvu.Cols: 'Confirm Order Receive(Customer)'!$E:$E
Name Z_6F1DCD5D_5DAC_4817_BF40_2B66F6F593E6_.wvu.Cols: 'View Shops revenue'!$E:$E
Name Z_6F1DCD5D_5DAC_4817_BF40_2B66F6F593E6_.wvu.Cols: 'View feedback list'!$E:$E
Name Z_6F1DCD5D_5DAC_4817_BF40_2B66F6F593E6_.wvu.Cols: 'View Shop Dashboard'!$E:$E
Name Z_BE54E0AD_3725_4423_92D7_4F1C045BE1BC_.wvu.Cols: AddProduct!$E:$E
Name Z_2C0D9096_8D85_462A_A9B5_0B488ADB4269_.wvu.Cols: 'Disable Voucher'!$E:$E
Name Z_BE54E0AD_3725_4423_92D7_4F1C045BE1BC_.wvu.Cols: 'View Discount List'!$E:$E
Name Z_6F1DCD5D_5DAC_4817_BF40_2B66F6F593E6_.wvu.Cols: 'Create Discount'!$E:$E
Name Z_6F1DCD5D_5DAC_4817_BF40_2B66F6F593E6_.wvu.Cols: 'View Order List (Customer)'!$E:$E
Name Z_2C0D9096_8D85_462A_A9B5_0B488ADB4269_.wvu.Cols: Register!$E:$E
Name Z_6F1DCD5D_5DAC_4817_BF40_2B66F6F593E6_.wvu.Cols: 'Disable Voucher'!$E:$E
Name Z_2C0D9096_8D85_462A_A9B5_0B488ADB4269_.wvu.Cols: 'Create Discount'!$E:$E
Name Z_6F1DCD5D_5DAC_4817_BF40_2B66F6F593E6_.wvu.Cols: 'Submit Feedback '!$E:$E
Name Z_BE54E0AD_3725_4423_92D7_4F1C045BE1BC_.wvu.Cols: ViewProductList!$E:$E
Name Z_BE54E0AD_3725_4423_92D7_4F1C045BE1BC_.wvu.Cols: 'Auto count Rating for Shop'!$E:$E
Name Z_2C0D9096_8D85_462A_A9B5_0B488ADB4269_.wvu.Cols: 'Change Order Status (Shopkeeper'!$E:$E
Name Z_BE54E0AD_3725_4423_92D7_4F1C045BE1BC_.wvu.Cols: 'View Voucher List'!$E:$E
Name Z_6F1DCD5D_5DAC_4817_BF40_2B66F6F593E6_.wvu.Cols: 'Resolve Order Return Request'!$E:$E
Name Z_BE54E0AD_3725_4423_92D7_4F1C045BE1BC_.wvu.Cols: 'ApproveReject Shipper register'!$E:$E
Name Z_BE54E0AD_3725_4423_92D7_4F1C045BE1BC_.wvu.Cols: 'Choose Payment Method'!$E:$E
Name Z_6F1DCD5D_5DAC_4817_BF40_2B66F6F593E6_.wvu.Cols: Login!$E:$E
Name Z_6F1DCD5D_5DAC_4817_BF40_2B66F6F593E6_.wvu.Cols: 'ActivateDeactivate account'!$E:$E
Name Z_2C0D9096_8D85_462A_A9B5_0B488ADB4269_.wvu.Cols: 'Change Order Status (Shipper)'!$E:$E
Name Z_6F1DCD5D_5DAC_4817_BF40_2B66F6F593E6_.wvu.Cols: 'ApproveReject shop register'!$E:$E
Name Z_BE54E0AD_3725_4423_92D7_4F1C045BE1BC_.wvu.Cols: 'Apply Voucher'!$E:$E
Name Z_BE54E0AD_3725_4423_92D7_4F1C045BE1BC_.wvu.Cols: 'Choose Shipping Method'!$E:$E
Name Z_2C0D9096_8D85_462A_A9B5_0B488ADB4269_.wvu.Cols: 'Delete feedback'!$E:$E
Name Z_2C0D9096_8D85_462A_A9B5_0B488ADB4269_.wvu.Cols: 'Check Out'!$E:$E
Name Z_2C0D9096_8D85_462A_A9B5_0B488ADB4269_.wvu.Cols: 'Recommend food by type for cust'!$E:$E
Name Z_2C0D9096_8D85_462A_A9B5_0B488ADB4269_.wvu.Cols: 'Confirm Order Receive(Customer)'!$E:$E
Name Z_6F1DCD5D_5DAC_4817_BF40_2B66F6F593E6_.wvu.Cols: 'Recommend food by type for cust'!$E:$E
Name Z_6F1DCD5D_5DAC_4817_BF40_2B66F6F593E6_.wvu.Cols: 'View Voucher List'!$E:$E
Name Z_2C0D9096_8D85_462A_A9B5_0B488ADB4269_.wvu.Cols: 'Disable Discount'!$E:$E
Name Z_BE54E0AD_3725_4423_92D7_4F1C045BE1BC_.wvu.Cols: 'Shipper Register'!$E:$E
Name Z_BE54E0AD_3725_4423_92D7_4F1C045BE1BC_.wvu.Cols: 'Disable Voucher'!$E:$E
Name Z_BE54E0AD_3725_4423_92D7_4F1C045BE1BC_.wvu.Cols: 'Submit Feedback '!$E:$E
Name Z_BE54E0AD_3725_4423_92D7_4F1C045BE1BC_.wvu.Cols: 'Delete feedback'!$E:$E
Name Z_2C0D9096_8D85_462A_A9B5_0B488ADB4269_.wvu.Cols: 'View Blog Report Detail'!$E:$E
Name Z_6F1DCD5D_5DAC_4817_BF40_2B66F6F593E6_.wvu.Cols: 'Change Order Status (Shopkeeper'!$E:$E

Sheet Guideline
A1: Guideline to make and understand Unit Test Case
A3: 1. Overview
A4: - In the template, Unit test cases are based on functions. Each sheet presents test cases for one function.
A5: - Cover: General information of the project and Unit Test cases
A6: - FunctionList: The list of Classes and Functions in the document. + To control that the number of Unit TC meets customer's requirement or the norm, user should fill value for 'Normal number of Test cases/KLOC'.
A7: + Click on Function link to open the related Test cases of the function. Note: You should create new Function sheet before creating the link
A8: - Test Report: provive the overview results of Functions Unit test: Test coverage, Test successful coverage (Summary, for normal/abnormal/boundary cases)
A9: Note: Should check the formula of "Sub Total" if you add more functions
A11: 2. Content in Test function sheet
A12: 2.1 Combination of test cases.
A13: - To verify that number of Unit TC meets customer's requirement or not. User has to fill number LOC of tested function and fill value of 'Normal number test cases/KLOC' item in FunctionList sheet, which is required by customer or normal value. The number of lacked TC is shown in 'Lack of test cases' item.
A14: - If the number of Unit TC does not meet the requirement, creator should explain the reasons.
... A46: - Test requirement: Brief description about requirements which are tested in this function, it is not mandatory.

Sheet Cover
B2: UNIT TEST DOCUMENT
A4: Project Name | B4: FastF&B | E4: Creator | F4: AnhDQ
A5: Project Code | B5: FFB | E5: Issue Date | F5: 45698
A6: Document Code | B6: =B5&"_"&"UnitTest"&"_"&"v1.0" -> FFB_UnitTest_v1.0 | E6: Version | F6: 1.1.2
A9: Record of change
A10: Effective Date | B10: Version | C10: Change Item | D10: *A,D,M | E10: Change description | F10: Reference
A11: 45698 | B11: 1.0 | D11: C | E11: Create report
A12: 45700 | B12: 1.0 | D12: A | E12: Add MethodList and Statistics form for iter 1
A13: 45701 | B13: 1.0 | D13: A | E13: Add all the sheet for iter 1
A14: 45702 | B14: 1.0 | D14: A | E14: Add all the test case for modules for iter 1
A15: 45720 | B15: 1.1 | D15: A | E15: Add MethodList and Statistics form for iter 2
A16: 45720 | B16: 1.1 | D16: A | E16: Add all the sheet for iter 2
A17: 45721 | B17: 1.1 | D17: A | E17: Add all the test case for modules for iter 2
A18: 45736 | B18: 1.2 | D18: A | E18: Add MethodList and Statistics form for iter 3
A19: 45737 | B19: 1.2 | D19: A | E19: Add all the sheet for iter 3
A20: 45738 | B20: 1.2 | D20: A | E20: Add all the test case for modules for iter 3

Sheet MethodList
C2: Method List
A4: Project Name | C4: =Cover!B4 -> FastF&B
A5: Project Code | C5: =Cover!B5 -> FFB
A6: Test Environment Setup Description | C6: 1. Server 2. MySql Database 3. Web Browser for React 4.Mobile App for Flutter 5.Postman
A8: No | B8: Module Name | C8: Method Name | D8: Sheet Name | E8: Description | F8: Pre-Condition
A9: 1 | B9: Account Management | C9: Login | D9: Login | F9: Already have an account in the system database
A10: 2 | B10: Account Management | C10: Logout | D10: Logout | F10: Logged into the system
A11: 3 | B11: Account Management | C11: Register | D11: Register | F11: Format password, email, phone number when entering
A12: 4 | B12: Account Management | C12: View profile | D12: View profile | F12: Logged into the system
A13: 5 | B13: Account Management | C13: Edit profile | D13: Edit profile | F13: Logged into the system
A14: 6 | B14: Account Management | C14: Change password | D14: Change password | F14: Logged into the system
A15: 7 | B15: Account Management | C15: Forgot password | D15: Forgot password | F15: Account must be registered with phone number in db
A16: 8 | B16: Blog Management | C16: View Blog List | D16: View Blog List | F16: Logged into the system
A17: 9 | B17: Blog Management | C17: View Blog Detail | D17: View Blog Detail | F17: Logged into the system
A18: 10 | B18: Blog Management | C18: Add Blog Post | D18: Add Blog Post | F18: Logged into the system
A19: 11 | B19: Blog Management | C19: Edit Blog Post | D19: Edit Blog Post | F19: Logged in to the system, is the owner of at least 1 blog
A20: 12 | B20: Blog Management | C20: Delete Blog Post | D20: Delete Blog Post | F20: Logged in to the system, is the owner of at least 1 blog
... A90: 82 | B90: Discount Management | C90: Disable Discount | D90: View Discount List | F90: Logged into the system

Sheet Statistics
A2: UNIT TEST REPORT
A4: Project Name | B4: =Cover!B4 -> FastF&B | D4: Creator | F4: AnhDQ
A5: Project Code | B5: =Cover!B5 -> FFB | D5: Reviewer/Approver | F5: NGUYENT
A6: Document Code | B6: =B5&"_"&"UnitTest"&"_"&"v1.2" -> FFB_UnitTest_v1.2 | D6: Issue Date | F6: 45698
A7: Notes
A11: No | B11: Function code | C11: Passed | D11: Failed | E11: Untested | F11: N | G11: A | H11: B | I11: Total Test Cases
A12: 1 | B12: Login | C12: =Login!A5 -> 4 | D12: =Login!C5 -> 0 | E12: =Login!F5 -> 0 | F12: =Login!L5 -> 1 | G12: =Login!M5 -> 3 | H12: =Login!N5 -> 0 | I12: =Login!O5 -> 4
A13: 2 | B13: Logout | C13: =Logout!A5 -> 1 | D13: =Logout!C5 -> 0 | E13: =Logout!F5 -> 0 | F13: =Logout!L5 -> 1 | G13: =Logout!M5 -> 0 | H13: =Logout!N5 -> 0 | I13: =Logout!O5 -> 1
A14: 3 | B14: Register | C14: =Register!A5 -> 18 | D14: =Register!C5 -> 0 | E14: =Register!F5 -> 0 | F14: =Register!L5 -> 1 | G14: =Register!M5 -> 17 | H14: =Register!N5 -> 0 | I14: =Register!O5 -> 18
A15: 4 | B15: View profile | C15: =ViewProfile!A5 -> 2 | D15: =ViewProfile!C5 -> 0 | E15: =ViewProfile!F5 -> 0 | F15: =ViewProfile!L5 -> 1 | G15: =ViewProfile!M5 -> 1 | H15: =ViewProfile!N5 -> 0 | I15: =ViewProfile!O5 -> 2
A16: 5 | B16: Edit profile | C16: =EditProfile!A5 -> 6 | D16: =EditProfile!C5 -> 0 | E16: =EditProfile!F5 -> 0 | F16: =EditProfile!L5 -> 1 | G16: =EditProfile!M5 -> 5 | H16: =EditProfile!N5 -> 0 | I16: =EditProfile!O5 -> 6
A17: 6 | B17: Change password | C17: =ChangePassword!A5 -> 4 | D17: =ChangePassword!C5 -> 0 | E17: =ChangePassword!F5 -> 0 | F17: =ChangePassword!L5 -> 1 | G17: =ChangePassword!M5 -> 3 | H17: =ChangePassword!N5 -> 0 | I17: =ChangePassword!O5 -> 4
A18: 7 | B18: Forgot password | C18: =Forgotpassword!A5 -> 4 | D18: =Forgotpassword!C5 -> 0 | E18: =Forgotpassword!F5 -> 0 | F18: =Forgotpassword!L5 -> 1 | G18: =Forgotpassword!M5 -> 3 | H18: =Forgotpassword!N5 -> 0 | I18: =Forgotpassword!O5 -> 4
A19: 8 | B19: View Blog List | C19: =ViewBlogList!A5 -> 2 | D19: =ViewBlogList!C5 -> 0 | E19: =ViewBlogList!F5 -> 0 | F19: =ViewBlogList!L5 -> 2 | G19: =ViewBlogList!M5 -> 0 | H19: =ViewBlogList!N5 -> 0 | I19: =ViewBlogList!O5 -> 2
A20: 9 | B20: View Blog Detail | C20: =ViewProfile!O5 -> 2 | D20: =ViewProfile!C5 -> 0 | E20: =ViewProfile!F5 -> 0 | F20: =ViewProfile!L5 -> 1 | G20: =ViewProfile!M5 -> 1 | H20: =ViewProfile!N5 -> 0 | I20: =ViewProfile!O5 -> 2
A21: 10 | B21: Add Blog Post | C21: =AddBlog!A5 -> 3 | D21: =AddBlog!C5 -> 0 | E21: =AddBlog!F5 -> 0 | F21: =AddBlog!L5 -> 2 | G21: =AddBlog!M5 -> 1 | H21: =AddBlog!N5 -> 0 | I21: =AddBlog!O5 -> 3
A22: 11 | B22: Edit Blog Post | C22: =EditBlog!O5 -> 4 | D22: =EditBlog!C5 -> 0 | E22: =EditBlog!F5 -> 0 | F22: =EditBlog!L5 -> 4 | G22: =EditBlog!M5 -> 0 | H22: =EditBlog!N5 -> 0 | I22: =EditBlog!O5 -> 4
A23: 12 | B23: Delete Blog Post | C23: =DeleteBlog!O5 -> 1 | D23: =DeleteBlog!C5 -> 0 | E23: =DeleteBlog!F5 -> 0 | F23: =DeleteBlog!L5 -> 1 | G23: =DeleteBlog!M5 -> 0 | H23: =DeleteBlog!N5 -> 0 | I23: =DeleteBlog!O5 -> 1
A24: 13 | B24: Comment/Reply on Blog | C24: =CommentReplyonBlog!A5 -> 8 | D24: =CommentReplyonBlog!C5 -> 0 | E24: =CommentReplyonBlog!F5 -> 0 | F24: =CommentReplyonBlog!L5 -> 2 | G24: =CommentReplyonBlog!M5 -> 4 | H24: =CommentReplyonBlog!N5 -> 2 | I24: =CommentReplyonBlog!O5 -> 8
A25: 14 | B25: View Shop Product (Shopkeeper) | C25: =ViewShopProduct!A5 -> 5 | D25: =ViewShopProduct!C5 -> 0 | E25: =ViewShopProduct!F5 -> 0 | F25: =ViewShopProduct!L5 -> 5 | G25: =ViewShopProduct!M5 -> 0 | H25: =ViewShopProduct!N5 -> 0 | I25: =ViewShopProduct!O5 -> 5
A26: 15 | B26: Add Product | C26: =AddProduct!A5 -> 6 | D26: =AddProduct!C5 -> 0 | E26: =AddProduct!F5 -> 0 | F26: =AddProduct!L5 -> 1 | G26: =AddProduct!M5 -> 3 | H26: =AddProduct!N5 -> 2 | I26: =AddProduct!O5 -> 6
A27: 16 | B27: Edit Product | C27: =EditProduct!A5 -> 6 | D27: =EditProduct!C5 -> 0 | E27: =EditProduct!F5 -> 0 | F27: =EditProduct!L5 -> 1 | G27: =EditProduct!M5 -> 3 | H27: =EditProduct!N5 -> 2 | I27: =EditProduct!O5 -> 6
A28: 17 | B28: Delete Product | C28: =DeleteProduct!A5 -> 1 | D28: =DeleteProduct!C5 -> 0 | E28: =DeleteProduct!F5 -> 0 | F28: =DeleteProduct!L5 -> 1 | G28: =DeleteProduct!M5 -> 0 | H28: =DeleteProduct!N5 -> 0 | I28: =DeleteProduct!O5 -> 1
A29: 18 | B29: View Product List | C29: =ViewProductList!A5 -> 4 | D29: =ViewProductList!C5 -> 0 | E29: =ViewProductList!F5 -> 0 | F29: =ViewProductList!L5 -> 3 | G29: =ViewProductList!M5 -> 1 | H29: =ViewProductList!N5 -> 0 | I29: =ViewProductList!O5 -> 4
A30: 19 | B30: View Product Detail (Shopkeeper) | C30: =ViewProductDetail!A5 -> 4 | D30: =ViewProductDetail!C5 -> 0 | E30: =ViewProductDetail!F5 -> 0 | F30: =ViewProductDetail!L5 -> 3 | G30: =ViewProductDetail!M5 -> 1 | H30: =ViewProductDetail!N5 -> 0 | I30: =ViewProductDetail!O5 -> 4
A31: 20 | B31: View user list | C31: =ViewUserList!A5 -> 3 | D31: =ViewUserList!C5 -> 0 | E31: =ViewUserList!F5 -> 0 | F31: =ViewUserList!L5 -> 3 | G31: =ViewUserList!M5 -> 0 | H31: =ViewUserList!N5 -> 0 | I31: =ViewUserList!O5 -> 3
A32: 21 | B32: Activate/Deactivate account | C32: ='ActivateDeactivate account'!A5 -> 5 | D32: ='ActivateDeactivate account'!C5 -> 0 | E32: ='ActivateDeactivate account'!F5 -> 0 | F32: ='ActivateDeactivate account'!L5 -> 2 | G32: ='ActivateDeactivate account'!M5 -> 3 | H32: ='ActivateDeactivate account'!N5 -> 0 | I32: ='ActivateDeactivate account'!O5 -> 5
A33: 22 | B33: View Reports (Operator) | C33: ='View Reports (Operator)'!A5 -> 2 | D33: ='View Reports (Operator)'!C5 -> 0 | E33: ='View Reports (Operator)'!F5 -> 0 | F33: ='View Reports (Operator)'!L5 -> 2 | G33: ='View Reports (Operator)'!M5 -> 0 | H33: ='View Reports (Operator)'!N5 -> 0 | I33: ='View Reports (Operator)'!O5 -> 2
A34: 23 | B34: View Report Detail (Operator) | C34: ='View Report Detail (Operator)'!A5 -> 3 | D34: ='View Report Detail (Operator)'!C5 -> 0 | E34: ='View Report Detail (Operator)'!F5 -> 0 | F34: ='View Report Detail (Operator)'!L5 -> 3 | G34: ='View Report Detail (Operator)'!M5 -> 0 | H34: ='View Report Detail (Operator)'!N5 -> 0 | I34: ='View Report Detail (Operator)'!O5 -> 3
A35: 24 | B35: Activate/Deactivate Shop | C35: ='ActivateDeactivate Shop'!A5 -> 5 | D35: ='ActivateDeactivate Shop'!C5 -> 0 | E35: ='ActivateDeactivate Shop'!F5 -> 0 | F35: ='ActivateDeactivate Shop'!L5 -> 2 | G35: ='ActivateDeactivate Shop'!M5 -> 3 | H35: ='ActivateDeactivate Shop'!N5 -> 0 | I35: ='ActivateDeactivate Shop'!O5 -> 5
A36: 25 | B36: Activate/Deactivate Blog | C36: ='ActivateDeactivate Blog'!A5 -> 5 | D36: ='ActivateDeactivate Blog'!C5 -> 0 | E36: ='ActivateDeactivate Blog'!F5 -> 0 | F36: ='ActivateDeactivate Blog'!L5 -> 0 | G36: ='ActivateDeactivate Blog'!M5 -> 0 | H36: ='ActivateDeactivate Blog'!N5 -> 0 | I36: ='ActivateDeactivate Blog'!O5 -> 5
A37: 26 | B37: View Shop List (Operator) | C37: ='View Shop List (Operator)'!A5 -> 4 | D37: ='View Shop List (Operator)'!C5 -> 0 | E37: ='View Shop List (Operator)'!F5 -> 0 | F37: ='View Shop List (Operator)'!L5 -> 0 | G37: ='View Shop List (Operator)'!M5 -> 0 | H37: ='View Shop List (Operator)'!N5 -> 0 | I37: ='View Shop List (Operator)'!O5 -> 4
A38: 27 | B38: View Shop Detail (Operator) | C38: ='View Shop Detail (Operator)'!A5 -> 2 | D38: ='View Shop Detail (Operator)'!C5 -> 0 | E38: ='View Shop Detail (Operator)'!F5 -> 0 | F38: ='View Shop Detail (Operator)'!L5 -> 1 | G38: ='View Shop Detail (Operator)'!M5 -> 0 | H38: ='View Shop Detail (Operator)'!N5 -> 0 | I38: ='View Shop Detail (Operator)'!O5 -> 2
A39: 28 | B39: Add to Cart | C39: ='Add to Cart'!A5 -> 5 | D39: ='Add to Cart'!C5 -> 0 | E39: ='Add to Cart'!F5 -> 0 | F39: ='Add to Cart'!L5 -> 0 | G39: ='Add to Cart'!M5 -> 0 | H39: ='Add to Cart'!N5 -> 0 | I39: ='Add to Cart'!O5 -> 5
A40: 29 | B40: Remove from Cart | C40: ='Remove from Cart'!A5 -> 3 | D40: ='Remove from Cart'!C5 -> 0 | E40: ='Remove from Cart'!F5 -> 0 | F40: ='Remove from Cart'!L5 -> 3 | G40: ='Remove from Cart'!M5 -> 0 | H40: ='Remove from Cart'!N5 -> 0 | I40: ='Remove from Cart'!O5 -> 3
A41: 30 | B41: View Cart | C41: ='View Cart'!A5 -> 2 | D41: ='View Cart'!C5 -> 0 | E41: ='View Cart'!F5 -> 0 | F41: ='View Cart'!L5 -> 2 | G41: ='View Cart'!M5 -> 0 | H41: ='View Cart'!N5 -> 0 | I41: ='View Cart'!O5 -> 2
A42: 31 | B42: View Home Page | C42: ='View Home Page'!A5 -> 8 | D42: ='View Home Page'!C5 -> 0 | E42: ='View Home Page'!F5 -> 0 | F42: ='View Home Page'!L5 -> 8 | G42: ='View Home Page'!M5 -> 0 | H42: ='View Home Page'!N5 -> 0 | I42: ='View Home Page'!O5 -> 8
A43: 32 | B43: Filter Product by Category | C43: ='Filter Product by Category'!A5 -> 3 | D43: ='Filter Product by Category'!C5 -> 0 | E43: ='Filter Product by Category'!F5 -> 0 | F43: ='Filter Product by Category'!L5 -> 3 | G43: ='Filter Product by Category'!M5 -> 0 | H43: ='Filter Product by Category'!N5 -> 0 | I43: ='Filter Product by Category'!O5 -> 3
A44: 33 | B44: Get location from google Map | C44: ='Get location from google Map'!A5 -> 1 | D44: ='Get location from google Map'!C5 -> 0 | E44: ='Get location from google Map'!F5 -> 0 | F44: ='Get location from google Map'!L5 -> 1 | G44: ='Get location from google Map'!M5 -> 0 | H44: ='Get location from google Map'!N5 -> 0 | I44: ='Get location from google Map'!O5 -> 1
A45: 34 | B45: Auto count Rating for Shop | C45: ='Auto count Rating for Shop'!A5 -> 2 | D45: ='Auto count Rating for Shop'!C5 -> 0 | E45: ='Auto count Rating for Shop'!F5 -> 0 | F45: ='Auto count Rating for Shop'!L5 -> 2 | G45: ='Auto count Rating for Shop'!M5 -> 0 | H45: ='Auto count Rating for Shop'!N5 -> 0 | I45: ='Auto count Rating for Shop'!O5 -> 2
A46: 35 | B46: Recommend food by type for customer | C46: ='Recommend food by type for cust'!A5 -> 0 | D46: ='Recommend food by type for cust'!C5 -> 0 | E46: ='Recommend food by type for cust'!F5 -> 0 | F46: ='Recommend food by type for cust'!L5 -> 0 | G46: ='Recommend food by type for cust'!M5 -> 0 | H46: ='Recommend food by type for cust'!N5 -> 0 | I46: ='Recommend food by type for cust'!O5 -> 0
A47: 36 | B47: Register Shop | C47: ='Register Shop'!A5 -> 10 | D47: ='Register Shop'!C5 -> 0 | E47: ='Register Shop'!F5 -> 0 | F47: ='Register Shop'!L5 -> 1 | G47: ='Register Shop'!M5 -> 8 | H47: ='Register Shop'!N5 -> 1 | I47: ='Register Shop'!O5 -> 10
A48: 37 | B48: Edit Shop Detail | C48: ='Edit Shop Detail'!A5 -> 4 | D48: ='View Shop Dashboard'!C5 -> 0 | E48: ='View Shop Dashboard'!F5 -> 0 | F48: ='Edit Shop Detail'!L5 -> 1 | G48: ='Edit Shop Detail'!M5 -> 3 | H48: ='Edit Shop Detail'!N5 -> 0 | I48: ='Edit Shop Detail'!O5 -> 4
A49: 38 | B49: View Shop Dashboard | C49: ='View Shop Dashboard'!A5 -> 19 | D49: ='View Shop Dashboard'!C5 -> 0 | E49: ='View Shop Dashboard'!F5 -> 0 | F49: ='View Shop Dashboard'!L5 -> 13 | G49: ='View Shop Dashboard'!M5 -> 6 | H49: ='View Shop Dashboard'!N5 -> 0 | I49: ='View Shop Dashboard'!O5 -> 19
A50: 39 | B50: View Shop's revenue | C50: ='View Shops revenue'!A5 -> 15 | D50: ='View Shops revenue'!C5 -> 0 | E50: ='View Shops revenue'!F5 -> 0 | F50: ='View Shops revenue'!L5 -> 9 | G50: ='View Shops revenue'!M5 -> 6 | H50: ='View Shops revenue'!N5 -> 0 | I50: ='View Shops revenue'!O5 -> 15
A51: 40 | B51: Shipper Register | C51: ='Shipper Register'!A5 -> 9 | D51: ='Shipper Register'!C5 -> 0 | E51: ='Shipper Register'!F5 -> 0 | F51: ='Shipper Register'!L5 -> 9 | G51: ='Shipper Register'!M5 -> 0 | H51: ='Shipper Register'!N5 -> 0 | I51: ='Shipper Register'!O5 -> 9
A52: 41 | B52: Activate/Deactivate Shipper | C52: ='ActivateDeactivate Shipper'!A5 -> 6 | D52: ='ActivateDeactivate Shipper'!C5 -> 0 | E52: ='ActivateDeactivate Shipper'!F5 -> 0 | F52: ='ActivateDeactivate Shipper'!L5 -> 4 | G52: ='ActivateDeactivate Shipper'!M5 -> 1 | H52: ='ActivateDeactivate Shipper'!N5 -> 1 | I52: ='ActivateDeactivate Shipper'!O5 -> 6
A53: 42 | B53: Approve/Reject shop register | C53: ='ApproveReject shop register'!A5 -> 5 | D53: ='ApproveReject shop register'!C5 -> 0 | E53: ='ApproveReject shop register'!F5 -> 0 | F53: ='ApproveReject shop register'!L5 -> 4 | G53: ='ApproveReject shop register'!M5 -> 1 | H53: ='ApproveReject shop register'!N5 -> 0 | I53: ='ApproveReject shop register'!O5 -> 5
A54: 43 | B54: Approve/Reject Shipper register | C54: ='ApproveReject Shipper register'!A5 -> 7 | D54: ='ApproveReject Shipper register'!C5 -> 0 | E54: ='ApproveReject Shipper register'!F5 -> 0 | F54: ='ApproveReject Shipper register'!L5 -> 1 | G54: ='ApproveReject Shipper register'!M5 -> 6 | H54: ='ApproveReject Shipper register'!N5 -> 0 | I54: ='ApproveReject Shipper register'!O5 -> 7
A55: 44 | B55: Config Food category | C55: ='Config Food category'!A5 -> 8 | D55: ='Config Food category'!C5 -> 0 | E55: ='Config Food category'!F5 -> 0 | F55: ='Config Food category'!L5 -> 4 | G55: ='Config Food category'!M5 -> 4 | H55: ='Config Food category'!N5 -> 0 | I55: ='Config Food category'!O5 -> 8
A56: 45 | B56: Config Application banner | C56: ='Config Application banner'!A5 -> 6 | D56: ='Config Application banner'!C5 -> 0 | E56: ='Config Application banner'!F5 -> 0 | F56: ='Config Application banner'!L5 -> 2 | G56: ='Config Application banner'!M5 -> 4 | H56: ='Config Application banner'!N5 -> 0 | I56: ='Config Application banner'!O5 -> 6
A57: 46 | B57: Config Payment method | C57: ='Config Payment method'!A5 -> 7 | D57: ='Config Payment method'!C5 -> 0 | E57: ='Config Payment method'!F5 -> 0 | F57: ='Config Payment method'!L5 -> 4 | G57: ='Config Payment method'!M5 -> 3 | H57: ='Config Payment method'!N5 -> 0 | I57: ='Config Payment method'!O5 -> 7
A58: 47 | B58: Config Shipping method | C58: ='Config Shipping method'!A5 -> 7 | D58: ='Config Shipping method'!C5 -> 0 | E58: ='Config Shipping method'!F5 -> 0 | F58: ='Config Shipping method'!L5 -> 4 | G58: ='Config Shipping method'!M5 -> 3 | H58: ='Config Shipping method'!N5 -> 0 | I58: ='Config Shipping method'!O5 -> 7
A59: 48 | B59: View Operator dashboard | C59: ='View Operator dashboard'!A5 -> 30 | D59: ='View Operator dashboard'!C5 -> 0 | E59: ='View Operator dashboard'!F5 -> 0 | F59: ='View Operator dashboard'!L5 -> 25 | G59: ='View Operator dashboard'!M5 -> 5 | H59: ='View Operator dashboard'!N5 -> 0 | I59: ='View Operator dashboard'!O5 -> 30
A60: 49 | B60: Search using sematic for product | C60: ='Search using sematic for produc'!A5 -> 2 | D60: ='Search using sematic for produc'!C5 -> 0 | E60: ='Search using sematic for produc'!F5 -> 0 | F60: ='Search using sematic for produc'!L5 -> 2 | G60: ='Search using sematic for produc'!M5 -> 0 | H60: ='Search using sematic for produc'!N5 -> 0 | I60: ='Search using sematic for produc'!O5 -> 2
A61: 50 | B61: Search using elastic for product | C61: ='Search using elastic for produc'!A5 -> 1 | D61: ='Search using elastic for produc'!C5 -> 0 | E61: ='Search using elastic for produc'!F5 -> 0 | F61: ='Search using elastic for produc'!L5 -> 1 | G61: ='Search using elastic for produc'!M5 -> 0 | H61: ='Search using elastic for produc'!N5 -> 0 | I61: ='Search using elastic for produc'!O5 -> 1
A62: 51 | B62: Report Shop | C62: ='Report Shop'!A5 -> 7 | D62: ='Report Shop'!C5 -> 0 | E62: ='Report Shop'!F5 -> 0 | F62: ='Report Shop'!L5 -> 6 | G62: ='Report Shop'!M5 -> 1 | H62: ='Report Shop'!N5 -> 0 | I62: ='Report Shop'!O5 -> 7
A63: 52 | B63: Report Product | C63: ='Report Product'!A5 -> 7 | D63: ='Report Product'!C5 -> 0 | E63: ='Report Product'!F5 -> 0 | F63: ='Report Product'!L5 -> 6 | G63: ='Report Product'!M5 -> 1 | H63: ='Report Product'!N5 -> 0 | I63: ='Report Product'!O5 -> 7
A64: 53 | B64: Report Blog | C64: ='Report Blog'!A5 -> 7 | D64: ='Report Blog'!C5 -> 0 | E64: ='Report Blog'!F5 -> 0 | F64: ='Report Blog'!L5 -> 6 | G64: ='Report Blog'!M5 -> 1 | H64: ='Report Blog'!N5 -> 0 | I64: ='Report Blog'!O5 -> 7
A65: 54 | B65: View Shop Reports(Shopkeeper) | C65: ='View Shop Reports(Shopkeeper)'!A5 -> 8 | D65: ='View Shop Reports(Shopkeeper)'!C5 -> 0 | E65: ='View Shop Reports(Shopkeeper)'!F5 -> 0 | F65: ='View Shop Reports(Shopkeeper)'!L5 -> 2 | G65: ='View Shop Reports(Shopkeeper)'!M5 -> 6 | H65: ='View Shop Reports(Shopkeeper)'!N5 -> 0 | I65: ='View Shop Reports(Shopkeeper)'!O5 -> 8
A66: 55 | B66: View Shop Report Detail (Shopkeeper) | C66: ='View Shop Report Detail (Shopke'!A5 -> 5 | D66: ='View Shop Report Detail (Shopke'!C5 -> 0 | E66: ='View Shop Report Detail (Shopke'!F5 -> 0 | F66: ='View Shop Report Detail (Shopke'!L5 -> 2 | G66: ='View Shop Report Detail (Shopke'!M5 -> 3 | H66: ='View Shop Report Detail (Shopke'!N5 -> 0 | I66: ='View Shop Report Detail (Shopke'!O5 -> 5
A67: 56 | B67: View Blog Reports | C67: ='View Blog Reports'!A5 -> 2 | D67: ='View Blog Reports'!C5 -> 0 | E67: ='View Blog Reports'!F5 -> 0 | F67: ='View Blog Reports'!L5 -> 1 | G67: ='View Blog Reports'!M5 -> 1 | H67: ='View Blog Reports'!N5 -> 0 | I67: ='View Blog Reports'!O5 -> 2
A68: 57 | B68: View Blog Report Detail | C68: ='View Blog Report Detail'!A5 -> 2 | D68: ='View Blog Report Detail'!C5 -> 0 | E68: ='View Blog Report Detail'!F5 -> 0 | F68: ='View Blog Report Detail'!L5 -> 1 | G68: ='View Blog Report Detail'!M5 -> 1 | H68: ='View Blog Report Detail'!N5 -> 0 | I68: ='View Blog Report Detail'!O5 -> 2
A69: 58 | B69: View feedback list | C69: ='View feedback list'!A5 -> 3 | D69: ='View feedback list'!C5 -> 0 | E69: ='View feedback list'!F5 -> 0 | F69: ='View feedback list'!L5 -> 1 | G69: ='View feedback list'!M5 -> 2 | H69: ='View feedback list'!N5 -> 0 | I69: ='View feedback list'!O5 -> 3
A70: 59 | B70: Delete feedback | C70: ='Delete feedback'!A5 -> 4 | D70: ='Delete feedback'!C5 -> 0 | E70: ='Delete feedback'!F5 -> 0 | F70: ='Delete feedback'!L5 -> 3 | G70: ='Delete feedback'!M5 -> 1 | H70: ='Delete feedback'!N5 -> 0 | I70: ='Delete feedback'!O5 -> 4
A71: 60 | B71: Submit Feedback | C71: ='Submit Feedback '!A5 -> 9 | D71: ='Submit Feedback '!C5 -> 0 | E71: ='Submit Feedback '!F5 -> 0 | F71: ='Submit Feedback '!L5 -> 6 | G71: ='Submit Feedback '!M5 -> 2 | H71: ='Submit Feedback '!N5 -> 1 | I71: ='Submit Feedback '!O5 -> 9
A72: 61 | B72: View Order List (Customer) | C72: ='View Order List (Customer)'!A5 -> 3 | D72: ='View Order List (Customer)'!C5 -> 0 | E72: ='View Order List (Customer)'!F5 -> 0 | F72: ='View Order List (Customer)'!L5 -> 2 | G72: ='View Order List (Customer)'!M5 -> 1 | H72: ='View Order List (Customer)'!N5 -> 0 | I72: ='View Order List (Customer)'!O5 -> 3
A73: 62 | B73: View Order Detail(Customer) | C73: ='View Order Detail(Customer)'!A5 -> 2 | D73: ='View Order Detail(Customer)'!C5 -> 0 | E73: ='View Order Detail(Customer)'!F5 -> 0 | F73: ='View Order Detail(Customer)'!L5 -> 1 | G73: ='View Order Detail(Customer)'!M5 -> 1 | H73: ='View Order Detail(Customer)'!N5 -> 0 | I73: ='View Order Detail(Customer)'!O5 -> 2
A74: 63 | B74: Cancel Order (Customer) | C74: ='Cancel Order (Customer)'!A5 -> 4 | D74: ='Cancel Order (Customer)'!C5 -> 0 | E74: ='Cancel Order (Customer)'!F5 -> 0 | F74: ='Cancel Order (Customer)'!L5 -> 3 | G74: ='Cancel Order (Customer)'!M5 -> 1 | H74: ='Cancel Order (Customer)'!N5 -> 0 | I74: ='Cancel Order (Customer)'!O5 -> 4
A75: 64 | B75: Request Order return | C75: ='Request Order return'!A5 -> 3 | D75: ='Request Order return'!C5 -> 0 | E75: ='Request Order return'!F5 -> 0 | F75: ='Request Order return'!L5 -> 1 | G75: ='Request Order return'!M5 -> 2 | H75: ='Request Order return'!N5 -> 0 | I75: ='Request Order return'!O5 -> 3
A76: 65 | B76: View Order List (Shopkeeper) | C76: ='View Order List (Shopkeeper)'!A5 -> 11 | D76: ='View Order List (Shopkeeper)'!C5 -> 0 | E76: ='View Order List (Shopkeeper)'!F5 -> 0 | F76: ='View Order List (Shopkeeper)'!L5 -> 10 | G76: ='View Order List (Shopkeeper)'!M5 -> 1 | H76: ='View Order List (Shopkeeper)'!N5 -> 0 | I76: ='View Order List (Shopkeeper)'!O5 -> 11
A77: 66 | B77: Accept Order | C77: ='Accept Order'!A5 -> 2 | D77: ='Accept Order'!C5 -> 0 | E77: ='Accept Order'!F5 -> 0 | F77: ='Accept Order'!L5 -> 1 | G77: ='Accept Order'!M5 -> 1 | H77: ='Accept Order'!N5 -> 0 | I77: ='Accept Order'!O5 -> 2
A78: 67 | B78: Reject Order | C78: ='Reject Order'!A5 -> 2 | D78: ='View Order List (Shopkeeper)'!C5 -> 0 | E78: ='Reject Order'!F5 -> 0 | F78: ='Reject Order'!L5 -> 1 | G78: ='Reject Order'!M5 -> 1 | H78: ='Reject Order'!N5 -> 0 | I78: ='Reject Order'!O5 -> 2
A79: 68 | B79: Change Order Status (Shopkeeper) | C79: ='Change Order Status (Shopkeeper'!A5 -> 3 | D79: ='Reject Order'!C5 -> 0 | E79: ='Change Order Status (Shopkeeper'!F5 -> 0 | F79: ='Change Order Status (Shopkeeper'!L5 -> 1 | G79: ='Change Order Status (Shopkeeper'!M5 -> 2 | H79: ='Change Order Status (Shopkeeper'!N5 -> 0 | I79: ='Change Order Status (Shopkeeper'!O5 -> 3
A80: 69 | B80: Resolve Order Return Request | C80: ='Resolve Order Return Request'!A5 -> 15 | D80: ='View Order List (Shopkeeper)'!C5 -> 0 | E80: ='Resolve Order Return Request'!F5 -> 0 | F80: ='Resolve Order Return Request'!L5 -> 11 | G80: ='Resolve Order Return Request'!M5 -> 3 | H80: ='Resolve Order Return Request'!N5 -> 1 | I80: ='Resolve Order Return Request'!O5 -> 15
A81: 70 | B81: View Order Detail (Shipper) | C81: ='View Order Detail (Shipper)'!A5 -> 4 | D81: ='View Order Detail (Shipper)'!C5 -> 0 | E81: ='View Order Detail (Shipper)'!F5 -> 0 | F81: ='View Order Detail (Shipper)'!L5 -> 3 | G81: ='View Order Detail (Shipper)'!M5 -> 1 | H81: ='View Order Detail (Shipper)'!N5 -> 0 | I81: ='View Order Detail (Shipper)'!O5 -> 4
A82: 71 | B82: Change Order Status (Shipper) | C82: ='Change Order Status (Shipper)'!A5 -> 4 | D82: ='Change Order Status (Shipper)'!C5 -> 0 | E82: ='Change Order Status (Shipper)'!F5 -> 0 | F82: ='Change Order Status (Shipper)'!L5 -> 1 | G82: ='Change Order Status (Shipper)'!M5 -> 3 | H82: ='Change Order Status (Shipper)'!N5 -> 0 | I82: ='Change Order Status (Shipper)'!O5 -> 4
A83: 72 | B83: Confirm Order Receive(Customer) | C83: ='Confirm Order Receive(Customer)'!A5 -> 3 | D83: ='Confirm Order Receive(Customer)'!C5 -> 0 | E83: ='Confirm Order Receive(Customer)'!F5 -> 0 | F83: ='Confirm Order Receive(Customer)'!L5 -> 1 | G83: ='Confirm Order Receive(Customer)'!M5 -> 2 | H83: ='Confirm Order Receive(Customer)'!N5 -> 0 | I83: ='Confirm Order Receive(Customer)'!O5 -> 3
A84: 73 | B84: Check Out | C84: ='Check Out'!A5 -> 5 | D84: ='Check Out'!C5 -> 0 | E84: ='Check Out'!F5 -> 0 | F84: ='Check Out'!L5 -> 2 | G84: ='Check Out'!M5 -> 2 | H84: ='Check Out'!N5 -> 1 | I84: ='Check Out'!O5 -> 5
A85: 74 | B85: Choose Payment Method | C85: ='Choose Payment Method'!A5 -> 3 | D85: ='Choose Payment Method'!C5 -> 0 | E85: ='Choose Payment Method'!F5 -> 0 | F85: ='Choose Payment Method'!L5 -> 1 | G85: ='Choose Payment Method'!M5 -> 2 | H85: ='Choose Payment Method'!N5 -> 0 | I85: ='Choose Payment Method'!O5 -> 3
A86: 75 | B86: Choose Shipping Method | C86: ='Choose Shipping Method'!A5 -> 3 | D86: ='Choose Shipping Method'!C5 -> 0 | E86: ='Choose Shipping Method'!F5 -> 0 | F86: ='Choose Shipping Method'!L5 -> 1 | G86: ='Choose Shipping Method'!M5 -> 2 | H86: ='Choose Shipping Method'!N5 -> 0 | I86: ='Choose Shipping Method'!O5 -> 3
A87: 76 | B87: View voucher List | C87: ='View Voucher List'!A5 -> 3 | D87: ='View Voucher List'!C5 -> 0 | E87: ='View Voucher List'!F5 -> 0 | F87: ='View Voucher List'!L5 -> 2 | G87: ='View Voucher List'!M5 -> 1 | H87: ='View Voucher List'!N5 -> 0 | I87: ='View Voucher List'!O5 -> 3
A88: 77 | B88: Create Voucher | C88: ='Create Voucher'!A5 -> 10 | D88: ='Create Voucher'!C5 -> 0 | E88: ='Create Voucher'!F5 -> 0 | F88: ='Create Voucher'!L5 -> 1 | G88: ='Create Voucher'!M5 -> 3 | H88: ='Create Voucher'!N5 -> 6 | I88: ='Create Voucher'!O5 -> 10
A89: 78 | B89: Apply Voucher | C89: ='Apply Voucher'!A5 -> 6 | D89: ='Apply Voucher'!C5 -> 0 | E89: ='Apply Voucher'!F5 -> 0 | F89: ='Apply Voucher'!L5 -> 1 | G89: ='Apply Voucher'!M5 -> 2 | H89: ='Apply Voucher'!N5 -> 3 | I89: ='Apply Voucher'!O5 -> 6
A90: 79 | B90: Disable Voucher | C90: ='Disable Voucher'!A5 -> 2 | D90: ='Disable Voucher'!C5 -> 0 | E90: ='Disable Voucher'!F5 -> 0 | F90: ='Disable Voucher'!L5 -> 1 | G90: ='Disable Voucher'!M5 -> 1 | H90: ='Disable Voucher'!N5 -> 0 | I90: ='Disable Voucher'!O5 -> 2
A91: 80 | B91: View Discount List | C91: ='View Discount List'!A5 -> 2 | D91: ='View Discount List'!C5 -> 0 | E91: ='View Discount List'!F5 -> 0 | F91: ='View Discount List'!L5 -> 1 | G91: ='View Discount List'!M5 -> 1 | H91: ='View Discount List'!N5 -> 0 | I91: ='View Discount List'!O5 -> 2
A92: 81 | B92: Create Discount | C92: ='Create Discount'!A5 -> 7 | D92: ='Create Discount'!C5 -> 0 | E92: ='Create Discount'!F5 -> 0 | F92: ='Create Discount'!L5 -> 1 | G92: ='Create Discount'!M5 -> 5 | H92: ='Create Discount'!N5 -> 1 | I92: ='Create Discount'!O5 -> 7
A93: 82 | B93: Disable Discount | C93: ='Disable Discount'!A5 -> 2 | D93: ='Disable Discount'!C5 -> 0 | E93: ='Disable Discount'!F5 -> 0 | F93: ='Disable Discount'!L5 -> 1 | G93: ='Disable Discount'!M5 -> 1 | H93: ='Disable Discount'!N5 -> 0 | I93: ='Disable Discount'!O5 -> 2
B94: Sub total | C94: =SUM(C10:C93) -> 427 | D94: =SUM(D10:D93) -> 0 | E94: =SUM(E10:E31) -> 0 | F94: =SUM(F10:F93) -> 231 | G94: =SUM(G10:G93) -> 160 | H94: =SUM(H10:H93) -> 21 | I94: =SUM(I10:I93) -> 427
B96: Test coverage | D96: =(C94+D94)*100/(I94) -> 100 | E96: %
B97: Test successful coverage | D97: =C94*100/(I94) -> 100 | E97: %
B98: Normal case | D98: =F94*100/I94 -> 54.098361 | E98: %
B99: Abnormal case | D99: =G94*100/I94 -> 37.470726 | E99: %
B100: Boundary case | D100: =H94*100/I94 -> 4.9180328 | E100: %

Sheet Register
A1: Code Module | C1: Register | F1: Method | L1: Register
A2: Created By | C2: AnhDQ | F2: Executed By | L2: AnhDQ
A3: Test requirement
A4: Passed | C4: Failed | F4: Untested | L4: N/A/B | O4: Total Test Cases
A5: =COUNTIF(F44:HQ44,"P") -> 18 | C5: =COUNTIF(F44:HQ44,"F") -> 0 | F5: =SUM(O5,-A5,-C5) -> 0 | L5: =COUNTIF(E43:HQ43,"N") -> 1 | M5: =COUNTIF(E43:HQ43,"A") -> 17 | N5: =COUNTIF(E43:HQ43,"B") -> 0 | O5: =COUNTA(E7:HT7) -> 18
F7: UTCID01 | G7: UTCID02 | H7: UTCID03 | I7: UTCID04 | J7: UTCID05 | K7: UTCID06 | L7: UTCID07 | M7: UTCID08 | N7: UTCID09 | O7: UTCID10 | P7: UTCID11 | Q7: UTCID12 | R7: UTCID13 | S7: UTCID14 | T7: UTCID15 | U7: UTCID16 | V7: UTCID17 | W7: UTCID18
A8: Condition | B8: Precondition
D9: Format password, email, phone number when entering
D10: Trong db có tồn tại số điện thoại 0234789156 và email abc@gmail.com
D11: Định dạng mật khẩu:ít nhất 8 kí tự, gồm 1 chữ hoa, 1 chữ số, 1 kí tự đặc biệt
D12: Số điện thoại phải có 10 chữ số và bắt đầu với số 0
B13: Phone
D14: 01327312983123 | F14: O | G14: O | H14: O | I14: O | J14: O | K14: O
D15: 0586619797 | L15: O | M15: O | N15: O | O15: O | P15: O | Q15: O
D16: 0234789156 | R16: O | S16: O | T16: O | U16: O | V16: O | W16: O
B17: Email
D18: abc@gmail.com | F18: O | I18: O | L18: O | O18: O | R18: O | U18: O
D19: ádasda | G19: O | J19: O | M19: O | P19: O | S19: O | V19: O
D20: anhdqhe170071@gmail.com | H20: O | K20: O | N20: O | Q20: O | T20: O | W20: O
B21: Password
D22: 123456 | F22: O | G22: O | H22: O | L22: O | M22: O | N22: O | R22: O | S22: O | T22: O
D23: Abc1234@ | I23: O | J23: O | K23: O | O23: O | P23: O | Q23: O | U23: O | V23: O | W23: O
A31: Confirm | B31: Return
D32: Đăng kí thành công | Q32: O
D33: Hiển thị thông báo lỗi | F33: O | G33: O | H33: O | I33: O | J33: O | K33: O | L33: O | M33: O | N33: O | O33: O | P33: O | R33: O | S33: O | T33: O | U33: O | V33: O | W33: O
B35: Exception
B37: Log message
D38: Sai định dạng nhập vào | F38: O | G38: O | H38: O | I38: O | J38: O | K38: O | L38: O | M38: O | N38: O | P38: O | R38: O | S38: O | T38: O | U38: O | V38: O
D39: Số điện thoại đã tồn tại | R39: O | S39: O | T39: O | U39: O | V39: O | W39: O
D40: Email đã tồn tại | F40: O | I40: O | L40: O | O40: O | R40: O | U40: O
D41: Đăng kí thành công | Q41: O
A43: Result | B43: Type(N : Normal, A : Abnormal, B : Boundary) | F43: A | G43: A | H43: A | I43: A | J43: A | K43: A | L43: A | M43: A | N43: A | O43: A | P43: A | Q43: N | R43: A | S43: A | T43: A | U43: A | V43: A | W43: A
B44: Passed/Failed | F44: P | G44: P | H44: P | I44: P | J44: P | K44: P | L44: P | M44: P | N44: P | O44: P | P44: P | Q44: P | R44: P | S44: P | T44: P | U44: P | V44: P | W44: P
B45: Executed Date | F45: 45724 | G45: 45724 | H45: 45724 | I45: 45724 | J45: 45724 | K45: 45724 | L45: 45724 | M45: 45724 | N45: 45724 | O45: 45724 | P45: 45724 | Q45: 45724 | R45: 45724 | S45: 45724 | T45: 45724 | U45: 45724 | V45: 45724 | W45: 45724
B46: Defect ID

Sheet AddBlog
A1: Code Module | C1: Blog Management | F1: Method | L1: AddBlogPost
A2: Created By | C2: AnhDQ | F2: Executed By | L2: AnhDQ
A3: Test requirement
A4: Passed | C4: Failed | F4: Untested | L4: N/A/B | O4: Total Test Cases
A5: =COUNTIF(F44:HQ44,"P") -> 3 | C5: =COUNTIF(F45:HQ45,"F") -> 0 | F5: =SUM(O5,-A5,-C5) -> 0 | L5: =COUNTIF(E43:HQ43,"N") -> 2 | M5: =COUNTIF(E43:HQ43,"A") -> 1 | N5: =COUNTIF(E43:HQ43,"B") -> 0 | O5: =COUNTA(E7:HT7) -> 3
F7: UTCID01 | G7: UTCID02 | H7: UTCID03
A8: Condition | B8: Precondition
D9: Logged into the system
B12: Content
D13: null | F13: O | H13: O
D14: "Cửa hàng này bán bún rất ngon" | G14: O
B15: Image
D16: null | F16: O | G16: O
D17: img1.jpg | H17: O
A31: Confirm | B31: Return
D32: Đăng bài thành công | G32: O | H32: O
D33: Lỗi khi đăng bài | F33: O
B38: Exception
B40: Log message
D41: Không thể bỏ trống cả nội dung và ảnh | F41: O
D42: Đăng bài thành công | G42: O | H42: O
A43: Result | B43: Type(N : Normal, A : Abnormal, B : Boundary) | F43: A | G43: N | H43: N
B44: Passed/Failed | F44: P | G44: P | H44: P
B45: Executed Date | F45: 45724 | G45: 45724 | H45: 45724
B46: Defect ID

Sheet Login
A1: Code Module | C1: Account Management | F1: Method | L1: Login
A2: Created By | C2: AnhDQ | F2: Executed By | L2: AnhDQ
A3: Test requirement
A4: Passed | C4: Failed | F4: Untested | L4: N/A/B | O4: Total Test Cases
A5: =COUNTIF(F39:HQ39,"P") -> 4 | C5: =COUNTIF(F39:HQ39,"F") -> 0 | F5: =SUM(O5,-A5,-C5) -> 0 | L5: =COUNTIF(E38:HQ38,"N") -> 1 | M5: =COUNTIF(E38:HQ38,"A") -> 3 | N5: =COUNTIF(E38:HQ38,"B") -> 0 | O5: =COUNTA(E7:HT7) -> 4
F7: UTCID01 | G7: UTCID02 | H7: UTCID03 | I7: UTCID04
A8: Condition | B8: Precondition
B9: Already have an account in the system database
D11: Phone:0586619796
D12: Password:Abc1234@
B13: Phone number
D14: 0586619796 | F14: O | H14: O
D15: 0123456789 | G15: O | I15: O
B16: Password
D17: Abc1234@ | F17: O | G17: O | W17: O
D18: 123456 | H18: O | I18: O
A27: Confirm | B27: Return
D28: Chuỗi JWT | F28: O
D29: Thông báo lỗi | G29: O | H29: O | I29: O
B33: Exception
B35: Log message
D36: Đăng nhập thành công
D37: Bad Credential
A38: Result | B38: Type(N : Normal, A : Abnormal, B : Boundary) | F38: N | G38: A | H38: A | I38: A
B39: Passed/Failed | F39: P | G39: P | H39: P | I39: P
B40: Executed Date | F40: 45724 | G40: 45724 | H40: 45724 | I40: 45724 | J40: 45724 | K40: 45724 | L40: 45724 | M40: 45724 | N40: 45724 | O40: 45724 | P40: 45724 | Q40: 45724 | R40: 45724 | S40: 45724 | T40: 45724
B41: Defect ID

Sheet Logout
A1: Code Module | C1: Account Management | F1: Method | L1: Logout
A2: Created By | C2: AnhDQ | F2: Executed By | L2: AnhDQ
A3: Test requirement
A4: Passed | C4: Failed | F4: Untested | L4: N/A/B | O4: Total Test Cases
A5: =COUNTIF(F39:HQ39,"P") -> 1 | C5: =COUNTIF(F39:HQ39,"F") -> 0 | F5: =SUM(O5,-A5,-C5) -> 0 | L5: =COUNTIF(E38:HQ38,"N") -> 1 | M5: =COUNTIF(E38:HQ38,"A") -> 0 | N5: =COUNTIF(E38:HQ38,"B") -> 0 | O5: =COUNTA(E7:HT7) -> 1
F7: UTCID01
A8: Condition | B8: Precondition
D9: Logged into the system
D10: Can connect with server
B13: Action
D14: Người dùng ấn vào đăng xuất | F14: O
A30: Confirm | B30: Return
D31: Chuyển về màn đăng nhập | F31: O
B33: Exception
B35: Log message
D36: Đăng xuất thành công
A38: Result | B38: Type(N : Normal, A : Abnormal, B : Boundary) | F38: N
B39: Passed/Failed | F39: P
B40: Executed Date | F40: 45724
B41: Defect ID

Sheet ViewProfile
A1: Code Module | C1: Account Management | F1: Method | L1: View profile
A2: Created By | C2: AnhDQ | F2: Executed By | L2: AnhDQ
A3: Test requirement | C3: <Brief description about requirements which are tested in this function>
A4: Passed | C4: Failed | F4: Untested | L4: N/A/B | O4: Total Test Cases
A5: =COUNTIF(F40:HQ40,"P") -> 2 | C5: =COUNTIF(F41:HQ41,"F") -> 0 | F5: =SUM(O5,-A5,-C5) -> 0 | L5: =COUNTIF(E39:HQ39,"N") -> 1 | M5: =COUNTIF(E39:HQ39,"A") -> 1 | N5: =COUNTIF(E39:HQ39,"B") -> 0 | O5: =COUNTA(E7:HT7) -> 2
F7: UTCID01 | G7: UTCID02
A8: Condition | B8: Precondition
D9: Logged into the system
B12: UserId
D13: 1 | F13: O
D14: null | G14: O
A29: Confirm | B29: Return
D30: View Profile | F30: O
D31: Lỗi khi view Profile | G31: O
B32: Exception
B34: Log message
D35: User Not Found | G35: O
A39: Result | B39: Type(N : Normal, A : Abnormal, B : Boundary) | F39: N | G39: A
B40: Passed/Failed | F40: P | G40: P
B41: Executed Date | F41: 45724 | G41: 45724 | H41: 45724 | I41: 45724 | J41: 45724 | K41: 45724 | L41: 45724
B42: Defect ID

Sheet EditProfile
A1: Code Module | C1: Account Management | F1: Method | L1: EditProfile
A2: Created By | C2: AnhDQ | F2: Executed By | L2: AnhDQ
A3: Test requirement
A4: Passed | C4: Failed | F4: Untested | L4: N/A/B | O4: Total Test Cases
A5: =COUNTIF(F45:HQ45,"P") -> 6 | C5: =COUNTIF(F46:HQ46,"F") -> 0 | F5: =SUM(O5,-A5,-C5) -> 0 | L5: =COUNTIF(E44:HQ44,"N") -> 1 | M5: =COUNTIF(E44:HQ44,"A") -> 5 | N5: =COUNTIF(E45:HQ45,"B") -> 0 | O5: =COUNTA(E7:HT7) -> 6
F7: UTCID01 | G7: UTCID02 | H7: UTCID03 | I7: UTCID04 | J7: UTCID05 | K7: UTCID06
A8: Condition | B8: Precondition
D9: Logged into the system
D10: Valid userId:1,profileId:1
B12: UserId
D13: 1 | K13: O
D14: null | F14: O
B15: ProfileId
D16: 1 | K16: O
D17: null | G17: O
B18: Gender
D19: Male | K19: O
D20: null | J20: O
B21: Email
D22: abc | H22: O
D23: anhdqhe170071@gmail.com | K23: O
B24: Dob
D25: 45767 | I25: O
D26: 37700 | K26: O
A33: Confirm | B33: Return
D34: Success | K34: O
D35: Fail | F35: O | G35: O | H35: O | I35: O | J35: O
B36: Exception
B38: Log message
D39: Chỉnh sửa thành công | K39: O
D40: Lỗi khi đọc profile | F40: O | G40: O
D41: Gender không hợp lệ | J41: O
D42: Email không hợp lệ | H42: O
D43: Ngày sinh không hợp lệ | I43: O
A44: Result | B44: Type(N : Normal, A : Abnormal, B : Boundary) | F44: A | G44: A | H44: A | I44: A | J44: A | K44: N
B45: Passed/Failed | F45: P | G45: P | H45: P | I45: P | J45: P | K45: P
B46: Executed Date | F46: 45724 | G46: 45724 | H46: 45724 | I46: 45724 | J46: 45724 | K46: 45724
B47: Defect ID

Sheet ChangePassword
A1: Code Module | C1: Account Management | F1: Method | L1: ChangePassword
A2: Created By | C2: AnhDQ | F2: Executed By | L2: AnhDQ
A3: Test requirement
A4: Passed | C4: Failed | F4: Untested | L4: N/A/B | O4: Total Test Cases
A5: =COUNTIF(F33:HQ33,"P") -> 4 | C5: =COUNTIF(F34:HQ34,"F") -> 0 | F5: =SUM(O5,-A5,-C5) -> 0 | L5: =COUNTIF(E32:HQ32,"N") -> 1 | M5: =COUNTIF(E32:HQ32,"A") -> 3 | N5: =COUNTIF(E33:HQ33,"B") -> 0 | O5: =COUNTA(E7:HT7) -> 4
F7: UTCID01 | G7: UTCID02 | H7: UTCID03 | I7: UTCID04
A8: Condition | B8: Precondition
D9: Logged into the system
D10: Current password:Abc1234@
B11: Old Password
D12: Abc1234@ | I12: O
D13: 12345678 | F13: O
B14: New Password
D15: 123456 | G15: O
D16: CDE1234@ | H16: O | I16: O
B17: Confirm password
D18: CDE1234@ | I18: O
D19: 123214 | G19: O | H19: O
A21: Confirm | B21: Return
D22: Đổi mật khẩu thành công
D23: Hiển thị thông báo lỗi | F23: O
B25: Exception
B27: Log message
D28: Mật khẩu mới không đúng định dạng | G28: O
D29: Mật khẩu không trùng | H29: O
D30: Đổi mật khẩu thành công | I30: O
D31: Sai mật khẩu cũ | F31: O
A32: Result | B32: Type(N : Normal, A : Abnormal, B : Boundary) | F32: A | G32: A | H32: A | I32: N
B33: Passed/Failed | F33: P | G33: P | H33: P | I33: P
B34: Executed Date | F34: 45724 | G34: 45724 | H34: 45724 | I34: 45724
B35: Defect ID

Sheet Forgotpassword
A1: Code Module | C1: Account Management | F1: Method | L1: ForgotPassword
A2: Created By | C2: AnhDQ | F2: Executed By | L2: AnhDQ
A3: Test requirement
A4: Passed | C4: Failed | F4: Untested | L4: N/A/B | O4: Total Test Cases
A5: =COUNTIF(F37:HT37,"P") -> 4 | C5: =COUNTIF(F38:HT38,"F") -> 0 | F5: =SUM(O5,-A5,-C5) -> 0 | L5: =COUNTIF(E36:HT36,"N") -> 1 | M5: =COUNTIF(E36:HT36,"A") -> 3 | N5: =COUNTIF(E37:HT37,"B") -> 0 | O5: =COUNTA(E7:HW7) -> 4
F7: UTCID01 | G7: UTCID02 | H7: UTCID03 | I7: UTCID04
A8: Condition | B8: Precondition
D9: Account must be registered with phone number in db
D10: Vào app nhưng chưa đăng nhập
D11: Mã OTP gửi về là 456789
D12: Định dạng mk :>=8 ký tự, phải chứa chữ hoa, số, kí tự đặc biệt
B13: Phone number
D14: 01234567896 | F14: O
D15: 0586619796 | G15: O | H15: O | I15: O
B16: New Password
D17: 123456 | G17: O
D18: CDE1234@ | H18: O | I18: O
B19: Confirm password
D20: CDE1234@ | G20: O | I20: O
D21: 123214 | H21: O
A26: Confirm | B26: Return
D27: Đổi mật khẩu thành công | I27: O
D28: Đổi mật khẩu thất bại | F28: O | G28: O | H28: O
B29: Exception
B31: Log message
D32: Mật khẩu mới không đúng định dạng | G32: O
D33: Mật khẩu không trùng | H33: O
D34: Không tìm thấy tài khoản | F34: O
D35: Đổi mật khẩu thành công | I35: O
A36: Result | B36: Type(N : Normal, A : Abnormal, B : Boundary) | F36: A | G36: A | H36: A | I36: N
B37: Passed/Failed | F37: P | G37: P | H37: P | I37: P
B38: Executed Date | F38: 45724 | G38: 45724 | H38: 45724 | I38: 45724
B39: Defect ID

Sheet ViewBlogList
A1: Code Module | C1: Blog Management | F1: Method | L1: View Blog List
A2: Created By | C2: AnhDQ | F2: Executed By | L2: AnhDQ
A3: Test requirement
A4: Passed | C4: Failed | F4: Untested | L4: N/A/B | O4: Total Test Cases
A5: =COUNTIF(F45:HQ45,"P") -> 2 | C5: =COUNTIF(F46:HQ46,"F") -> 0 | F5: =SUM(O5,-A5,-C5) -> 0 | L5: =COUNTIF(E44:HQ44,"N") -> 2 | M5: =COUNTIF(E45:HQ45,"A") -> 0 | N5: =COUNTIF(E45:HQ45,"B") -> 0 | O5: =COUNTA(E7:HT7) -> 2
F7: UTCID01 | G7: UTCID02
A8: Condition | B8: Precondition
D9: Logged into the system
D10: Đã đăng nhập thành công
D11: Không có Blog trong db | F11: O
D12: Có blog trong db | G12: O
A32: Confirm | B32: Return
D33: Danh sách các Blog có trên App | G33: O
D34: Null | F34: O
B39: Exception
B41: Log message
A44: Result | B44: Type(N : Normal, A : Abnormal, B : Boundary) | F44: N | G44: N
B45: Passed/Failed | F45: P | G45: P
B46: Executed Date | F46: 45724 | G46: 45724
B47: Defect ID

Sheet ViewBlogDetail
A1: Code Module | C1: Blog Management | F1: Method | L1: View Blog Detail
A2: Created By | C2: AnhDQ | F2: Executed By | L2: AnhDQ
A3: Test requirement
A4: Passed | C4: Failed | F4: Untested | L4: N/A/B | O4: Total Test Cases
A5: =COUNTIF(F45:HQ45,"P") -> 2 | C5: =COUNTIF(F46:HQ46,"F") -> 0 | F5: =SUM(O5,-A5,-C5) -> 0 | L5: =COUNTIF(E44:HQ44,"N") -> 1 | M5: =COUNTIF(E44:HQ44,"A") -> 1 | N5: =COUNTIF(E45:HQ45,"B") -> 0 | O5: =COUNTA(E7:HT7) -> 2
F7: UTCID01 | G7: UTCID02
A8: Condition | B8: Precondition
D9: Logged into the system
D10: Đã đăng nhập thành công
D11: Không có Blog trong db | F11: O
D12: Có blog trong db | G12: O
A32: Confirm | B32: Return
D33: BlogDetail | G33: O
D34: Không tìm thấy blog | F34: O
B39: Exception
B41: Log message
F42: O
A44: Result | B44: Type(N : Normal, A : Abnormal, B : Boundary) | F44: A | G44: N
B45: Passed/Failed | F45: P | G45: P
B46: Executed Date | F46: 45724 | G46: 45724
B47: Defect ID

Sheet EditBlog
A1: Code Module | C1: Blog Management | F1: Method | L1: EditBlog
A2: Created By | C2: AnhDQ | F2: Executed By | L2: AnhDQ
A3: Test requirement
A4: Passed | C4: Failed | F4: Untested | L4: N/A/B | O4: Total Test Cases
A5: =COUNTIF(F44:HQ44,"P") -> 4 | C5: =COUNTIF(F45:HQ45,"F") -> 0 | F5: =SUM(O5,-A5,-C5) -> 0 | L5: =COUNTIF(E43:HQ43,"N") -> 4 | M5: =COUNTIF(E44:HQ44,"A") -> 0 | N5: =COUNTIF(E44:HQ44,"B") -> 0 | O5: =COUNTA(E7:HT7) -> 4
F7: UTCID01 | G7: UTCID02 | H7: UTCID03 | I7: UTCID04
A8: Condition | B8: Precondition
D9: Logged in to the system, is the owner of at least 1 blog
B13: Content
D14: null | F14: O | G14: O
D15: "Cửa hàng này bán bún rất ngon" | H15: O | I15: O
B16: Image
D17: Không thêm ảnh mới | F17: O | H17: O
D18: img1.jpg | G18: O | I18: O
A31: Confirm | B31: Return
D32: Chỉnh sửa bài viết thành công | F32: O | G32: O | H32: O | I32: O
D33: Lỗi khi chỉnh sửa bài
B38: Exception
B40: Log message
D41: Chỉnh sửa bài thành công
A43: Result | B43: Type(N : Normal, A : Abnormal, B : Boundary) | F43: N | G43: N | H43: N | I43: N
B44: Passed/Failed | F44: P | G44: P | H44: P | I44: P
B45: Executed Date | F45: 45724 | G45: 45724 | H45: 45724 | I45: 45724
B46: Defect ID

Sheet CommentReplyonBlog
A1: Code Modulenưa | C1: Blog Management | F1: Method | L1: Comment/Reply on Blog
A2: Created By | C2: AnhDQ | F2: Executed By | L2: NguyenT
A3: Test requirement
A4: Passed | C4: Failed | F4: Untested | L4: N/A/B | O4: Total Test Cases
A5: =COUNTIF(F42:HQ42,"P") -> 8 | C5: =COUNTIF(F42:HQ42,"F") -> 0 | F5: =SUM(O5,-A5,-C5) -> 0 | L5: =COUNTIF(E41:HQ41,"N") -> 2 | M5: =COUNTIF(E41:HQ41,"A") -> 4 | N5: =COUNTIF(E41:HQ41,"B") -> 2 | O5: =COUNTA(E7:HT7) -> 8
F7: UTCID01 | G7: UTCID02 | H7: UTCID03 | I7: UTCID04 | J7: UTCID05 | K7: UTCID06 | L7: UTCID07 | M7: UTCID08
A8: Condition | B8: Precondition
D9: Logged into the system
B11: BlogId
D12: 1 | F12: O | H12: O | I12: O | J12: O | K12: O | L12: O | M12: O
D13: null | G13: O
B14: UserId
D15: 1 | F15: O | G15: O | H15: O | I15: O | K15: O | L15: O | M15: O
D16: null | J16: O
B17: ParentId
D18: 2 | H18: O | I18: O
D19: null | F19: O | G19: O | J19: O | K19: O | L19: O | M19: O
B20: IsReply
D21: TRUE | H21: O | I21: O | K21: O
D22: FALSE | F22: O | G22: O | J22: O | L22: O | M22: O
B23: Parent blogId
D24: 1 | H24: O
D25: 2 | I25: O
D26: null | F26: O | G26: O | J26: O | K26: O | L26: O | M26: O
B27: content
D28: "" | L28: O
D29: null | M29: O
D30: "comment content" | F30: O | G30: O | H30: O | I30: O | J30: O | K30: O
A32: Confirm | B32: Return
D33: TRUE | F33: O | H33: O
D34: FALSE | G34: O | I34: O | J34: O | K34: O | L34: O | M34: O
B35: Exception
D36: NotFoundException | G36: O | J36: O
D37: BadRequestException | I37: O | K37: O | L37: O | M37: O
B38: Log message
A41: Result | B41: Type(N : Normal, A : Abnormal, B : Boundary) | F41: N | G41: A | H41: N | I41: A | J41: A | K41: A | L41: B | M41: B
B42: Passed/Failed | F42: P | G42: P | H42: P | I42: P | J42: P | K42: P | L42: P | M42: P
B43: Executed Date | F43: 45724 | G43: 45724 | H43: 45724 | I43: 45724 | J43: 45724 | K43: 45724 | L43: 45724 | M43: 45724
B44: Defect ID

Sheet DeleteBlog
A1: Code Module | C1: Blog Management | F1: Method | L1: Delete Blog Post
A2: Created By | C2: AnhDQ | F2: Executed By | L2: AnhDQ
A3: Test requirement
A4: Passed | C4: Failed | F4: Untested | L4: N/A/B | O4: Total Test Cases
A5: =COUNTIF(F45:HQ45,"P") -> 1 | C5: =COUNTIF(F46:HQ46,"F") -> 0 | F5: =SUM(O5,-A5,-C5) -> 0 | L5: =COUNTIF(E44:HQ44,"N") -> 1 | M5: =COUNTIF(E44:HQ44,"A") -> 0 | N5: =COUNTIF(E44:HQ44,"B") -> 0 | O5: =COUNTA(E7:HT7) -> 1
F7: UTCID01
A8: Condition | B8: Precondition
D9: Logged in to the system, is the owner of at least 1 blog
D10: Đã đăng nhập vào hệ thống
D11: Sở hữu ít nhất 1 bài viết | F11: O
B13: Action
D14: Người dùng ấn vào xóa bài viết | F14: O
A32: Confirm | B32: Return
D33: T | F33: O
D34: F
B39: Exception
B41: Log message
D42: Xóa bài viết thành công
A44: Result | B44: Type(N : Normal, A : Abnormal, B : Boundary) | F44: N
B45: Passed/Failed | F45: P
B46: Executed Date | F46: 45724
B47: Defect ID

Sheet ViewShopProduct
A1: Code Module | C1: Product Management | F1: Method | L1: View Shop Product
A2: Created By | C2: AnhDQ | F2: Executed By | L2: AnhDQ
A3: Test requirement
A4: Passed | C4: Failed | F4: Untested | L4: N/A/B | O4: Total Test Cases
A5: =COUNTIF(F39:HQ39,"P") -> 5 | C5: =COUNTIF(F39:HQ39,"F") -> 0 | F5: =SUM(O5,-A5,-C5) -> 0 | L5: =COUNTIF(E38:HQ38,"N") -> 5 | M5: =COUNTIF(E38:HQ38,"A") -> 0 | N5: =COUNTIF(E38:HQ38,"B") -> 0 | O5: =COUNTA(E7:HT7) -> 5
F7: UTCID01 | G7: UTCID02 | H7: UTCID03 | I7: UTCID04 | J7: UTCID05
A8: Condition | B8: Precondition
D9: Logged into the system, is the owner of the shop
D10: Can connect with server
B15: FoodOption
D16: typeId:1,price:10.000 | F16: O | G16: O | J16: O
D17: typeId:2,price:50.000 | F17: O | H17: O | I17: O | J17: O
B19: Discount
D20: null | J20: O
D21: 0,1 | F21: O | G21: O | H21: O
D22: 1 | I22: O
A29: Confirm | B29: Return
D30: TRUE | F30: O | G30: O | H30: O | I30: O | J30: O
D31: Fasle
B32: Exception
B34: Log message
D35: Giá sản phẩm :0 | F35: O | G35: O | I35: O
D36: Giá sản phẩm :45.000 | H36: O
D37: Giá sản phẩm :50.000 | J37: O
A38: Result | B38: Type(N : Normal, A : Abnormal, B : Boundary) | F38: N | G38: N | H38: N | I38: N | J38: N
B39: Passed/Failed | F39: P | G39: P | H39: P | I39: P | J39: P
B40: Executed Date | F40: 45724 | G40: 45724 | H40: 45724 | I40: 45724 | J40: 45724
B41: Defect ID

Sheet ViewProductDetail
A1: Code Module | C1: Product Management | F1: Method | L1: View Product Detail
A2: Created By | C2: AnhDQ | F2: Executed By | L2: AnhDQ
A3: Test requirement
A4: Passed | C4: Failed | F4: Untested | L4: N/A/B | O4: Total Test Cases
A5: =COUNTIF(F39:HQ39,"P") -> 4 | C5: =COUNTIF(F39:HQ39,"F") -> 0 | F5: =SUM(O5,-A5,-C5) -> 0 | L5: =COUNTIF(E38:HQ38,"N") -> 3 | M5: =COUNTIF(E38:HQ38,"A") -> 1 | N5: =COUNTIF(E38:HQ38,"B") -> 0 | O5: =COUNTA(E7:HT7) -> 4
F7: UTCID01 | G7: UTCID02 | H7: UTCID03 | I7: UTCID04
A8: Condition | B8: Precondition
D9: Logged in to the system, is the owner of the shop, has at least 1 product
D10: Can connect with server
B13: FoodOption
D14: typeId:1,price:10.000 | F14: O | G14: O
D15: typeId:2,price:50.000 | G15: O | H15: O | I15: O
B17: Discount
D18: null | F18: O | G18: O
D19: 0,1 | F19: O | H19: O
D20: 1 | F20: O | I20: O
A29: Confirm | B29: Return
D30: T | F30: O | G30: O | H30: O | I30: O
D31: F
B32: Exception
B34: Log message
D35: Giá sản phẩm :0 | F35: O | I35: O
D36: Giá sản phẩm :45.000 | H36: O
D37: Giá sản phẩm :50.000 | G37: O
A38: Result | B38: Type(N : Normal, A : Abnormal, B : Boundary) | F38: A | G38: N | H38: N | I38: N
B39: Passed/Failed | F39: P | G39: P | H39: P | I39: P
B40: Executed Date | F40: 45724 | G40: 45724 | H40: 45724 | I40: 45724
B41: Defect ID

Sheet ViewProductList
A1: Code Module | C1: Product Management | F1: Method | L1: View Product List
A2: Created By | C2: AnhDQ | F2: Executed By | L2: AnhDQ
A3: Test requirement
A4: Passed | C4: Failed | F4: Untested | L4: N/A/B | O4: Total Test Cases
A5: =COUNTIF(F39:HQ39,"P") -> 4 | C5: =COUNTIF(F39:HQ39,"F") -> 0 | F5: =SUM(O5,-A5,-C5) -> 0 | L5: =COUNTIF(E38:HQ38,"N") -> 3 | M5: =COUNTIF(E38:HQ38,"A") -> 1 | N5: =COUNTIF(E38:HQ38,"B") -> 0 | O5: =COUNTA(E7:HT7) -> 4
F7: UTCID01 | G7: UTCID02 | H7: UTCID03 | I7: UTCID04
A8: Condition | B8: Precondition
D9: Logged into the system, use the search section to filter out a list of products, there must be at least 1 product in the database
D10: Can connect with server
B13: Search
D14: null | F14: O
D15: Cơm rang gà | G15: O | H15: O | I15: O
B16: FoodOption
D17: typeId:1,price:10.000 | G17: O
D18: typeId:2,price:50.000 | G18: O | H18: O | I18: O
B19: Discount
D20: null | G20: O
D21: 0,1 | H21: O
D22: 1 | I22: O
A29: Confirm | B29: Return
D30: T | F30: O | G30: O | H30: O | I30: O
D31: F
B32: Exception
B34: Log message
D35: Giá sản phẩm :0 | I35: O
D36: Giá sản phẩm :45.000 | H36: O
D37: Giá sản phẩm :50.000 | G37: O
A38: Result | B38: Type(N : Normal, A : Abnormal, B : Boundary) | F38: A | G38: N | H38: N | I38: N
B39: Passed/Failed | F39: P | G39: P | H39: P | I39: P
B40: Executed Date | F40: 45724 | G40: 45724 | H40: 45724 | I40: 45724
B41: Defect ID

Sheet AddProduct
A1: Code Module | C1: Product Management | F1: Method | L1: Add Product
A2: Created By | C2: AnhDQ | F2: Executed By | L2: AnhDQ
A3: Test requirement
A4: Passed | C4: Failed | F4: Untested | L4: N/A/B | O4: Total Test Cases
A5: =COUNTIF(F45:HQ45,"P") -> 6 | C5: =COUNTIF(F45:HQ45,"F") -> 0 | F5: =SUM(O5,-A5,-C5) -> 0 | L5: =COUNTIF(E44:HQ44,"N") -> 1 | M5: =COUNTIF(E44:HQ44,"A") -> 3 | N5: =COUNTIF(E44:HQ44,"B") -> 2 | O5: =COUNTA(E7:HT7) -> 6
F7: UTCID01 | G7: UTCID02 | H7: UTCID03 | I7: UTCID04 | J7: UTCID05 | K7: UTCID06
A8: Condition | B8: Precondition
D9: Logged into the system, is the owner of the shop
D10: Can connect with server
B15: Name
D16: Cơm rang | K16: O
D17: null | F17: O
B18: Category
D19: null | G19: O
D20: Cơm | K20: O
B21: FoodOption
D22: null | H22: O
D23: typeId:2,price:50.000 | K23: O
B24: Expiry Date
D25: 40288 | I25: O
D26: 45736 | K26: O
B27: Quantity
D28: 0 | J28: O
D29: 1 | K29: O
A34: Confirm | B34: Return
D35: T | K35: O
D36: F | F36: O | G36: O | H36: O | I36: O | J36: O
B37: Exception
B39: Log message
D40: Không thể bỏ trống các trường đánh dấu * | F40: O | G40: O | H40: O
D41: Ngày hết hạn không thể trong quá khứ | I41: O
D42: Số lương phải lớn hơn 0 | J42: O
D43: Thêm sản phẩm thành công | K43: O
A44: Result | B44: Type(N : Normal, A : Abnormal, B : Boundary) | F44: A | G44: A | H44: A | I44: B | J44: B | K44: N
B45: Passed/Failed | F45: P | G45: P | H45: P | I45: P | J45: P | K45: P
B46: Executed Date | F46: 45724 | G46: 45724 | H46: 45724 | I46: 45724 | J46: 45724 | K46: 45724
B47: Defect ID

Sheet EditProduct
A1: Code Module | C1: Product Management | F1: Method | L1: EditProduct
A2: Created By | C2: AnhDQ | F2: Executed By | L2: AnhDQ
A3: Test requirement
A4: Passed | C4: Failed | F4: Untested | L4: N/A/B | O4: Total Test Cases
A5: =COUNTIF(F45:HQ45,"P") -> 6 | C5: =COUNTIF(F45:HQ45,"F") -> 0 | F5: =SUM(O5,-A5,-C5) -> 0 | L5: =COUNTIF(E44:HQ44,"N") -> 1 | M5: =COUNTIF(E44:HQ44,"A") -> 3 | N5: =COUNTIF(E44:HQ44,"B") -> 2 | O5: =COUNTA(E7:HT7) -> 6
F7: UTCID01 | G7: UTCID02 | H7: UTCID03 | I7: UTCID04 | J7: UTCID05 | K7: UTCID06
A8: Condition | B8: Precondition
D9: Logged in to the system, is the owner of the shop, has at least 1 product
D10: Can connect with server
B15: Name
D16: Cơm rang | K16: O
D17: null | F17: O
B18: Category
D19: null | G19: O
D20: Cơm | K20: O
B21: FoodOption
D22: null | H22: O
D23: typeId:2,price:50.000 | K23: O
B24: Expiry Date
D25: 40288 | I25: O
D26: 45736 | K26: O
B27: Quantity
D28: 0 | J28: O
D29: 1 | K29: O
A34: Confirm | B34: Return
D35: T | K35: O
D36: F | F36: O | G36: O | H36: O | I36: O | J36: O
B37: Exception
B39: Log message
D40: Không thể bỏ trống các trường đánh dấu * | F40: O | G40: O | H40: O
D41: Ngày hết hạn không thể trong quá khứ | I41: O
D42: Số lương phải lớn hơn 0 | J42: O
D43: Thêm sản phẩm thành công | K43: O
A44: Result | B44: Type(N : Normal, A : Abnormal, B : Boundary) | F44: A | G44: A | H44: A | I44: B | J44: B | K44: N
B45: Passed/Failed | F45: P | G45: P | H45: P | I45: P | J45: P | K45: P
B46: Executed Date | F46: 45724 | G46: 45724 | H46: 45724 | I46: 45724 | J46: 45724 | K46: 45724
B47: Defect ID

Sheet DeleteProduct
A1: Code Module | C1: Product Management | F1: Method | L1: Delete Product
A2: Created By | C2: AnhDQ | F2: Executed By | L2: AnhDQ
A3: Test requirement
A4: Passed | C4: Failed | F4: Untested | L4: N/A/B | O4: Total Test Cases
A5: =COUNTIF(F39:HQ39,"P") -> 1 | C5: =COUNTIF(F39:HQ39,"F") -> 0 | F5: =SUM(O5,-A5,-C5) -> 0 | L5: =COUNTIF(E38:HQ38,"N") -> 1 | M5: =COUNTIF(E38:HQ38,"A") -> 0 | N5: =COUNTIF(E38:HQ38,"B") -> 0 | O5: =COUNTA(E7:HT7) -> 1
F7: UTCID01
A8: Condition | B8: Precondition
D9: Logged in to the system, is the owner of the shop, has at least 1 product
D10: Can connect with server
B13: Action
D14: Ấn vào nút xóa sản phẩm | F14: O
A30: Confirm | B30: Return
D31: T | F31: O
D32: F
B33: Exception
B35: Log message
D36: "success"
D37: "input1 is null"
A38: Result | B38: Type(N : Normal, A : Abnormal, B : Boundary) | F38: N
B39: Passed/Failed | F39: P
B40: Executed Date | F40: 45724
B41: Defect ID

Sheet ViewUserList
A1: Code Module | C1: OperatorFeature | F1: Method | L1: View user list
A2: Created By | C2: AnhDQ | F2: Executed By | L2: AnhDQ
A3: Test requirement
A4: Passed | C4: Failed | F4: Untested | L4: N/A/B | O4: Total Test Cases
A5: =COUNTIF(F39:HQ39,"P") -> 3 | C5: =COUNTIF(F39:HQ39,"F") -> 0 | F5: =SUM(O5,-A5,-C5) -> 0 | L5: =COUNTIF(E38:HQ38,"N") -> 3 | M5: =COUNTIF(E38:HQ38,"A") -> 0 | N5: =COUNTIF(E38:HQ38,"B") -> 0 | O5: =COUNTA(E7:HT7) -> 3
F7: UTCID01 | G7: UTCID02 | H7: UTCID03
A8: Condition | B8: Precondition
D9: Logged into the system
D10: Can connect with server
D11: Danh sách người dùng trống | F11: O
D12: Danh sách người dùng có dữ liệu | G12: O | H12: O
B14: Search
D15: "John" | F15: O | G15: O
D16: "jasjkdnasjdnas" | H16: O
A30: Confirm | B30: Return
D31: T | F31: O | G31: O | H31: O
D32: F
B33: Exception
B35: Log message
D36: Null | F36: O | H36: O
D37: Danh sách người dùng | G37: O
A38: Result | B38: Type(N : Normal, A : Abnormal, B : Boundary) | F38: N | G38: N | H38: N
B39: Passed/Failed | F39: P | G39: P | H39: P
B40: Executed Date | F40: 45724 | G40: 45724 | H40: 45724
B41: Defect ID

Sheet ActivateDeactivate account
A1: Code Module | C1: Operator Feature | F1: Method | L1: Activate/Deactivate account
A2: Created By | C2: AnhDQ | F2: Executed By
A3: Test requirement | C3: Successfully change user status
A4: Passed | C4: Failed | F4: Untested | L4: N/A/B | O4: Total Test Cases
A5: =COUNTIF(F39:HQ39,"P") -> 5 | C5: =COUNTIF(F39:HQ39,"F") -> 0 | F5: =SUM(O5,-A5,-C5) -> 0 | L5: =COUNTIF(E38:HQ38,"N") -> 2 | M5: =COUNTIF(E38:HQ38,"A") -> 3 | N5: =COUNTIF(E38:HQ38,"B") -> 0 | O5: =COUNTA(E7:HT7) -> 5
F7: UTCID01 | G7: UTCID02 | H7: UTCID03 | I7: UTCID04 | J7: UTCID05
A8: Condition | B8: Precondition
D9: Can connect with server
D10: Exsited User:User 1:id=1,status=ACTIVE;User 2:id=2,status=INACTIVE
B12: UserId
D13: null | F13: O
D14: 1 | G14: O | H14: O
D15: 2 | I15: O | J15: O
B16: Status
D17: ACTIVE | G17: O | I17: O
D18: INACTIVE | H18: O | J18: O
A29: Confirm | B29: Return
D30: Success | H30: O | I30: O
D31: FALSE | F31: O | G31: O | J31: O
B32: Exception
B34: Log message
D35: User is already active/inactive | G35: O | J35: O
D36: User not found | F36: O
D37: Success | H37: O | I37: O
A38: Result | B38: Type(N : Normal, A : Abnormal, B : Boundary) | F38: A | G38: A | H38: N | I38: N | J38: A
B39: Passed/Failed | F39: P | G39: P | H39: P | I39: P | J39: P
B40: Executed Date | F40: 39139 | G40: 39139 | H40: 39140 | I40: 39141 | J40: 39142
B41: Defect ID

Sheet View Report Detail (Operator)
A1: Code Module | C1: Operator Feature | F1: Method | L1: View Report Detail (Operator)
A2: Created By | C2: AnhDQ | F2: Executed By
A3: Test requirement | C3: <Brief description about requirements which are tested in this function>
A4: Passed | C4: Failed | F4: Untested | L4: N/A/B | O4: Total Test Cases
A5: =COUNTIF(F38:HQ38,"P") -> 3 | C5: =COUNTIF(F38:HQ38,"F") -> 0 | F5: =SUM(O5,-A5,-C5) -> 0 | L5: =COUNTIF(E37:HQ37,"N") -> 3 | M5: =COUNTIF(E37:HQ37,"A") -> 0 | N5: =COUNTIF(E37:HQ37,"B") -> 0 | O5: =COUNTA(E7:HT7) -> 3
F7: UTCID01 | G7: UTCID02 | H7: UTCID03
A8: Condition | B8: Precondition
D9: Can connect with server
B13: Filter by Type
D14: BLOG | F14: O
D15: SHOP | G15: O
D16: PRODUCT | H16: O
A29: Confirm | B29: Return
D30: T | F30: O | G30: O | H30: O
D31: F
B32: Exception
B34: Log message
D35: "success" | F35: O | G35: O | H35: O
A37: Result | B37: Type(N : Normal, A : Abnormal, B : Boundary) | F37: N | G37: N | H37: N
B38: Passed/Failed | F38: P | G38: P | H38: P
B39: Executed Date | F39: 39139 | G39: 39139 | H39: 39140
B40: Defect ID

Sheet View Reports (Operator)
A1: Code Module | C1: Operator Feature | F1: Method | L1: View Reports (Operator)
A2: Created By | C2: AnhDQ | F2: Executed By
A3: Test requirement | C3: <Brief description about requirements which are tested in this function>
A4: Passed | C4: Failed | F4: Untested | L4: N/A/B | O4: Total Test Cases
A5: =COUNTIF(F38:HQ38,"P") -> 2 | C5: =COUNTIF(F38:HQ38,"F") -> 0 | F5: =SUM(O5,-A5,-C5) -> 0 | L5: =COUNTIF(E37:HQ37,"N") -> 2 | M5: =COUNTIF(E37:HQ37,"A") -> 0 | N5: =COUNTIF(E37:HQ37,"B") -> 0 | O5: =COUNTA(E7:HT7) -> 2
F7: UTCID01 | G7: UTCID02
A8: Condition | B8: Precondition
D9: Can connect with server
B11: Report
D12: null | F12: O
D13: Có dữ liệu | G13: O
W22: O
A29: Confirm | B29: Return
D30: T | F30: O | G30: O
D31: F
B32: Exception
B34: Log message
D35: "success" | F35: O | G35: O
A37: Result | B37: Type(N : Normal, A : Abnormal, B : Boundary) | F37: N | G37: N
B38: Passed/Failed | F38: P | G38: P
B39: Executed Date | F39: 39139 | G39: 39139
B40: Defect ID

Sheet ActivateDeactivate Shop
A1: Code Module | C1: Operator Feature | F1: Method | L1: Activate/Deactivate Shop
A2: Created By | C2: AnhDQ | F2: Executed By
A3: Test requirement | C3: <Brief description about requirements which are tested in this function>
A4: Passed | C4: Failed | F4: Untested | L4: N/A/B | O4: Total Test Cases
A5: =COUNTIF(F39:HQ39,"P") -> 5 | C5: =COUNTIF(F39:HQ39,"F") -> 0 | F5: =SUM(O5,-A5,-C5) -> 0 | L5: =COUNTIF(E38:HQ38,"N") -> 2 | M5: =COUNTIF(E38:HQ38,"A") -> 3 | N5: =COUNTIF(E38:HQ38,"B") -> 0 | O5: =COUNTA(E7:HT7) -> 5
F7: UTCID01 | G7: UTCID02 | H7: UTCID03 | I7: UTCID04 | J7: UTCID05
A8: Condition | B8: Precondition
D9: Can connect with server
D10: Exsited Shop:Shop 1:id=1,status=ACTIVE;Shop 2:id=2,status=INACTIVE
B12: ShopId
D13: null | F13: O
D14: 1 | G14: O | H14: O
D15: 2 | I15: O | J15: O
B16: Status
D17: ACTIVE | G17: O | I17: O
D18: INACTIVE | H18: O | J18: O
A29: Confirm | B29: Return
D30: Success | H30: O | I30: O
D31: FALSE | F31: O | G31: O | J31: O
B32: Exception
B34: Log message
D35: Shop is already active/inactive | G35: O | J35: O
D36: Shop not found | F36: O
D37: Success | H37: O | I37: O
A38: Result | B38: Type(N : Normal, A : Abnormal, B : Boundary) | F38: A | G38: A | H38: N | I38: N | J38: A
B39: Passed/Failed | F39: P | G39: P | H39: P | I39: P | J39: P
B40: Executed Date | F40: 39139 | G40: 39139 | H40: 39140 | I40: 39141 | J40: 39142
B41: Defect ID

Sheet ActivateDeactivate Blog
A1: Code Module | C1: Operator Feature | F1: Method | L1: Activate/Deactivate Blog
A2: Created By | C2: AnhDQ | F2: Executed By
A3: Test requirement | C3: <Brief description about requirements which are tested in this function>
A4: Passed | C4: Failed | F4: Untested | L4: N/A/B | O4: Total Test Cases
A5: =COUNTIF(F44:HQ44,"P") -> 5 | C5: =COUNTIF(F45:HQ45,"F") -> 0 | F5: =SUM(O5,-A5,-C5) -> 0 | L5: =COUNTIF(E44:HQ44,"N") -> 0 | M5: =COUNTIF(E44:HQ44,"A") -> 0 | N5: =COUNTIF(E44:HQ44,"B") -> 0 | O5: =COUNTA(E7:HT7) -> 5
F7: UTCID01 | G7: UTCID02 | H7: UTCID03 | I7: UTCID04 | J7: UTCID05
A8: Condition | B8: Precondition
D10: Exsited Blog:Blog 1:id=1,status=ACTIVE;Blog 2:id=2,status=INACTIVE
B12: BlogId
D13: null | F13: O
D14: 1 | G14: O | H14: O
D15: 2 | I15: O | J15: O
B16: Status
D17: ACTIVE | G17: O | I17: O
D18: INACTIVE | H18: O | J18: O
A31: Confirm | B31: Return
D32: Success | H32: O | I32: O
D33: FALSE | F33: O | G33: O | J33: O
B34: Exception
B36: Log message
D37: Blog is already active/inactive | G37: O | J37: O
D38: Blog not found | F38: O
D39: Success | H39: O | I39: O
A43: Result | B43: Type(N : Normal, A : Abnormal, B : Boundary) | F43: A | G43: A | H43: N | I43: N | J43: A
B44: Passed/Failed | F44: P | G44: P | H44: P | I44: P | J44: P
B45: Executed Date | F45: 39139 | G45: 39139 | H45: 39140 | I45: 39141 | J45: 39142
B46: Defect ID

Sheet View Shop List (Operator)
A1: Code Module | C1: Operator Feature | F1: Method | L1: methodName
A2: Created By | C2: AnhDQ | F2: Executed By
A3: Test requirement | C3: <Brief description about requirements which are tested in this function>
A4: Passed | C4: Failed | F4: Untested | L4: N/A/B | O4: Total Test Cases
A5: =COUNTIF(F44:HQ44,"P") -> 4 | C5: =COUNTIF(F45:HQ45,"F") -> 0 | F5: =SUM(O5,-A5,-C5) -> 0 | L5: =COUNTIF(E44:HQ44,"N") -> 0 | M5: =COUNTIF(E44:HQ44,"A") -> 0 | N5: =COUNTIF(E44:HQ44,"B") -> 0 | O5: =COUNTA(E7:HT7) -> 4
F7: UTCID01 | G7: UTCID02 | H7: UTCID03 | I7: UTCID04
A8: Condition | B8: Precondition
B13: Shop
D14: null | F14: O
D15: Not null | G15: O
B16: Filter
D17: ACTIVE | H17: O
D18: null | I18: O
A31: Confirm | B31: Return
D32: Danh sách Shop | G32: O | H32: O | I32: O
D33: Null | F33: O
B38: Exception
B40: Log message
A43: Result | B43: Type(N : Normal, A : Abnormal, B : Boundary) | F43: N | G43: N | H43: N | I43: N
B44: Passed/Failed | F44: P | G44: P | H44: P | I44: P
B45: Executed Date | F45: 39139 | G45: 39139 | H45: 39139 | I45: 39139
B46: Defect ID

Sheet View Shop Detail (Operator)
A1: Code Module | C1: Operator Feature | F1: Method | L1: View Shop Detail (Operator)
A2: Created By | C2: AnhDQ | F2: Executed By
A3: Test requirement | C3: <Brief description about requirements which are tested in this function>
A4: Passed | C4: Failed | F4: Untested | L4: N/A/B | O4: Total Test Cases
A5: =COUNTIF(F44:HQ44,"P") -> 2 | C5: =COUNTIF(F45:HQ45,"F") -> 0 | F5: =SUM(O5,-A5,-C5) -> 0 | L5: =COUNTIF(E43:HQ43,"N") -> 1 | M5: =COUNTIF(E44:HQ44,"A") -> 0 | N5: =COUNTIF(E44:HQ44,"B") -> 0 | O5: =COUNTA(E7:HT7) -> 2
F7: UTCID01 | G7: UTCID02
A8: Condition | B8: Precondition
B12: ShopId
D13: null | F13: O
D14: 1 | G14: O
A31: Confirm | B31: Return
D32: ShopDetail | G32: O
D33: null | F33: O
B38: Exception
B40: Log message
D41: Shop not Found | F41: O
D42: Success | G42: O
A43: Result | B43: Type(N : Normal, A : Abnormal, B : Boundary) | F43: A | G43: N
B44: Passed/Failed | F44: P | G44: P
B45: Executed Date | F45: 39139 | G45: 39139
B46: Defect ID

Sheet Auto count Rating for Shop
A1: Code Module | C1: Common Feature | F1: Method | L1: Auto count Rating for Shop
A2: Created By | C2: AnhDQ | F2: Executed By
A3: Test requirement | C3: <Brief description about requirements which are tested in this function>
A4: Passed | C4: Failed | F4: Untested | L4: N/A/B | O4: Total Test Cases
A5: =COUNTIF(F38:HQ38,"P") -> 2 | C5: =COUNTIF(F38:HQ38,"F") -> 0 | F5: =SUM(O5,-A5,-C5) -> 0 | L5: =COUNTIF(E37:HQ37,"N") -> 2 | M5: =COUNTIF(E37:HQ37,"A") -> 0 | N5: =COUNTIF(E37:HQ37,"B") -> 0 | O5: =COUNTA(E7:HT7) -> 2
F7: UTCID01 | G7: UTCID02
A8: Condition | B8: Precondition
D9: Can connect with server
D10: Shop with 4.0 rate, 10 view count
B12: Rate
D13: 0 | F13: O
D14: 5 | G14: O
A29: Confirm | B29: Return
D30: Rate:3.6 | F30: O
D31: Rate:4.1 | G31: O
B32: Exception
B34: Log message
A37: Result | B37: Type(N : Normal, A : Abnormal, B : Boundary) | F37: N | G37: N
B38: Passed/Failed | F38: P | G38: P
B39: Executed Date | F39: 39139 | G39: 39139
B40: Defect ID

Sheet Add to Cart
A1: Code Module | C1: Cart Management | F1: Method | L1: Add to Cart
A2: Created By | C2: AnhDQ | F2: Executed By
A3: Test requirement | C3: <Brief description about requirements which are tested in this function>
A4: Passed | C4: Failed | F4: Untested | L4: N/A/B | O4: Total Test Cases
A5: =COUNTIF(F51:HQ51,"P") -> 5 | C5: =COUNTIF(F52:HQ52,"F") -> 0 | F5: =SUM(O5,-A5,-C5) -> 0 | L5: =COUNTIF(E51:HQ51,"N") -> 0 | M5: =COUNTIF(E51:HQ51,"A") -> 0 | N5: =COUNTIF(E51:HQ51,"B") -> 0 | O5: =COUNTA(E7:HT7) -> 5
F7: UTCID01 | G7: UTCID02 | H7: UTCID03 | I7: UTCID04 | J7: UTCID05
A8: Condition | B8: Precondition
D10: An exsited cart with product id:1,quantity 1,FoodOption id 1,quantity :1
D11: Product 1 is from Shop 1,Product 2 is from Shop 2
B12: Product
D13: null | F13: O
D14: 1 | G14: O | H14: O | I14: O | J14: O
D15: 2 | J15: O
B16: FoodOption
D17: null | G17: O
D18: 1 | H18: O | I18: O | J18: O
D19: 2 | I19: O
D20: 3 | J20: O
B21: Quantity
D22: 1 | E22: 1 | H22: O | I22: O | J22: O
A36: Confirm | B36: Return
B38: Cart List
C39: Cart 1
C40: Product 1:Quantity 1,FoodOption 1: Quantity 1 | F40: O | G40: O
C41: Product 1:Quantity 2,FoodOption 1: Quantity 2 | H41: O | J41: O
C42: Product 1:Quantity 2,FoodOption 1: Quantity 2,FoodOption 2:Quantity 1 | I42: O
C43: Cart 2
C44: Product 2:Quantity 1,FoodOption 3: Quantity 1 | J44: O
B45: Exception
B47: Log message
D48: Thêm vào giỏ hàng thành công | F48: O | H48: O | I48: O | J48: O
D49: Phải chọn Size cho sản phẩm | G49: O
A50: Result | B50: Type(N : Normal, A : Abnormal, B : Boundary) | F50: N | G50: A | H50: N | I50: N | J50: N
B51: Passed/Failed | F51: P | G51: P | H51: P | I51: P | J51: P
B52: Executed Date | F52: 39139 | G52: 39139 | H52: 39139 | I52: 39139 | J52: 39139
B53: Defect ID

Sheet Remove from Cart
A1: Code Module | C1: Cart Management | F1: Method | L1: Remove from Cart
A2: Created By | C2: AnhDQ | F2: Executed By
A3: Test requirement | C3: <Brief description about requirements which are tested in this function>
A4: Passed | C4: Failed | F4: Untested | L4: N/A/B | O4: Total Test Cases
A5: =COUNTIF(F42:HQ42,"P") -> 3 | C5: =COUNTIF(F43:HQ43,"F") -> 0 | F5: =SUM(O5,-A5,-C5) -> 0 | L5: =COUNTIF(E41:HQ41,"N") -> 3 | M5: =COUNTIF(E42:HQ42,"A") -> 0 | N5: =COUNTIF(E42:HQ42,"B") -> 0 | O5: =COUNTA(E7:HT7) -> 3
F7: UTCID01 | G7: UTCID02 | H7: UTCID03
A8: Condition | B8: Precondition
D9: An exsited cart with product id:1,quantity 2,FoodOption id 1,quantity :2
B12: ProductId
D13: null | F13: O | H13: O
D14: 1 | G14: O
B15: FoodOptionId
D16: null | F16: O
D17: 1 | H17: O
A31: Confirm | B31: Return
C32: Cart 1
C33: Product 1:Quantity 2,FoodOption 1: Quantity 2 | F33: O
C34: Product 1:Quantity 2,FoodOption 1: Quantity 1 | H34: O
C35: Null | G35: O
B36: Exception
B38: Log message
D39: "please input a>= -1" | F39: O
A41: Result | B41: Type(N : Normal, A : Abnormal, B : Boundary) | F41: N | G41: N | H41: N
B42: Passed/Failed | F42: P | G42: P | H42: P
B43: Executed Date | F43: 39139 | G43: 39139 | H43: 39139
B44: Defect ID

Sheet View Cart
A1: Code Module | C1: Cart Management | F1: Method | L1: View Cart
A2: Created By | C2: AnhDQ | F2: Executed By
A3: Test requirement | C3: <Brief description about requirements which are tested in this function>
A4: Passed | C4: Failed | F4: Untested | L4: N/A/B | O4: Total Test Cases
A5: =COUNTIF(F39:HQ39,"P") -> 2 | C5: =COUNTIF(F40:HQ40,"F") -> 0 | F5: =SUM(O5,-A5,-C5) -> 0 | L5: =COUNTIF(E38:HQ38,"N") -> 2 | M5: =COUNTIF(E39:HQ39,"A") -> 0 | N5: =COUNTIF(E39:HQ39,"B") -> 0 | O5: =COUNTA(E7:HT7) -> 2
F7: UTCID01 | G7: UTCID02
A8: Condition | B8: Precondition
B11: CartId
D12: null | F12: O
D13: 1 | G13: O
A31: Confirm | B31: Return
D32: T | F32: O | G32: O
D33: F
B35: Log message
A38: Result | B38: Type(N : Normal, A : Abnormal, B : Boundary) | F38: N | G38: N
B39: Passed/Failed | F39: P | G39: P
B40: Executed Date | F40: 39139 | G40: 39139
B41: Defect ID

Sheet View Home Page
A1: Code Module | C1: Common Feature | F1: Method | L1: View Home Page
A2: Created By | C2: AnhDQ | F2: Executed By
A3: Test requirement | C3: <Brief description about requirements which are tested in this function>
A4: Passed | C4: Failed | F4: Untested | L4: N/A/B | O4: Total Test Cases
A5: =COUNTIF(F47:HQ47,"P") -> 8 | C5: =COUNTIF(F48:HQ48,"F") -> 0 | F5: =SUM(O5,-A5,-C5) -> 0 | L5: =COUNTIF(E46:HQ46,"N") -> 8 | M5: =COUNTIF(E47:HQ47,"A") -> 0 | N5: =COUNTIF(E47:HQ47,"B") -> 0 | O5: =COUNTA(E7:HT7) -> 8
F7: UTCID01 | G7: UTCID02 | H7: UTCID02 | I7: UTCID02 | J7: UTCID02 | K7: UTCID02 | L7: UTCID07 | M7: UTCID08
A8: Condition | B8: Precondition
B12: Category
D13: null | F13: O
D14: not null | G14: O
B15: Banner
D16: null | H16: O
D17: not null | I17: O
B18: Product
D19: null | J19: O
D20: not null | K20: O
B21: Popular Product
D22: null | L22: O
D23: not null | M23: O
A34: Confirm | B34: Return
D35: Home Page | F35: O | G35: O | H35: O | I35: O | J35: O | K35: O | L35: O | M35: O
B43: Log message
A46: Result | B46: Type(N : Normal, A : Abnormal, B : Boundary) | F46: N | G46: N | H46: N | I46: N | J46: N | K46: N | L46: N | M46: N
B47: Passed/Failed | F47: P | G47: P | H47: P | I47: P | J47: P | K47: P | L47: P | M47: P
B48: Executed Date | F48: 39139 | G48: 39139 | H48: 39139 | I48: 39139 | J48: 39139 | K48: 39139 | L48: 39144 | M48: 39144
B49: Defect ID

Sheet Filter Product by Category
A1: Code Modulenưa | C1: Common Feature | F1: Method | L1: Filter Product by Category
A2: Created By | C2: AnhDQ | F2: Executed By
A3: Test requirement | C3: <Brief description about requirements which are tested in this function>
A4: Passed | C4: Failed | F4: Untested | L4: N/A/B | O4: Total Test Cases
A5: =COUNTIF(F39:HQ39,"P") -> 3 | C5: =COUNTIF(F40:HQ40,"F") -> 0 | F5: =SUM(O5,-A5,-C5) -> 0 | L5: =COUNTIF(E38:HQ38,"N") -> 3 | M5: =COUNTIF(E39:HQ39,"A") -> 0 | N5: =COUNTIF(E39:HQ39,"B") -> 0 | O5: =COUNTA(E7:HT7) -> 3
F7: UTCID01 | G7: UTCID02 | H7: UTCID03
A8: Condition | B8: Precondition
B12: CategoryId
D13: null | F13: O
D14: 1 | G14: O | H14: O
A31: Confirm | B31: Return
C32: Product List
D33: null | F33: O | H33: O
D34: not null | G34: O
B35: Log message
A38: Result | B38: Type(N : Normal, A : Abnormal, B : Boundary) | F38: N | G38: N | H38: N
B39: Passed/Failed | F39: P | G39: P | H39: P
B40: Executed Date | F40: 39139 | G40: 39139 | H40: 39139
B41: Defect ID

Sheet Get location from google Map
A1: Code Module | C1: Common Feature | F1: Method | L1: Get location from google Map
A2: Created By | C2: AnhDQ | F2: Executed By
A3: Test requirement | C3: <Brief description about requirements which are tested in this function>
A4: Passed | C4: Failed | F4: Untested | L4: N/A/B | O4: Total Test Cases
A5: =COUNTIF(F38:HQ38,"P") -> 1 | C5: =COUNTIF(F38:HQ38,"F") -> 0 | F5: =SUM(O5,-A5,-C5) -> 0 | L5: =COUNTIF(E37:HQ37,"N") -> 1 | M5: =COUNTIF(E37:HQ37,"A") -> 0 | N5: =COUNTIF(E37:HQ37,"B") -> 0 | O5: =COUNTA(E7:HT7) -> 1
F7: UTCID01
A8: Condition | B8: Precondition
D9: Can connect with server
B12: Search
D13: 123 đường ABC | F13: O
A29: Confirm | B29: Return
D30: lattitude,longtitude | F30: O
B32: Exception
B34: Log message
A37: Result | B37: Type(N : Normal, A : Abnormal, B : Boundary) | F37: N
B38: Passed/Failed | F38: P
B39: Executed Date | F39: 39139
B40: Defect ID

Sheet Recommend food by type for cust
A1: Code Module | C1: Common Feature | F1: Method | L1: Recommend food by type for customer
A2: Created By | C2: AnhDQ | F2: Executed By
A3: Test requirement | C3: <Brief description about requirements which are tested in this function>
A4: Passed | C4: Failed | F4: Untested | L4: N/A/B | O4: Total Test Cases
A5: =COUNTIF(F38:HQ38,"P") -> 0 | C5: =COUNTIF(F38:HQ38,"F") -> 0 | F5: =SUM(O5,-A5,-C5) -> 0 | L5: =COUNTIF(E37:HQ37,"N") -> 0 | M5: =COUNTIF(E37:HQ37,"A") -> 0 | N5: =COUNTIF(E37:HQ37,"B") -> 0 | O5: =COUNTA(E7:HT7) -> 0
A8: Condition | B8: Precondition
D9: Can connect with server
B12: Date
D13: 29 | F13: O | G13: O
D14: 30
D15: 31
B16: Month
D17: 2 | F17: O
D18: 3 | G18: O
D19: 4
B20: Year
D21: 2000 | F21: O
D22: 2009 | G22: O
A29: Confirm | B29: Return
D30: T | F30: O | G30: O
D31: F
B32: Exception
B34: Log message
D35: "success"
D36: "input1 is null"
A37: Result | B37: Type(N : Normal, A : Abnormal, B : Boundary)
B38: Passed/Failed
B39: Executed Date | F39: 39139 | G39: 39139 | H39: 39140 | I39: 39141 | J39: 39142 | K39: 39143 | L39: 39144 | M39: 39145 | N39: 39146 | O39: 39147 | P39: 39148 | Q39: 39149 | R39: 39150 | S39: 39151 | T39: 39152
B40: Defect ID | K40: DFID002 | L40: DFID004 | M40: DFID005 | N40: DFID006 | O40: DFID007 | P40: DFID008 | Q40: DFID009 | R40: DFID010 | S40: DFID011 | T40: DFID012

Sheet Register Shop
A1: Code Module | C1: Shop Management | F1: Method | L1: Register Shop
A2: Created By | C2: AnhDQ | F2: Executed By | L2: NguyenT
A3: Test requirement | C3: <Brief description about requirements which are tested in this function>
A4: Passed | C4: Failed | F4: Untested | L4: N/A/B | O4: Total Test Cases
A5: =COUNTIF(F56:HQ56,"P") -> 10 | C5: =COUNTIF(F56:HQ56,"F") -> 0 | F5: =SUM(O5,-A5,-C5) -> 0 | L5: =COUNTIF(E55:HQ55,"N") -> 1 | M5: =COUNTIF(E55:HQ55,"A") -> 8 | N5: =COUNTIF(E55:HQ55,"B") -> 1 | O5: =COUNTA(E7:HT7) -> 10
F7: UTCID01 | G7: UTCID02 | H7: UTCID03 | I7: UTCID04 | J7: UTCID05 | K7: UTCID06 | L7: UTCID07 | M7: UTCID08 | N7: UTCID09 | O7: UTCID10
A8: Condition | B8: Precondition
D9: Login into application
D10: UserId = 1
D11: Profile has UserId = 1
D12: today = 31/01/2024
B13: UserId
D14: null | G14: O
D15: 1 | F15: O | H15: O | I15: O | J15: O | K15: O | L15: O | M15: O | N15: O | O15: O
B16: Profile(UserId)
D17: null | H17: O
D18: 1 | F18: O | G18: O | I18: O | J18: O | K18: O | L18: O | M18: O | N18: O | O18: O
B19: OwnerId
D20: 1 | I20: O
D21: null | F21: O | G21: O | H21: O | J21: O | K21: O | L21: O | M21: O | N21: O | O21: O
B22: Role
D23: shipper | J23: O
D24: customer | F24: O | G24: O | H24: O | I24: O | K24: O | L24: O | M24: O | O24: O
D25: shopkepper | N25: O
B26: CitizenIDExpiredDate
D27: 45292 | K27: O
D28: 47514 | F28: O | G28: O | H28: O | I28: O | J28: O | L28: O | M28: O | O28: O
B29: MultipartFile
D30: null | L30: O
D31: notNull | F31: O | G31: O | H31: O | I31: O | J31: O | K31: O | M31: O | N31: O | O31: O
B32: Input Fields
D33: null | M33: O
D34: notNull | F34: O | G34: O | H34: O | I34: O | J34: O | K34: O | L34: O | N34: O | O34: O
B35: Phone
D36: 978067432 | F36: O | G36: O | H36: O | I36: O | J36: O | K36: O | L36: O | M36: O | N36: O
D37: 123jduwh | O37: O
A39: Confirm | B39: Return
D40: T | F40: O
D41: F | G41: O | H41: O | I41: O | J41: O | K41: O | L41: O | M41: O | N41: O | O41: O
B42: Exception
D43: NotFoundException | G43: O | H43: O
D44: BadRequestException | I44: O | J44: O | K44: O | L44: O | M44: O | N44: O | O44: O
B45: Log message
D46: "success" | F46: O
D47: "User Not Found' | G47: O
D48: "Profile Not Found" | H48: O
D49: "User đã có cửa hàng." | I49: O | N49: O
D50: ""User không thể tạo cửa hàng vì là shipper | J50: O
D51: "Giấy tờ tùy thân đã hết hạn!" | K51: O
D52: "Số điện thoại không hợp lệ" | O52: O
D53: "File is null" | L53: O
D54: "input is null" | M54: O
A55: Result | B55: Type(N : Normal, A : Abnormal, B : Boundary) | F55: N | G55: A | H55: A | I55: A | J55: A | K55: B | L55: A | M55: A | N55: A | O55: A
B56: Passed/Failed | F56: P | G56: P | H56: P | I56: P | J56: P | K56: P | L56: P | M56: P | N56: P | O56: P
B57: Executed Date | F57: 39139 | G57: 39139 | H57: 39140 | I57: 39141 | J57: 39142 | K57: 39143 | L57: 39144 | M57: 39145 | N57: 39146 | O57: 39147
B58: Defect ID

Sheet Edit Shop Detail
A1: Code Module | C1: Shop Management | F1: Method | L1: Edit Shop Detail
A2: Created By | C2: AnhDQ | F2: Executed By
A3: Test requirement | C3: <Brief description about requirements which are tested in this function>
A4: Passed | C4: Failed | F4: Untested | L4: N/A/B | O4: Total Test Cases
A5: =COUNTIF(F41:HQ41,"P") -> 4 | C5: =COUNTIF(F41:HQ41,"F") -> 0 | F5: =SUM(O5,-A5,-C5) -> 0 | L5: =COUNTIF(E40:HQ40,"N") -> 1 | M5: =COUNTIF(E40:HQ40,"A") -> 3 | N5: =COUNTIF(E40:HQ40,"B") -> 0 | O5: =COUNTA(E7:HT7) -> 4
F7: UTCID01 | G7: UTCID02 | H7: UTCID03 | I7: UTCID04
A8: Condition | B8: Precondition
D9: Can connect with server
B12: ShopId
D13: null | F13: O
D14: 1 | G14: O | H14: O | I14: O
B15: Logo
D16: img.jpg | G16: O | H16: O | I16: O
B17: TaxCode
D18: 12346 | G18: O | H18: O | I18: O
A30: Confirm | B30: Return
D31: Success | I31: O
D32: Faiil | F32: O | G32: O | H32: O
B33: Exception
B35: Log message
D36: Lỗi encrypt | H36: O
D37: Lỗi khi upload ảnh | G37: O
D38: Không tìm thấy shop | F38: O
D39: Update profile Shop thành công | I39: O
A40: Result | B40: Type(N : Normal, A : Abnormal, B : Boundary) | F40: A | G40: A | H40: A | I40: N
B41: Passed/Failed | F41: P | G41: P | H41: P | I41: P
B42: Executed Date | F42: 39139 | G42: 39139 | H42: 39140 | I42: 39141
B43: Defect ID

Sheet View Shop Dashboard
A1: Code Module | C1: Shop Management | F1: Method | L1: View Shop Dashboard
A2: Created By | C2: AnhDQ | F2: Executed By
A3: Test requirement | C3: <Brief description about requirements which are tested in this function>
A4: Passed | C4: Failed | F4: Untested | L4: N/A/B | O4: Total Test Cases
A5: =COUNTIF(F38:HQ38,"P") -> 19 | C5: =COUNTIF(F38:HQ38,"F") -> 0 | F5: =SUM(O5,-A5,-C5) -> 0 | L5: =COUNTIF(E37:HQ37,"N") -> 13 | M5: =COUNTIF(E37:HQ37,"A") -> 6 | N5: =COUNTIF(E37:HQ37,"B") -> 0 | O5: =COUNTA(E7:HT7) -> 19
F7: UTCID01 | G7: UTCID02 | H7: UTCID03 | I7: UTCID04 | J7: UTCID05 | K7: UTCID06 | L7: UTCID07 | M7: UTCID08 | N7: UTCID09 | O7: UTCID10 | P7: UTCID11 | Q7: UTCID12 | R7: UTCID13 | S7: UTCID14 | T7: UTCID15 | U7: UTCID16 | V7: UTCID17 | W7: UTCID18 | X7: UTCID19
A8: Condition | B8: Precondition
D9: Can connect with server
B12: OrderIdList | D12: null | F12: O
D13: 1,2 | G13: O | H13: O | I13: O | M13: O | N13: O | O13: O | S13: O | T13: O | U13: O
D14: 1,2,3,4 | J14: O | K14: O | L14: O | P14: O | Q14: O | R14: O | V14: O | W14: O | X14: O
B15: ShopId
D16: null | G16: O | L16: O | M16: O | R16: O | S16: O | X16: O
D17: 1 | H17: O | I17: O | J17: O | N17: O | O17: O | P17: O | T17: O | U17: O | V17: O
B18: OrderStatus
D19: PENDING | H19: O | J19: O | N19: O | P19: O | T19: O | V19: O
D20: CANCELLED | I20: O | K20: O | O20: O | Q20: O | U20: O | W20: O
B21: Day | G21: O | H21: O | I21: O | J21: O | K21: O | L21: O
B22: Month | M22: O | N22: O | O22: O | P22: O | Q22: O | R22: O
B23: Year | S23: O | T23: O | U23: O | V23: O | W23: O | X23: O
A29: Confirm | B29: Return
D30: CountOrderByStatus | F30: O | H30: O | I30: O | J30: O | K30: O | N30: O | O30: O | P30: O | Q30: O | T30: O | U30: O | V30: O | W30: O
D31: Null | G31: O | L31: O | M31: O | R31: O | S31: O | X31: O
B32: Exception
B34: Log message
A37: Result | B37: Type(N : Normal, A : Abnormal, B : Boundary) | F37: N | G37: A | H37: N | I37: N | J37: N | K37: N | L37: A | M37: A | N37: N | O37: N | P37: N | Q37: N | R37: A | S37: A | T37: N | U37: N | V37: N | W37: N | X37: A
B38: Passed/Failed | F38: P | G38: P | H38: P | I38: P | J38: P | K38: P | L38: P | M38: P | N38: P | O38: P | P38: P | Q38: P | R38: P | S38: P | T38: P | U38: P | V38: P | W38: P | X38: P
B39: Executed Date | F39: 39139 | G39: 39139 | H39: 39140 | I39: 39141 | J39: 39142 | K39: 39143 | L39: 39144 | M39: 39139 | N39: 39140 | O39: 39141 | P39: 39142 | Q39: 39143 | R39: 39144 | S39: 39139 | T39: 39140 | U39: 39141 | V39: 39142 | W39: 39143 | X39: 39144
B40: Defect ID

Sheet View Shops revenue
A1: Code Module | C1: Shop Management | F1: Method | L1: View Shop's revenue
A2: Created By | C2: AnhDQ | F2: Executed By
A3: Test requirement | C3: <Brief description about requirements which are tested in this function>
A4: Passed | C4: Failed | F4: Untested | L4: N/A/B | O4: Total Test Cases
A5: =COUNTIF(F38:HQ38,"P") -> 15 | C5: =COUNTIF(F38:HQ38,"F") -> 0 | F5: =SUM(O5,-A5,-C5) -> 0 | L5: =COUNTIF(E37:HQ37,"N") -> 9 | M5: =COUNTIF(E37:HQ37,"A") -> 6 | N5: =COUNTIF(E37:HQ37,"B") -> 0 | O5: =COUNTA(E7:HT7) -> 15
F7: UTCID01 | G7: UTCID02 | H7: UTCID03 | I7: UTCID04 | J7: UTCID05 | K7: UTCID06 | L7: UTCID07 | M7: UTCID08 | N7: UTCID09 | O7: UTCID10 | P7: UTCID11 | Q7: UTCID12 | R7: UTCID13 | S7: UTCID14 | T7: UTCID15
A8: Condition | B8: Precondition
D9: Can connect with server
B12: OrderIdList | D12: null | F12: O | G12: O | K12: O | L12: O | P12: O | Q12: O
D13: 1,2 | H13: O | J13: O | M13: O | O13: O | R13: O | T13: O
D14: 1,2,3,4 | I14: O | N14: O | S14: O
B15: ShopId
D16: null | F16: O | J16: O | K16: O | O16: O | P16: O | T16: O
D17: 1 | G17: O | H17: O | I17: O | L17: O | M17: O | N17: O | Q17: O | R17: O | S17: O
B18: Day | F18: O | G18: O | H18: O | I18: O | J18: O
B19: Month | K19: O | L19: O | M19: O | N19: O | O19: O
B20: Year | P20: O | Q20: O | R20: O | S20: O | T20: O
A29: Confirm | B29: Return
D30: ShopRevenue | G30: O | H30: O | I30: O | L30: O | M30: O | N30: O | Q30: O | R30: O | S30: O
D31: Null | F31: O | J31: O | K31: O | O31: O | P31: O | T31: O
B32: Exception
B34: Log message
D35: "success"
D36: "input1 is null"
A37: Result | B37: Type(N : Normal, A : Abnormal, B : Boundary) | F37: A | G37: N | H37: N | I37: N | J37: A | K37: A | L37: N | M37: N | N37: N | O37: A | P37: A | Q37: N | R37: N | S37: N | T37: A
B38: Passed/Failed | F38: P | G38: P | H38: P | I38: P | J38: P | K38: P | L38: P | M38: P | N38: P | O38: P | P38: P | Q38: P | R38: P | S38: P | T38: P
B39: Executed Date | F39: 39139 | G39: 39139 | H39: 39140 | I39: 39141 | J39: 39142 | K39: 39139 | L39: 39139 | M39: 39140 | N39: 39141 | O39: 39142 | P39: 39139 | Q39: 39139 | R39: 39140 | S39: 39141 | T39: 39142
B40: Defect ID

Sheet Shipper Register
A1: Code Module | C1: Account Management | F1: Method | L1: ShipperRegister
A2: Created By | C2: NguyenT | F2: Executed By | L2: NhatNM
A3: Test requirement
A4: Passed | C4: Failed | F4: Untested | L4: N/A/B | O4: Total Test Cases
A5: =COUNTIF(F62:HQ62,"P") -> 9 | C5: =COUNTIF(F46:HQ46,"F") -> 0 | F5: =SUM(O5,-A5,-C5) -> 0 | L5: =COUNTIF(E61:HQ61,"N") -> 9 | M5: =COUNTIF(E61:HQ61,"A") -> 0 | N5: =COUNTIF(E41:HQ41,"B") -> 0 | O5: =COUNTA(E7:HT7) -> 9
F7: UTCID01 | G7: UTCID02 | H7: UTCID03 | I7: UTCID04 | J7: UTCID05 | K7: UTCID06 | L7: UTCID07 | M7: UTCID08 | N7: UTCID09
A8: Condition | B8: Precondition
D9: Can connect with server
D10: User has already in the system
B12: name | D12: Nhat Nguyen | F12: O | G12: O | H12: O | I12: O | L12: O | M12: O
D13: null | J13: O | K13: O
D14: 12345 | N14: O
B15: roleId
D16: 2 | H16: O | L16: O
D17: 4 | F17: O | G17: O | I17: O | M17: O
D18: null | J18: O | K18: O | N18: O
B19: gender
D20: male | F20: O | G20: O | H20: O | I20: O | L20: O | M20: O
D21: null | J21: O | K21: O | N21: O
B22: dob
D23: 34834 | F23: O | G23: O | H23: O | I23: O | L23: O | M23: O
D24: null | J24: O | K24: O | N24: O
B25: phone
D26: 0342498878 | F26: O | G26: O | H26: O | I26: O | L26: O | M26: O
D27: null | J27: O | K27: O | N27: O
B28: email
D29: nhat@gmail.com | F29: O | G29: O | H29: O | I29: O | L29: O | M29: O
D30: null | J30: O | K30: O | N30: O
B31: citizenIDNumber
D32: 001203016678 | F32: O | G32: O | H32: O | I32: O | L32: O | M32: O
D33: null | J33: O | K33: O | N33: O
B34: citizenIDExpiredDate
D35: 46022 | F35: O | G35: O | H35: O | L35: O | M35: O
D36: 37756 | I36: O
D37: null | J37: O | K37: O | N37: O
B38: drivingLicenseExpiredDate
D39: 46203 | F39: O | G39: O | I39: O | M39: O
D40: 37756 | L40: O
D41: null | H41: O | J41: O | K41: O | N41: O
B42: Image
D43: image1.jpg | F43: O | G43: O | I43: O
D44: null | H44: O | J44: O | K44: O | L44: O | M44: O | N44: O
A47: Confirm | B47: Return
D48: Success | F48: O
D49: Fail | G49: O | H49: O | I49: O | J49: O | K49: O | L49: O | M49: O | N49: O
B50: Exception
B52: Log message
D53: Đăng ký thành công | F53: O
D54: Người dùng đã là shipper | G54: O
D55: Người dùng có vai trò shopkeeper | H55: O
D56: Thẻ căn cước đã hết hạn | I56: O
D57: Không tìm thấy người dùng | J57: O | N57: O
D58: Không tìm thấy hồ sơ người dùng | K58: O
D59: Giấy phép lái xe đã hết hạn | L59: O
D60: Không thấy file | M60: O
A61: Result | B61: Type(N : Normal, A : Abnormal, B : Boundary) | F61: N | G61: N | H61: N | I61: N | J61: N | K61: N | L61: N | M61: N | N61: N
B62: Passed/Failed | F62: P | G62: P | H62: P | I62: P | J62: P | K62: P | L62: P | M62: P | N62: P
B63: Executed Date | F63: 45731 | G63: 45731 | H63: 45731 | I63: 45731 | J63: 45731 | K63: 45731 | L63: 45731 | M63: 45731 | N63: 45731
B64: Defect ID

Sheet ActivateDeactivate Shipper
A1: Code Module | C1: Operator Feature | F1: Method | L1: Activate/Deactivate Shipper
A2: Created By | C2: NguyenT | F2: Executed By | L2: NhatNM
A3: Test requirement
A4: Passed | C4: Failed | F4: Untested | L4: N/A/B | O4: Total Test Cases
A5: =COUNTIF(F34:HQ34,"P") -> 6 | C5: =COUNTIF(F34:HQ34,"F") -> 0 | F5: =SUM(O5,-A5,-C5) -> 0 | L5: =COUNTIF(E33:HQ33,"N") -> 4 | M5: =COUNTIF(E33:HQ33,"A") -> 1 | N5: =COUNTIF(E33:HQ33,"B") -> 1 | O5: =COUNTA(E7:HT7) -> 6
F7: UTCID01 | G7: UTCID02 | H7: UTCID03 | I7: UTCID04 | J7: UTCID05 | K7: UTCID06
A8: Condition | B8: Precondition
D9: Can connect with server
D10: Shipper has already in the system
B11: userId
D12: 1 | F12: O | G12: O | H12: O | K12: O
D13: null | I13: O
D14: 999 | J14: O
B15: Shipper status
D16: ACTIVE | F16: O | G16: O | I16: O | J16: O
D17: INACTIVE | H17: O | K17: O
B18: reason
D19: null | F19: O | G19: O | I19: O | J19: O | K19: O
D20: Inactive due to policy violation | H20: O
A22: Confirm | B22: Return
D23: Success | F23: O | H23: O
D24: Fail | G24: O | I24: O | J24: O | K24: O
B25: Exception
B27: Log message
D28: Duyệt thành công | F28: O
D29: Người dùng đã là shipper | G29: O
D30: Đã cấm shipper | H30: O
D31: Không có người dùng trong hệ thống | I31: O | J31: O
D32: Không có lý do hợp lệ | K32: O
A33: Result | B33: Type(N : Normal, A : Abnormal, B : Boundary) | F33: A | G33: N | H33: N | I33: N | J33: N | K33: B
B34: Passed/Failed | F34: P | G34: P | H34: P | I34: P | J34: P | K34: P
B35: Executed Date | F35: 45731 | G35: 45731 | H35: 45731 | I35: 45731 | J35: 45731 | K35: 45731
B36: Defect ID

Sheet ApproveReject shop register
A1: Code Module | C1: Operator Feature | F1: Method | L1: Approve/Reject shop register
A2: Created By | C2: NguyenT | F2: Executed By | L2: NhatNM
A3: Test requirement
A4: Passed | C4: Failed | F4: Untested | L4: N/A/B | O4: Total Test Cases
A5: =COUNTIF(F42:HQ42,"P") -> 5 | C5: =COUNTIF(F42:HQ42,"F") -> 0 | F5: =SUM(O5,-A5,-C5) -> 0 | L5: =COUNTIF(E41:HQ41,"N") -> 4 | M5: =COUNTIF(E41:HQ41,"A") -> 1 | N5: =COUNTIF(E41:HQ41,"B") -> 0 | O5: =COUNTA(E7:HT7) -> 5
F7: UTCID01 | G7: UTCID02 | H7: UTCID03 | I7: UTCID04 | J7: UTCID05
A8: Condition | B8: Precondition
D9: Can connect with server
D10: Shipper has already in the system
B12: shopId
D13: 1 | F13: O | G13: O | I13: O
D14: null | H14: O | J14: O
B15: status
D16: ACTIVE | F16: O | I16: O
D17: INACTIVE | G17: O
D18: null | H18: O | J18: O
B19: userId
D20: 1 | F20: O | G20: O | I20: O
D21: null | H21: O | J21: O
B22: roleId
D23: 1 | F23: O | G23: O | J23: O
D24: 2 | I24: O
D25: null | H25: O
B26: reason
D27: shop is invalid | G27: O
D28: null | F28: O | H28: O | I28: O | J28: O
A29: Confirm | B29: Return
D30: Success | F30: O | G30: O
D31: Fail | H31: O | I31: O | J31: O
B32: Exception
B34: Log message
D35: Duyệt shop thành công | F35: O
D36: Đã từ chối đăng kí shop | G36: O
D37: Không tìm thấy người dùng | H37: O
D38: Người dùng đã là shop | I38: O
D39: Người dùng chưa đăng kí thành shop | J39: O
A41: Result | B41: Type(N : Normal, A : Abnormal, B : Boundary) | F41: A | G41: N | H41: N | I41: N | J41: N
B42: Passed/Failed | F42: P | G42: P | H42: P | I42: P | J42: P
B43: Executed Date | F43: 45731 | G43: 45731 | H43: 45731 | I43: 45731 | J43: 45731
B44: Defect ID

Sheet ApproveReject Shipper register
A1: Code Module | C1: Operator Feature | F1: Method | L1: Approve/Reject Shipper register
A2: Created By | C2: NguyenT | F2: Executed By | L2: NhatNM
A3: Test requirement
A4: Passed | C4: Failed | F4: Untested | L4: N/A/B | O4: Total Test Cases
A5: =COUNTIF(F45:HQ45,"P") -> 7 | C5: =COUNTIF(F45:HQ45,"F") -> 0 | F5: =SUM(O5,-A5,-C5) -> 0 | L5: =COUNTIF(E44:HQ44,"N") -> 1 | M5: =COUNTIF(E44:HQ44,"A") -> 6 | N5: =COUNTIF(E44:HQ44,"B") -> 0 | O5: =COUNTA(E7:HT7) -> 7
F7: UTCID01 | G7: UTCID02 | H7: UTCID03 | I7: UTCID04 | J7: UTCID05 | K7: UTCID06 | L7: UTCID07
A8: Condition | B8: Precondition
D9: Can connect with server
D10: Shipper are in PENDING status
D11: Users do the steps to register as a shipper.
B12: userId
D13: 1 | F13: O | G13: O | H13: O | I13: O | K13: O | L13: O
D14: null | J14: O
B15: shipperStatus
D16: null | H16: O | J16: O
D17: ACTIVE | F17: O | G17: O | I17: O | L17: O
D18: INACTIVE | K18: O
B20: RoleId
D21: 4 | F21: O | G21: O | I21: O | K21: O
D22: null | H22: O | J22: O | L22: O
B23: reason
D24: Missing information | I24: O
D25: null | F25: O | G25: O | H25: O | J25: O | L25: O
D26: Shipper banned | K26: O
A29: Confirm | B29: Return
D30: success to approve/reject shipper | F30: O
D31: fail to approve/reject shipper | G31: O | H31: O | I31: O | J31: O | K31: O | L31: O
B32: Exception
B34: Log message
D35: Shipper đã được duyệt thành công | F35: O
D36: User đã là shipper. | G36: O
D37: Chỉ có thể duyệt shipper đang ở trạng thái chờ. | H37: O
D38: Thiếu giấy tờ | I38: O
D39: User không tồn tại | J39: O
D40: Shipper đang trong trạng thái inactive | K40: O
D41: Không tìm thấy role | L41: O
A44: Result | B44: Type(N : Normal, A : Abnormal, B : Boundary) | F44: N | G44: A | H44: A | I44: A | J44: A | K44: A | L44: A
B45: Passed/Failed | F45: P | G45: P | H45: P | I45: P | J45: P | K45: P | L45: P
B46: Executed Date | F46: 45731 | G46: 45731 | H46: 45731 | I46: 45731 | J46: 45731 | K46: 45731 | L46: 45731
B47: Defect ID

Sheet Config Food category
A1: Code Module | C1: Operator Feature | F1: Method | L1: Config Food category
A2: Created By | C2: AnhDQ | F2: Executed By | L2: NhatNM
A3: Test requirement
A4: Passed | C4: Failed | F4: Untested | L4: N/A/B | O4: Total Test Cases
A5: =COUNTIF(F56:HQ56,"P") -> 8 | C5: =COUNTIF(F56:HQ56,"F") -> 0 | F5: =SUM(O5,-A5,-C5) -> 0 | L5: =COUNTIF(E55:HQ55,"N") -> 4 | M5: =COUNTIF(E55:HQ55,"A") -> 4 | N5: =COUNTIF(E55:HQ55,"B") -> 0 | O5: =COUNTA(E7:HT7) -> 8
F7: UTCID01 | G7: UTCID02 | H7: UTCID03 | I7: UTCID04 | J7: UTCID05 | K7: UTCID06 | L7: UTCID07 | M7: UTCID08
A8: Condition | B8: Precondition
D9: Operator can access into Category list
D10: Operator update category | J10: O | K10: O
D11: Operator search a category | F11: O | G11: O
D12: Operator add new category | H12: O | I12: O | M12: O
D13: Operator delete a category | L13: O
B15: search
D16: Cá | F16: O
D17: 123 | G17: O
D18: null | H18: O | I18: O | J18: O | K18: O | L18: O | M18: O
B19: categoryId
D20: 1 | F20: O | I20: O | J20: O | K20: O
D21: null | G21: O | L21: O
D22: 2 | H22: O | M22: O
B23: categoryName
D24: Cá | F24: O | I24: O
D25: null | G25: O | K25: O | L25: O
D26: Bánh mì | H26: O | J26: O | M26: O
B27: Description
D28: Danh mục Cá | F28: O | I28: O
D29: null | G29: O | K29: O | L29: O
D30: Danh mục Bánh mì | H30: O | J30: O | M30: O
B31: Image
D32: Image 1 | F32: O | H32: O | I32: O | J32: O | K32: O | M32: O
D33: null | G33: O | L33: O
B34: CreatedAt
D35: 45703 | F35: O | H35: O | I35: O | J35: O | K35: O
D36: 37636 | M36: O
D37: null | G37: O | L37: O
A39: Confirm | B39: Return
D40: Success | F40: O | H40: O | J40: O | L40: O
D41: Fail | G41: O | I41: O | K41: O | M41: O
B43: Exception
B45: Log message
D46: Tìm thấy category | F46: O
D47: Không tìm thấy category | G47: O
D48: Tạo thành công | H48: O
D49: Tạo thất bại | I49: O
D50: Chỉnh sửa thành công | J50: O
D51: Chỉnh sửa thất bại | K51: O
D52: Xóa thành công | L52: O
D53: Ngày tạo không hợp lệ | M53: O
A55: Result | B55: Type(N : Normal, A : Abnormal, B : Boundary) | F55: N | G55: A | H55: N | I55: A | J55: N | K55: A | L55: N | M55: A
B56: Passed/Failed | F56: P | G56: P | H56: P | I56: P | J56: P | K56: P | L56: P | M56: P
B57: Executed Date | F57: 45731 | G57: 45731 | H57: 45731 | I57: 45731 | J57: 45731 | K57: 45731 | L57: 45731 | M57: 45731
B58: Defect ID

Sheet Config Application banner
A1: Code Module | C1: Operator Feature | F1: Method | L1: Config Application banner
A2: Created By | C2: AnhDQ | F2: Executed By | L2: NhatNM
A3: Test requirement
A4: Passed | C4: Failed | F4: Untested | L4: N/A/B | O4: Total Test Cases
A5: =COUNTIF(F42:HQ42,"P") -> 6 | C5: =COUNTIF(F43:HQ43,"F") -> 0 | F5: =SUM(O5,-A5,-C5) -> 0 | L5: =COUNTIF(E41:HQ41,"N") -> 2 | M5: =COUNTIF(E41:HQ41,"A") -> 4 | N5: =COUNTIF(E41:HQ41,"B") -> 0 | O5: =COUNTA(E7:HT7) -> 6
F7: UTCID01 | G7: UTCID02 | H7: UTCID03 | I7: UTCID04 | J7: UTCID05 | K7: UTCID06
A8: Condition | B8: Precondition
D9: There is at least one banner in the database.
D10: There is a banner with ID exists.
D11: There are shops and BANNER types.
D12: There is a banner with the ID already exists.
B13: Image
D14: image.jpg | F14: O | G14: O | J14: O | K14: O
D15: null | H15: O | I15: O
B16: shopId
D17: 1 | F17: O | G17: O | I17: O | J17: O | K17: O
D18: null | H18: O
B19: ownerId
D20: 1 | F20: O | G20: O | I20: O | K20: O
D21: null | H21: O | J21: O
B22: typeId
D23: 1 | F23: O | G23: O | J23: O | K23: O
D24: null | I24: O
B25: status
D26: ACTIVE | F26: O
D27: INACTIVE | G27: O
D28: null | H28: O | I28: O | J28: O | K28: O
A30: Confirm | B30: Return
D31: success | F31: O | G31: O
D32: fail | H32: O | I32: O | J32: O | K32: O
B33: Log message
D34: Đã đăng banner | F34: O
D35: Đã cấm banner | G35: O
D36: Thông tin không tồn tại | H36: O
D37: Không có banner | I37: O
D38: Không có userId | J38: O
D39: Không nhận được banner từ shop | K39: O
A41: Result | B41: Type(N : Normal, A : Abnormal, B : Boundary) | F41: N | G41: N | H41: A | I41: A | J41: A | K41: A
B42: Passed/Failed | F42: P | G42: P | H42: P | I42: P | J42: P | K42: P
B43: Executed Date | F43: 45731 | G43: 45731 | H43: 45731 | I43: 45731 | J43: 45731 | K43: 45731
B44: Defect ID

Sheet Config Payment method
A1: Code Module | C1: Operator Feature | F1: Method | L1: Config Payment Method
A2: Created By | C2: AnhDQ | F2: Executed By | L2: NhatNM
A3: Test requirement
A4: Passed | C4: Failed | F4: Untested | L4: N/A/B | O4: Total Test Cases
A5: =COUNTIF(F45:HQ45,"P") -> 7 | C5: =COUNTIF(F46:HQ46,"F") -> 0 | F5: =SUM(O5,-A5,-C5) -> 0 | L5: =COUNTIF(E44:HQ44,"N") -> 4 | M5: =COUNTIF(E44:HQ44,"A") -> 3 | N5: =COUNTIF(E44:HQ44,"B") -> 0 | O5: =COUNTA(E7:HT7) -> 7
F7: UTCID01 | G7: UTCID02 | H7: UTCID03 | I7: UTCID04 | J7: UTCID05 | K7: UTCID06 | L7: UTCID07
A8: Condition | B8: Precondition
D9: Can connect with server
D10: Payment exists
B12: paymentId
D13: 1 | F13: O | H13: O | J13: O | L13: O
D14: 2 | G14: O
D15: null | I15: O | K15: O
B16: paymentName
D17: direct payment | F17: O | H17: O | I17: O
D18: transfer payment | G18: O | J18: O
D19: null | K19: O | L19: O
B20: description
D21: Cash on Delivery | F21: O | H21: O | I21: O | L21: O
D22: Payment via QR transfer | G22: O | J22: O
D23: null | K23: O | L23: O
B25: status | D25: ACTIVE | F25: O | G25: O | I25: O | J25: O | L25: O
D26: INACTIVE | H26: O
D27: null | K27: O
A29: Confirm | B29: Return
D31: success | F31: O | G31: O | H31: O | J31: O
D32: fail | I32: O | K32: O | L32: O
B33: Exception
B36: Log message
D37: Tạo thành công | F37: O | G37: O
D38: Đã gỡ phương thức thanh toán | H38: O
D39: Ko có paymentId | I39: O
D40: Cập nhật thành công | J40: O
D41: Thất bại | K41: O
D42: Phương thức không có tên | L42: O
A44: Result | B44: Type(N : Normal, A : Abnormal, B : Boundary) | F44: N | G44: N | H44: N | I44: A | J44: N | K44: A | L44: A
B45: Passed/Failed | F45: P | G45: P | H45: P | I45: P | J45: P | K45: P | L45: P
B46: Executed Date | F46: 45731 | G46: 45731 | H46: 45731 | I46: 45731 | J46: 45731 | K46: 45731 | L46: 45731
B47: Defect ID

Sheet Config Shipping method
A1: Code Module | C1: Operator Feature | F1: Method | L1: Config Shipping method
A2: Created By | C2: AnhDQ | F2: Executed By | L2: NhatNM
A3: Test requirement
A4: Passed | C4: Failed | F4: Untested | L4: N/A/B | O4: Total Test Cases
A5: =COUNTIF(F42:HQ42,"P") -> 7 | C5: =COUNTIF(F43:HQ43,"F") -> 0 | F5: =SUM(O5,-A5,-C5) -> 0 | L5: =COUNTIF(E41:HQ41,"N") -> 4 | M5: =COUNTIF(E41:HQ41,"A") -> 3 | N5: =COUNTIF(E41:HQ41,"B") -> 0 | O5: =COUNTA(E7:HT7) -> 7
F7: UTCID01 | G7: UTCID02 | H7: UTCID03 | I7: UTCID04 | J7: UTCID05 | K7: UTCID06 | L7: UTCID07
A8: Condition | B8: Precondition
D9: Can connect with server
B10: deliveryMethodId
D11: 1 | F11: O | H11: O | J11: O | L11: O
D12: 2 | G12: O
D13: null | I13: O | K13: O
B14: deliveryMethodName
D15: free ship | F15: O | H15: O | I15: O
D16: ship by shipper | G16: O | J16: O
D17: null | K17: O | L17: O
B18: description
D19: Self ship shop | F19: O | H19: O | I19: O | L19: O
D20: The system shipper will ship | G20: O | J20: O
D21: null | K21: O | L21: O
B23: status | D23: ACTIVE | F23: O | G23: O | I23: O | J23: O | L23: O
D24: INACTIVE | H24: O
D25: null | K25: O
A27: Confirm | B27: Return
D28: success | F28: O | G28: O | H28: O | J28: O
D29: fail | I29: O | K29: O | L29: O
B30: Exception
B33: Log message
D34: Tạo thành công | F34: O | G34: O
D35: Đã gỡ phương thức vận chuyển | H35: O
D36: Ko có deliveryMethodId | I36: O
D37: Cập nhật thành công | J37: O
D38: Thất bại | K38: O
D39: Phương thức không có tên | L39: O
A41: Result | B41: Type(N : Normal, A : Abnormal, B : Boundary) | F41: N | G41: N | H41: N | I41: A | J41: N | K41: A | L41: A
B42: Passed/Failed | F42: P | G42: P | H42: P | I42: P | J42: P | K42: P | L42: P
B43: Executed Date | F43: 45731 | G43: 45731 | H43: 45731 | I43: 45731 | J43: 45731 | K43: 45731 | L43: 45731
B44: Defect ID

Sheet View Operator dashboard
A1: Code Module | C1: Operator Feature | F1: Method | L1: View Operator Dashboard
A2: Created By | C2: AnhDQ | F2: Executed By | L2: NhatNM
A3: Test requirement
A4: Passed | C4: Failed | F4: Untested | L4: N/A/B | O4: Total Test Cases
A5: =COUNTIF(F87:IM87,"P") -> 30 | C5: =COUNTIF(F113:IM113,"F") -> 0 | F5: =SUM(O5,-A5,-C5) -> 0 | L5: =COUNTIF(E86:IM86,"N") -> 25 | M5: =COUNTIF(E86:IM86,"A") -> 5 | N5: =COUNTIF(E86:IM86,"B") -> 0 | O5: =COUNTA(E7:IP7) -> 30
F7: UTCID01 | G7: UTCID02 | H7: UTCID03 | I7: UTCID04 | J7: UTCID05 | K7: UTCID06 | L7: UTCID07 | M7: UTCID08 | N7: UTCID09 | O7: UTCID10 | P7: UTCID11 | Q7: UTCID12 | R7: UTCID13 | S7: UTCID14 | T7: UTCID15 | U7: UTCID16 | V7: UTCID17 | W7: UTCID18 | X7: UTCID19 | Y7: UTCID20 | Z7: UTCID21 | AA7: UTCID22 | AB7: UTCID23 | AC7: UTCID24 | AD7: UTCID25 | AE7: UTCID26 | AF7: UTCID27 | AG7: UTCID28 | AH7: UTCID29 | AI7: UTCID30
A8: Condition | B8: Precondition
B11: user
D12: userList | K12: O | L12: O | V12: O | W12: O | X12: O | AB12: O | AC12: O | AD12: O | AE12: O
D13: null | F13: O | G13: O | H13: O | I13: O | J13: O | M13: O | N13: O | O13: O | P13: O | Q13: O | S13: O | T13: O | U13: O | Y13: O | Z13: O | AA13: O | AF13: O | AG13: O | AH13: O | AI13: O
B14: TypeId
D15: 4 (order) | F15: O | M15: O | N15: O | O15: O | AF15: O
D16: 5 (shop) | G16: O | I16: O | J16: O | P16: O | Q16: O | R16: O | Y16: O | Z16: O | AA16: O | AG16: O
D17: 7 (report) | H17: O | S17: O | T17: O | U17: O | AH17: O
D18: null | K18: O | L18: O | V18: O | W18: O | X18: O | AB18: O | AC18: O | AD18: O | AE18: O | AI18: O
B19: OrderStatus
D20: DELIVERED | F20: O | M20: O | N20: O | O20: O | AF20: O
D21: null | G21: O | H21: O | I21: O | J21: O | K21: O | L21: O | P21: O | Q21: O | R21: O | S21: O | T21: O | U21: O | V21: O | W21: O | X21: O | Y21: O | Z21: O | AA21: O | AB21: O | AC21: O | AD21: O | AE21: O | AG21: O | AH21: O | AI21: O
B22: ReportStatus
D23: COMPLETED | H23: O | S23: O | T23: O | U23: O | AH23: O
D24: null | F24: O | G24: O | I24: O | J24: O | K24: O | L24: O | M24: O | N24: O | O24: O | P24: O | Q24: O | R24: O | V24: O | W24: O | X24: O | Y24: O | Z24: O | AA24: O | AB24: O | AC24: O | AD24: O | AE24: O | AF24: O | AG24: O | AI24: O
B26: Status
D27: ACTIVE | G27: O | K27: O | P27: O | Q27: O | R27: O | V27: O | W27: O | X27: O | AE27: O | AG27: O
D28: INACTIVE | J28: O | L28: O | Y28: O | Z28: O | AA28: O | AB28: O | AC28: O | AD28: O
D29: PENDING | I29: O
D30: null | F30: O | H30: O | M30: O | N30: O | O30: O | S30: O | T30: O | U30: O | AF30: O | AH30: O | AI30: O
B31: startDate
D32: 37787 | AE32: O | AF32: O | AG32: O | AH32: O
D33: 45703 | F33: O | G33: O | H33: O | I33: O | J33: O | K33: O | L33: O
D34: null | M34: O | N34: O | O34: O | P34: O | Q34: O | R34: O | S34: O | T34: O | U34: O | V34: O | W34: O | X34: O | Y34: O | Z34: O | AA34: O | AB34: O | AC34: O | AD34: O | AI34: O
B35: endDate
D36: 37794 | AE36: O | AF36: O | AG36: O | AH36: O
D37: 45710 | F37: O | G37: O | H37: O | I37: O | J37: O | K37: O | L37: O
D38: null | M38: O | N38: O | O38: O | P38: O | Q38: O | R38: O | S38: O | T38: O | U38: O | V38: O | W38: O | X38: O | Y38: O | Z38: O | AA38: O | AB38: O | AC38: O | AD38: O | AI38: O
B39: year
D40: 2025 | F40: O | G40: O | H40: O | I40: O | J40: O | K40: O | L40: O | M40: O | P40: O | S40: O | V40: O | Y40: O | AB40: O
D41: 2003 | AE41: O | AF41: O | AG41: O | AH41: O
D42: null | N42: O | O42: O | Q42: O | R42: O | T42: O | U42: O | W42: O | X42: O | Z42: O | AA42: O | AC42: O | AD42: O | AI42: O
B43: month
D44: 2 | F44: O | G44: O | H44: O | I44: O | J44: O | K44: O | L44: O | N44: O | Q44: O | T44: O | W44: O | Z44: O | AC44: O | AE44: O | AF44: O | AG44: O | AH44: O
D45: null | M45: O | O45: O | P45: O | R45: O | S45: O | U45: O | V45: O | X45: O | Y45: O | AA45: O | AB45: O | AD45: O | AI45: O
B46: day
D47: 22 | O47: O | R47: O | U47: O | X47: O | AA47: O | AD47: O
D48: null | F48: O | G48: O | H48: O | I48: O | J48: O | K48: O | L48: O | M48: O | N48: O | P48: O | Q48: O | S48: O | T48: O | V48: O | W48: O | Y48: O | Z48: O | AB48: O | AC48: O | AE48: O | AF48: O | AG48: O | AH48: O | AI48: O
A52: Confirm | B52: Return
D53: success | F53: O | G53: O | H53: O | I53: O | J53: O | K53: O | L53: O | M53: O | N53: O | O53: O | P53: O | Q53: O | R53: O | S53: O | T53: O | U53: O | V53: O | W53: O | X53: O | Y53: O | Z53: O | AA53: O | AB53: O | AC53: O | AD53: O
D54: fail | AE54: O | AF54: O | AG54: O | AH54: O | AI54: O
B55: Exception
B57: Log message
D58: danh sách các đơn hàng đã giao | F58: O
D59: danh sách các cửa hàng hoạt động | G59: O
D60: danh sách các khiếu nại đã hoàn thành | H60: O
D61: danh sách các cửa hàng đang chờ | I61: O
D62: danh sách các cửa hàng bị cấm | J62: O
D63: danh sách người dùng đang hoạt động | K63: O
D64: danh sách người dùng bị cấm | L64: O
D65: Thống kê các đơn hàng theo năm | M65: O
D66: Thống kê các đơn hàng theo tháng | N66: O
D67: Thống kê các đơn hàng theo ngày | O67: O
D68: Thống kê các cửa hàng có trong hệ thống trong năm | P68: O
D69: Thống kê các cửa hàng có trong hệ thống trong tháng | Q69: O
D70: Thống kê các cửa hàng có trong hệ thống trong ngày | R70: O
D71: Thống kê các khiếu nại trong năm | S71: O
D72: Thống kê các khiếu nại trong tháng | T72: O
D73: Thống kê các khiếu nại trong ngày | U73: O
D74: Thống kê người dùng đã đăng kí vào hệ thống theo năm | V74: O
D75: Thống kê người dùng đã đăng kí vào hệ thống theo tháng | W75: O
D76: Thống kê người dùng đã đăng kí vào hệ thống theo ngày | X76: O
D77: Thống kê các cửa hàng bị cấm trong năm | Y77: O
D78: Thống kê các cửa hàng bị cấm trong tháng | Z78: O
D79: Thống kê các cửa hàng bị cấm trong ngày | AA79: O
D80: Thống kê các người dùng bị cấm trong năm | AB80: O
D81: Thống kê các người dùng bị cấm trong tháng | AC81: O
D82: Thống kê các người dùng bị cấm trong ngày | AD82: O
D83: Không có thông tin trong thời gian này | AE83: O | AF83: O | AG83: O | AH83: O
D84: Không có thông tin | AI84: O
A86: Result | B86: Type(N : Normal, A : Abnormal, B : Boundary) | F86: N | G86: N | H86: N | I86: N | J86: N | K86: N | L86: N | M86: N | N86: N | O86: N | P86: N | Q86: N | R86: N | S86: N | T86: N | U86: N | V86: N | W86: N | X86: N | Y86: N | Z86: N | AA86: N | AB86: N | AC86: N | AD86: N | AE86: A | AF86: A | AG86: A | AH86: A | AI86: A
B87: Passed/Failed | F87: P | G87: P | H87: P | I87: P | J87: P | K87: P | L87: P | M87: P | N87: P | O87: P | P87: P | Q87: P | R87: P | S87: P | T87: P | U87: P | V87: P | W87: P | X87: P | Y87: P | Z87: P | AA87: P | AB87: P | AC87: P | AD87: P | AE87: P | AF87: P | AG87: P | AH87: P | AI87: P
B88: Executed Date | F88: 45731 | G88: 45731 | H88: 45731 | I88: 45731 | J88: 45731 | K88: 45731 | L88: 45731 | M88: 45731 | N88: 45731 | O88: 45731 | P88: 45731 | Q88: 45731 | R88: 45731 | S88: 45731 | T88: 45731 | U88: 45731 | V88: 45731 | W88: 45731 | X88: 45731 | Y88: 45731 | Z88: 45731 | AA88: 45731 | AB88: 45731 | AC88: 45731 | AD88: 45731 | AE88: 45731 | AF88: 45731 | AG88: 45731 | AH88: 45731 | AI88: 45731
B89: Defect ID

Sheet Report Shop
A1: Code Module | C1: Feedbacl Management | F1: Method | L1: ReportShop
A2: Created By | C2: AnhDQ | F2: Executed By | L2: NhatNM
A3: Test requirement
A4: Passed | C4: Failed | F4: Untested | L4: N/A/B | O4: Total Test Cases
A5: =COUNTIF(F45:HQ45,"P") -> 7 | C5: =COUNTIF(F46:HQ46,"F") -> 0 | F5: =SUM(O5,-A5,-C5) -> 0 | L5: =COUNTIF(E44:HQ44,"N") -> 6 | M5: =COUNTIF(E44:HQ44,"A") -> 1 | N5: =COUNTIF(E45:HQ45,"B") -> 0 | O5: =COUNTA(E7:HT7) -> 7
F7: UTCID01 | G7: UTCID02 | H7: UTCID02 | I7: UTCID02 | J7: UTCID02 | K7: UTCID02 | L7: UTCID07
A8: Condition | B8: Precondition
B12: userId
D13: 1 | F13: O | H13: O | I13: O | J13: O | K13: O
D14: null | G14: O | L14: O
B15: shopId
D16: 1 | F16: O | G16: O | I16: O | J16: O | K16: O
D17: null | H17: O | L17: O
B18: content
D19: shop is not good | F19: O | G19: O | H19: O | I19: O | J19: O | K19: O
D20: null | L20: O
B21: evidence
D22: image.jpg | F22: O | G22: O | H22: O | K22: O
D23: abcd12345 | J23: O
D24: null | I24: O | L24: O
B25: createdAt
D26: 45713 | F26: O | G26: O | H26: O | I26: O | J26: O
D27: 37733 | K27: O
D28: null | L28: O
A30: Confirm | B30: Return
D31: success | F31: O
D32: fail | G32: O | H32: O | I32: O | J32: O | K32: O | L32: O
B33: Exception
B35: Log message
D36: report thành công | F36: O
D37: không có userId | G37: O
D38: không có shopId | H38: O
D39: chưa cung cấp băng chứng | I39: O
D40: bằng chứng sai định dạng | J40: O
D41: thời gian không hợp lệ | K41: O
D42: thông tin trống | L42: O
A44: Result | B44: Type(N : Normal, A : Abnormal, B : Boundary) | F44: N | G44: N | H44: N | I44: N | J44: N | K44: N | L44: A
B45: Passed/Failed | F45: P | G45: P | H45: P | I45: P | J45: P | K45: P | L45: P
B46: Executed Date | F46: 45731 | G46: 45731 | H46: 45731 | I46: 45731 | J46: 45731 | K46: 45731 | L46: 45731
B47: Defect ID

Sheet Report Product
A1: Code Module | C1: Feedbacl Management | F1: Method | L1: ReportProduct
A2: Created By | C2: AnhDQ | F2: Executed By | L2: NhatNM
A3: Test requirement
A4: Passed | C4: Failed | F4: Untested | L4: N/A/B | O4: Total Test Cases
A5: =COUNTIF(F45:HQ45,"P") -> 7 | C5: =COUNTIF(F46:HQ46,"F") -> 0 | F5: =SUM(O5,-A5,-C5) -> 0 | L5: =COUNTIF(E44:HQ44,"N") -> 6 | M5: =COUNTIF(E44:HQ44,"A") -> 1 | N5: =COUNTIF(E45:HQ45,"B") -> 0 | O5: =COUNTA(E7:HT7) -> 7
F7: UTCID01 | G7: UTCID02 | H7: UTCID02 | I7: UTCID02 | J7: UTCID02 | K7: UTCID02 | L7: UTCID07
A8: Condition | B8: Precondition
B12: userId
D13: 1 | F13: O | H13: O | I13: O | J13: O | K13: O
D14: null | G14: O | L14: O
B15: productId
D16: 1 | F16: O | G16: O | I16: O | J16: O | K16: O
D17: null | H17: O | L17: O
B18: content
D19: product is not good | F19: O | G19: O | H19: O | I19: O | J19: O | K19: O
D20: null | L20: O
B21: evidence
D22: image.jpg | F22: O | G22: O | H22: O | K22: O
D23: abcd12334 | J23: O
D24: null | I24: O | L24: O
B25: createdAt
D26: 45713 | F26: O | G26: O | H26: O | I26: O | J26: O
D27: 37733 | K27: O
D28: null | L28: O
A30: Confirm | B30: Return
D31: success | F31: O
D32: fail | G32: O | H32: O | I32: O | J32: O | K32: O | L32: O
B33: Exception
B35: Log message
D36: report thành công | F36: O
D37: không có userId | G37: O
D38: không có productId | H38: O
D39: chưa cung cấp băng chứng | I39: O
D40: bằng chứng sai định dạng | J40: O
D41: thời gian không hợp lệ | K41: O
D42: thông tin trống | L42: O
A44: Result | B44: Type(N : Normal, A : Abnormal, B : Boundary) | F44: N | G44: N | H44: N | I44: N | J44: N | K44: N | L44: A
B45: Passed/Failed | F45: P | G45: P | H45: P | I45: P | J45: P | K45: P | L45: P
B46: Executed Date | F46: 45731 | G46: 45731 | H46: 45731 | I46: 45731 | J46: 45731 | K46: 45731 | L46: 45731
B47: Defect ID

Sheet Report Blog
A1: Code Module | C1: Feedbacl Management | F1: Method | L1: ReportBlog
A2: Created By | C2: AnhDQ | F2: Executed By | L2: NhatNM
A3: Test requirement
A4: Passed | C4: Failed | F4: Untested | L4: N/A/B | O4: Total Test Cases
A5: =COUNTIF(F45:HQ45,"P") -> 7 | C5: =COUNTIF(F46:HQ46,"F") -> 0 | F5: =SUM(O5,-A5,-C5) -> 0 | L5: =COUNTIF(E44:HQ44,"N") -> 6 | M5: =COUNTIF(E44:HQ44,"A") -> 1 | N5: =COUNTIF(E45:HQ45,"B") -> 0 | O5: =COUNTA(E7:HT7) -> 7
F7: UTCID01 | G7: UTCID02 | H7: UTCID02 | I7: UTCID02 | J7: UTCID02 | K7: UTCID02 | L7: UTCID07
A8: Condition | B8: Precondition
B12: userId
D13: 1 | F13: O | H13: O | I13: O | J13: O | K13: O
D14: null | G14: O | L14: O
B15: blogId
D16: 1 | F16: O | G16: O | I16: O | J16: O | K16: O
D17: null | H17: O | L17: O
B18: content
D19: this blog is not good | F19: O | G19: O | H19: O | I19: O | J19: O | K19: O
D20: null | L20: O
B21: evidence
D22: image.jpg | F22: O | G22: O | H22: O | K22: O
D23: abcd12334 | J23: O
D24: null | I24: O | L24: O
B25: createdAt
D26: 45713 | F26: O | G26: O | H26: O | I26: O | J26: O
D27: 37733 | K27: O
D28: null | L28: O
A30: Confirm | B30: Return
D31: success | F31: O
D32: fail | G32: O | H32: O | I32: O | J32: O | K32: O | L32: O
B33: Exception
B35: Log message
D36: report thành công | F36: O
D37: không có userId | G37: O
D38: không có blogId | H38: O
D39: chưa cung cấp băng chứng | I39: O
D40: bằng chứng sai định dạng | J40: O
D41: thời gian không hợp lệ | K41: O
D42: thông tin trống | L42: O
A44: Result | B44: Type(N : Normal, A : Abnormal, B : Boundary) | F44: N | G44: N | H44: N | I44: N | J44: N | K44: N | L44: A
B45: Passed/Failed | F45: P | G45: P | H45: P | I45: P | J45: P | K45: P | L45: P
B46: Executed Date | F46: 45731 | G46: 45731 | H46: 45731 | I46: 45731 | J46: 45731 | K46: 45731 | L46: 45731
B47: Defect ID

Sheet Search using sematic for produc
A1: Code Module | C1: ModuleName | F1: Method | L1: methodName
A2: Created By | C2: <Developer Name> | F2: Executed By
A3: Test requirement | C3: <Brief description about requirements which are tested in this function>
A4: Passed | C4: Failed | F4: Untested | L4: N/A/B | O4: Total Test Cases
A5: =COUNTIF(F44:HQ44,"P") -> 2 | C5: =COUNTIF(F45:HQ45,"F") -> 0 | F5: =SUM(O5,-A5,-C5) -> 0 | L5: =COUNTIF(E43:HQ43,"N") -> 2 | M5: =COUNTIF(E44:HQ44,"A") -> 0 | N5: =COUNTIF(E44:HQ44,"B") -> 0 | O5: =COUNTA(E7:HT7) -> 2
F7: UTCID01 | G7: UTCID02
A8: Condition | B8: Precondition
B12: Search
D13: Cơm | F13: O
D14: Takoyaki | G14: O
A31: Confirm | B31: Return
C32: Search list
D33: Cơm rang | F33: O | G33: O
D34: Cơm rang thập cẩm | F34: O | G34: O
D35: Cơm thịt nương | F35: O | G35: O
B38: Exception
B40: Log message
A43: Result | B43: Type(N : Normal, A : Abnormal, B : Boundary) | F43: N | G43: N
B44: Passed/Failed | F44: P | G44: P
B45: Executed Date | F45: 39139 | G45: 39139
B46: Defect ID

Sheet Search using elastic for produc
A1: Code Module | C1: ModuleName | F1: Method | L1: methodName
A2: Created By | C2: <Developer Name> | F2: Executed By
A3: Test requirement | C3: <Brief description about requirements which are tested in this function>
A4: Passed | C4: Failed | F4: Untested | L4: N/A/B | O4: Total Test Cases
A5: =COUNTIF(F44:HQ44,"P") -> 1 | C5: =COUNTIF(F45:HQ45,"F") -> 0 | F5: =SUM(O5,-A5,-C5) -> 0 | L5: =COUNTIF(E43:HQ43,"N") -> 1 | M5: =COUNTIF(E43:HQ43,"A") -> 0 | N5: =COUNTIF(E43:HQ43,"B") -> 0 | O5: =COUNTA(E7:HT7) -> 1
F7: UTCID01
A8: Condition | B8: Precondition
B13: Search
D14: Cơm | F14: O
A31: Confirm
B32: Return
C33: Search list
D34: Cơm rang | F34: O
D35: Cơm rang thập cẩm | F35: O
D36: Cơm thịt nương | F36: O
B38: Exception
B40: Log message
D41: "please input a>= -1" | F41: O
A43: Result | B43: Type(N : Normal, A : Abnormal, B : Boundary) | F43: N
B44: Passed/Failed | F44: P
B45: Executed Date | F45: 39139
B46: Defect ID

Sheet View Shop Reports(Shopkeeper)
A1: Code Module | C1: ModuleName1 | F1: Method | L1: methodName1
A2: Created By | C2: <Developer Name> | F2: Executed By
A3: Test requirement | C3: <Brief description about requirements which are tested in this function>
A4: Passed | C4: Failed | F4: Untested | L4: N/A/B | O4: Total Test Cases
A5: =COUNTIF(F38:HQ38,"P") -> 8 | C5: =COUNTIF(F38:HQ38,"F") -> 0 | F5: =SUM(O5,-A5,-C5) -> 0 | L5: =COUNTIF(E37:HQ37,"N") -> 2 | M5: =COUNTIF(E37:HQ37,"A") -> 6 | N5: =COUNTIF(E37:HQ37,"B") -> 0 | O5: =COUNTA(E7:HT7) -> 8
F7: UTCID01 | G7: UTCID02 | H7: UTCID03 | I7: UTCID04 | J7: UTCID05 | K7: UTCID06 | L7: UTCID07 | M7: UTCID08
A8: Condition | B8: Precondition
D9: Can connect with server
B12: ReportList
D13: null | F13: O | G13: O | J13: O | K13: O
D14: not null | H14: O | I14: O | L14: O | M14: O
B15: ShopId
D16: null | H16: O | L16: O
D17: 1 | F17: O | G17: O | I17: O | J17: O | K17: O | M17: O
B18: TYPE
D19: PRODUCT | F19: O | G19: O | H19: O | I19: O
D20: SHOP | J20: O | K20: O | L20: O | M20: O
A29: Confirm | B29: Return
D30: Report List | I30: O | M30: O
D31: null | F31: O | G31: O | H31: O | J31: O | K31: O | L31: O
B32: Exception
B34: Log message
D35: "success"
D36: "input1 is null"
A37: Result | B37: Type(N : Normal, A : Abnormal, B : Boundary) | F37: A | G37: A | H37: A | I37: N | J37: A | K37: A | L37: A | M37: N
B38: Passed/Failed | F38: P | G38: P | H38: P | I38: P | J38: P | K38: P | L38: P | M38: P
B39: Executed Date | F39: 39139 | G39: 39139 | H39: 39140 | I39: 39141 | J39: 39142 | K39: 39143 | L39: 39144 | M39: 39145
B40: Defect ID

Sheet View Shop Report Detail (Shopke
A1: Code Module | C1: ModuleName1 | F1: Method | L1: methodName1
A2: Created By | C2: <Developer Name> | F2: Executed By
A3: Test requirement | C3: <Brief description about requirements which are tested in this function>
A4: Passed | C4: Failed | F4: Untested | L4: N/A/B | O4: Total Test Cases
A5: =COUNTIF(F38:HQ38,"P") -> 5 | C5: =COUNTIF(F38:HQ38,"F") -> 0 | F5: =SUM(O5,-A5,-C5) -> 0 | L5: =COUNTIF(E37:HQ37,"N") -> 2 | M5: =COUNTIF(E37:HQ37,"A") -> 3 | N5: =COUNTIF(E37:HQ37,"B") -> 0 | O5: =COUNTA(E7:HT7) -> 5
F7: UTCID01 | G7: UTCID02 | H7: UTCID03 | I7: UTCID04 | J7: UTCID05
A8: Condition | B8: Precondition
D9: Can connect with server
B13: ReportId
D14: null | F14: O
D15: 1 | G15: O | H15: O | I15: O | J15: O
B16: ProductId
D17: null | G17: O
D18: 1 | H18: O
B19: ShopId
D20: null | I20: O
D21: 1 | J21: O
B22: TYPE
D23: PRODUCT | G23: O | H23: O
D24: SHOP | I24: O | J24: O
A29: Confirm | B29: Return
D30: Report Detail | H30: O | J30: O
D31: Null | F31: O | G31: O | I31: O
B32: Exception
B34: Log message
D35: "success"
D36: "input1 is null"
A37: Result | B37: Type(N : Normal, A : Abnormal, B : Boundary) | F37: A | G37: A | H37: N | I37: A | J37: N
B38: Passed/Failed | F38: P | G38: P | H38: P | I38: P | J38: P
B39: Executed Date | F39: 39139 | G39: 39139 | H39: 39140 | I39: 39141 | J39: 39142
B40: Defect ID

Sheet View Blog Reports
A1: Code Module | C1: ModuleName1 | F1: Method | L1: methodName1
A2: Created By | C2: <Developer Name> | F2: Executed By
A3: Test requirement | C3: <Brief description about requirements which are tested in this function>
A4: Passed | C4: Failed | F4: Untested | L4: N/A/B | O4: Total Test Cases
A5: =COUNTIF(F38:HQ38,"P") -> 2 | C5: =COUNTIF(F38:HQ38,"F") -> 0 | F5: =SUM(O5,-A5,-C5) -> 0 | L5: =COUNTIF(E37:HQ37,"N") -> 1 | M5: =COUNTIF(E37:HQ37,"A") -> 1 | N5: =COUNTIF(E37:HQ37,"B") -> 0 | O5: =COUNTA(E7:HT7) -> 2
F7: UTCID01 | G7: UTCID02
A8: Condition | B8: Precondition
D9: Can connect with server
B12: ReportList
D13: null | F13: O
D14: not null | G14: O
B15: Type
D16: BLOG | F16: O | G16: O
A29: Confirm | B29: Return
D30: Report List | G30: O
D31: null | F31: O
B32: Exception
B34: Log message
D35: "success"
D36: "input1 is null"
A37: Result | B37: Type(N : Normal, A : Abnormal, B : Boundary) | F37: A | G37: N
B38: Passed/Failed | F38: P | G38: P
B39: Executed Date | F39: 39139 | G39: 39139
B40: Defect ID

Sheet View Blog Report Detail
A1: Code Module | C1: ModuleName1 | F1: Method | L1: methodName1
A2: Created By | C2: <Developer Name> | F2: Executed By
A3: Test requirement | C3: <Brief description about requirements which are tested in this function>
A4: Passed | C4: Failed | F4: Untested | L4: N/A/B | O4: Total Test Cases
A5: =COUNTIF(F38:HQ38,"P") -> 2 | C5: =COUNTIF(F38:HQ38,"F") -> 0 | F5: =SUM(O5,-A5,-C5) -> 0 | L5: =COUNTIF(E37:HQ37,"N") -> 1 | M5: =COUNTIF(E37:HQ37,"A") -> 1 | N5: =COUNTIF(E37:HQ37,"B") -> 0 | O5: =COUNTA(E7:HT7) -> 2
F7: UTCID01 | G7: UTCID02
A8: Condition | B8: Precondition
D9: Can connect with server
B12: ReportId
D13: null | F13: O
D14: 1 | G14: O
A29: Confirm | B29: Return
D30: Report Detail | G30: O
D31: null | F31: O
B32: Exception
B34: Log message
D35: "success"
D36: "input1 is null"
A37: Result | B37: Type(N : Normal, A : Abnormal, B : Boundary) | F37: A | G37: N
B38: Passed/Failed | F38: P | G38: P
B39: Executed Date | F39: 39139 | G39: 39139
B40: Defect ID

Sheet View feedback list
A1: Code Module | C1: ModuleName1 | F1: Method | L1: methodName1
A2: Created By | C2: <Developer Name> | F2: Executed By
A3: Test requirement | C3: <Brief description about requirements which are tested in this function>
A4: Passed | C4: Failed | F4: Untested | L4: N/A/B | O4: Total Test Cases
A5: =COUNTIF(F38:HQ38,"P") -> 3 | C5: =COUNTIF(F38:HQ38,"F") -> 0 | F5: =SUM(O5,-A5,-C5) -> 0 | L5: =COUNTIF(E37:HQ37,"N") -> 1 | M5: =COUNTIF(E37:HQ37,"A") -> 2 | N5: =COUNTIF(E37:HQ37,"B") -> 0 | O5: =COUNTA(E7:HT7) -> 3
F7: UTCID01 | G7: UTCID02 | H7: UTCID03
A8: Condition | B8: Precondition
D9: Can connect with server
B11: ProductId
D12: null | F12: O
D13: 1 | G13: O | H13: O
B14: FeedbackList
D15: null | G15: O
D16: not null | H16: O
A29: Confirm | B29: Return
D30: Feedback List | H30: O
D31: null | F31: O | G31: O
B32: Exception
B34: Log message
A37: Result | B37: Type(N : Normal, A : Abnormal, B : Boundary) | F37: A | G37: A | H37: N
B38: Passed/Failed | F38: P | G38: P | H38: P
B39: Executed Date | F39: 39139 | G39: 39139 | H39: 39140
B40: Defect ID

Sheet Delete feedback
A1: Code Module | C1: ModuleName1 | F1: Method | L1: methodName1
A2: Created By | C2: <Developer Name> | F2: Executed By
A3: Test requirement | C3: <Brief description about requirements which are tested in this function>
A4: Passed | C4: Failed | F4: Untested | L4: N/A/B | O4: Total Test Cases
A5: =COUNTIF(F38:HQ38,"P") -> 4 | C5: =COUNTIF(F38:HQ38,"F") -> 0 | F5: =SUM(O5,-A5,-C5) -> 0 | L5: =COUNTIF(E37:HQ37,"N") -> 3 | M5: =COUNTIF(E37:HQ37,"A") -> 1 | N5: =COUNTIF(E37:HQ37,"B") -> 0 | O5: =COUNTA(E7:HT7) -> 4
F7: UTCID01 | G7: UTCID02 | H7: UTCID03 | I7: UTCID04
A8: Condition | B8: Precondition
D9: Can connect with server
B12: FeedbackId
D13: null | F13: O
D14: 1 | G14: O | H14: O | I14: O
B15: UserId
D16: null | G16: O
D17: 1 | H17: O
D18: 2 | I18: O
A29: Confirm | B29: Return
D30: Delete feedback successfull | I30: O
D31: Cannot delete this feedback | F31: O | G31: O | H31: O
B32: Exception
B34: Log message
D35: "success"
D36: "input1 is null"
A37: Result | B37: Type(N : Normal, A : Abnormal, B : Boundary) | F37: A | G37: N | H37: N | I37: N
B38: Passed/Failed | F38: P | G38: P | H38: P | I38: P
B39: Executed Date | F39: 39139 | G39: 39139 | H39: 39140 | I39: 39141
B40: Defect ID

Sheet Submit Feedback 
A1: Code Module | C1: ModuleName1 | F1: Method | L1: methodName1
A2: Created By | C2: <Developer Name> | F2: Executed By
A3: Test requirement | C3: <Brief description about requirements which are tested in this function>
A4: Passed | C4: Failed | F4: Untested | L4: N/A/B | O4: Total Test Cases
A5: =COUNTIF(F38:HQ38,"P") -> 9 | C5: =COUNTIF(F38:HQ38,"F") -> 0 | F5: =SUM(O5,-A5,-C5) -> 0 | L5: =COUNTIF(E37:HQ37,"N") -> 6 | M5: =COUNTIF(E37:HQ37,"A") -> 2 | N5: =COUNTIF(E37:HQ37,"B") -> 1 | O5: =COUNTA(E7:HT7) -> 9
F7: UTCID01 | G7: UTCID02 | H7: UTCID03 | I7: UTCID04 | J7: UTCID05 | K7: UTCID06 | L7: UTCID07 | M7: UTCID08 | N7: UTCID09
A8: Condition | B8: Precondition
D9: Can connect with server
B12: TYPE
D13: BLOG | F13: O | I13: O | L13: O
D14: PRODUCT | G14: O | J14: O | M14: O
D15: SHOP | H15: O | K15: O | N15: O
B16: REASON
D17: KHÁC | F17: O | G17: O | H17: O
D18: Lí do đã được config từ hệ thống | I18: O | J18: O | K18: O | L18: O | M18: O | N18: O
B19: PICTURE
D20: null | F20: O | G20: O | H20: O | I20: O | J20: O | K20: O
D21: not null | L21: O | M21: O | N21: O
A29: Confirm | B29: Return
D30: Tạo report thành công | F30: O | G30: O | H30: O | I30: O | J30: O | K30: O
D31: Tạo report thất bại | L31: O | M31: O | N31: O
B32: Exception
B34: Log message
D35: "success"
D36: "input1 is null"
A37: Result | B37: Type(N : Normal, A : Abnormal, B : Boundary) | F37: A | G37: N | H37: N | I37: N | J37: N | K37: B | L37: A | M37: N | N37: N
B38: Passed/Failed | F38: P | G38: P | H38: P | I38: P | J38: P | K38: P | L38: P | M38: P | N38: P
B39: Executed Date | F39: 39139 | G39: 39139 | H39: 39140 | I39: 39141 | J39: 39142 | K39: 39143 | L39: 39144 | M39: 39145 | N39: 39146
B40: Defect ID

Sheet View Order List (Customer)
A1: Code Module | C1: ModuleName1 | F1: Method | L1: methodName1
A2: Created By | C2: <Developer Name> | F2: Executed By
A3: Test requirement | C3: <Brief description about requirements which are tested in this function>
A4: Passed | C4: Failed | F4: Untested | L4: N/A/B | O4: Total Test Cases
A5: =COUNTIF(F38:HQ38,"P") -> 3 | C5: =COUNTIF(F38:HQ38,"F") -> 0 | F5: =SUM(O5,-A5,-C5) -> 0 | L5: =COUNTIF(E37:HQ37,"N") -> 2 | M5: =COUNTIF(E37:HQ37,"A") -> 1 | N5: =COUNTIF(E37:HQ37,"B") -> 0 | O5: =COUNTA(E7:HT7) -> 3
F7: UTCID01 | G7: UTCID02 | H7: UTCID03
A8: Condition | B8: Precondition
D9: Can connect with server
B11: Order
D12: null | F12: O
D13: not null | G13: O | H13: O
B14: Status
D15: PENDING | G15: O
D16: CANCELLED | H16: O
A29: Confirm | B29: Return
D30: OrderList | G30: O | H30: O
D31: null | F31: O
B32: Exception
B34: Log message
D35: "success"
D36: "input1 is null"
A37: Result | B37: Type(N : Normal, A : Abnormal, B : Boundary) | F37: A | G37: N | H37: N
B38: Passed/Failed | F38: P | G38: P | H38: P
B39: Executed Date | F39: 39139 | G39: 39139 | H39: 39140
B40: Defect ID

Sheet View Order Detail(Customer)
A1: Code Module | C1: ModuleName1 | F1: Method | L1: methodName1
A2: Created By | C2: <Developer Name> | F2: Executed By
A3: Test requirement | C3: <Brief description about requirements which are tested in this function>
A4: Passed | C4: Failed | F4: Untested | L4: N/A/B | O4: Total Test Cases
A5: =COUNTIF(F38:HQ38,"P") -> 2 | C5: =COUNTIF(F38:HQ38,"F") -> 0 | F5: =SUM(O5,-A5,-C5) -> 0 | L5: =COUNTIF(E37:HQ37,"N") -> 1 | M5: =COUNTIF(E37:HQ37,"A") -> 1 | N5: =COUNTIF(E37:HQ37,"B") -> 0 | O5: =COUNTA(E7:HT7) -> 2
F7: UTCID01 | G7: UTCID02
A8: Condition | B8: Precondition
D9: Can connect with server
B11: OrderId
D12: null | F12: O
D13: 1 | G13: O
A29: Confirm | B29: Return
D30: T | G30: O
D31: F | F31: O
B32: Exception
B34: Log message
D35: "success"
D36: "input1 is null"
A37: Result | B37: Type(N : Normal, A : Abnormal, B : Boundary) | F37: A | G37: N
B38: Passed/Failed | F38: P | G38: P
B39: Executed Date | F39: 39139 | G39: 39139
B40: Defect ID

Sheet Cancel Order (Customer)
A1: Code Module | C1: ModuleName1 | F1: Method | L1: methodName1
A2: Created By | C2: <Developer Name> | F2: Executed By
A3: Test requirement | C3: <Brief description about requirements which are tested in this function>
A4: Passed | C4: Failed | F4: Untested | L4: N/A/B | O4: Total Test Cases
A5: =COUNTIF(F38:HQ38,"P") -> 4 | C5: =COUNTIF(F38:HQ38,"F") -> 0 | F5: =SUM(O5,-A5,-C5) -> 0 | L5: =COUNTIF(E37:HQ37,"N") -> 3 | M5: =COUNTIF(E37:HQ37,"A") -> 1 | N5: =COUNTIF(E37:HQ37,"B") -> 0 | O5: =COUNTA(E7:HT7) -> 4
F7: UTCID01 | G7: UTCID02 | H7: UTCID03 | I7: UTCID04
A8: Condition | B8: Precondition
D9: Can connect with server
B12: OrderId
D13: null | F13: O
D14: 1 | G14: O | H14: O | I14: O
B15: OrderStatus
D16: PREPARING | G16: O
D17: PENDING | H17: O
D18: SHIP_PENDING | I18: O
A29: Confirm | B29: Return
D30: Cancel order | G30: O | H30: O | I30: O
D31: Cannot cancel orderr | F31: O
B32: Exception
B34: Log message
D35: "success"
D36: "input1 is null"
A37: Result | B37: Type(N : Normal, A : Abnormal, B : Boundary) | F37: A | G37: N | H37: N | I37: N
B38: Passed/Failed | F38: P | G38: P | H38: P | I38: P
B39: Executed Date | F39: 39139 | G39: 39139 | H39: 39140 | I39: 39141
B40: Defect ID

Sheet Request Order return
A1: Code Module | C1: ModuleName1 | F1: Method | L1: methodName1
A2: Created By | C2: <Developer Name> | F2: Executed By
A3: Test requirement | C3: <Brief description about requirements which are tested in this function>
A4: Passed | C4: Failed | F4: Untested | L4: N/A/B | O4: Total Test Cases
A5: =COUNTIF(F38:HQ38,"P") -> 3 | C5: =COUNTIF(F38:HQ38,"F") -> 0 | F5: =SUM(O5,-A5,-C5) -> 0 | L5: =COUNTIF(E37:HQ37,"N") -> 1 | M5: =COUNTIF(E37:HQ37,"A") -> 2 | N5: =COUNTIF(E37:HQ37,"B") -> 0 | O5: =COUNTA(E7:HT7) -> 3
F7: UTCID01 | G7: UTCID02 | H7: UTCID03
A8: Condition | B8: Precondition
D9: Can connect with server
B11: OrderId
D12: null | F12: O
D13: 1 | G13: O | H13: O
B14: OrderStatus
D15: SHIPPING | G15: O
D16: SHIPPED | H16: O
A29: Confirm | B29: Return
D30: Request Successfull | H30: O
D31: Request Fail | F31: O | G31: O
B32: Exception
B34: Log message
D35: "success"
D36: "input1 is null"
A37: Result | B37: Type(N : Normal, A : Abnormal, B : Boundary) | F37: A | G37: A | H37: N
B38: Passed/Failed | F38: P | G38: P | H38: P
B39: Executed Date | F39: 39139 | G39: 39139 | H39: 39140
B40: Defect ID

Sheet View Order List (Shopkeeper)
A1: Code Module | C1: ModuleName1 | F1: Method | L1: methodName1
A2: Created By | C2: <Developer Name> | F2: Executed By
A3: Test requirement | C3: <Brief description about requirements which are tested in this function>
A4: Passed | C4: Failed | F4: Untested | L4: N/A/B | O4: Total Test Cases
A5: =COUNTIF(F38:HQ38,"P") -> 11 | C5: =COUNTIF(F38:HQ38,"F") -> 0 | F5: =SUM(O5,-A5,-C5) -> 0 | L5: =COUNTIF(E37:HQ37,"N") -> 10 | M5: =COUNTIF(E37:HQ37,"A") -> 1 | N5: =COUNTIF(E37:HQ37,"B") -> 0 | O5: =COUNTA(E7:HT7) -> 11
F7: UTCID01 | G7: UTCID02 | H7: UTCID03 | I7: UTCID04 | J7: UTCID05 | K7: UTCID06 | L7: UTCID07 | M7: UTCID08 | N7: UTCID09 | O7: UTCID10 | P7: UTCID11
A8: Condition | B8: Precondition
D9: Can connect with server
B12: Order
D13: null | F13: O
D14: not null | G14: O | H14: O | I14: O | J14: O | K14: O | L14: O | M14: O | N14: O | O14: O | P14: O
B15: Status
D16: PENDING | G16: O
D17: PROCESSING | H17: O
D18: SHIP_PENDING | I18: O
D19: SHIPPING | J19: O
D20: DELIVERED | K20: O
D21: CANCELLED | L21: O
D22: RETURNED | M22: O
D23: REJECTED | N23: O
D24: RETURN_PENDING | O24: O
D25: RETURN_REJECTED | P25: O
A29: Confirm | B29: Return
D30: OrderList | G30: O | H30: O | I30: O | J30: O | K30: O | L30: O | M30: O | N30: O | O30: O | P30: O
D31: null | F31: O
B32: Exception
B34: Log message
D35: "success"
D36: "input1 is null"
A37: Result | B37: Type(N : Normal, A : Abnormal, B : Boundary) | F37: A | G37: N | H37: N | I37: N | J37: N | K37: N | L37: N | M37: N | N37: N | O37: N | P37: N
B38: Passed/Failed | F38: P | G38: P | H38: P | I38: P | J38: P | K38: P | L38: P | M38: P | N38: P | O38: P | P38: P
B39: Executed Date | F39: 39139 | G39: 39139 | H39: 39140 | I39: 39141 | J39: 39142 | K39: 39143 | L39: 39144 | M39: 39145 | N39: 39146 | O39: 39147 | P39: 39148
B40: Defect ID

Sheet Accept Order
A1: Code Module | C1: ModuleName1 | F1: Method | L1: methodName1
A2: Created By | C2: <Developer Name> | F2: Executed By
A3: Test requirement | C3: <Brief description about requirements which are tested in this function>
A4: Passed | C4: Failed | F4: Untested | L4: N/A/B | O4: Total Test Cases
A5: =COUNTIF(F38:HQ38,"P") -> 2 | C5: =COUNTIF(F38:HQ38,"F") -> 0 | F5: =SUM(O5,-A5,-C5) -> 0 | L5: =COUNTIF(E37:HQ37,"N") -> 1 | M5: =COUNTIF(E37:HQ37,"A") -> 1 | N5: =COUNTIF(E37:HQ37,"B") -> 0 | O5: =COUNTA(E7:HT7) -> 2
F7: UTCID01 | G7: UTCID02
A8: Condition | B8: Precondition
D9: Can connect with server
B13: OrderId
D14: null | F14: O
D15: 1 | G15: O
B16: OrderStatus
D17: PENDING | G17: O
A29: Confirm | B29: Return
D30: Order Accepted | G30: O
D31: Cannot accept order | F31: O
B32: Exception
B34: Log message
D35: "success"
D36: "input1 is null"
A37: Result | B37: Type(N : Normal, A : Abnormal, B : Boundary) | F37: A | G37: N
B38: Passed/Failed | F38: P | G38: P
B39: Executed Date | F39: 39139 | G39: 39139
B40: Defect ID

Sheet Reject Order
A1: Code Module | C1: ModuleName1 | F1: Method | L1: methodName1
A2: Created By | C2: <Developer Name> | F2: Executed By
A3: Test requirement | C3: <Brief description about requirements which are tested in this function>
A4: Passed | C4: Failed | F4: Untested | L4: N/A/B | O4: Total Test Cases
A5: =COUNTIF(F38:HQ38,"P") -> 2 | C5: =COUNTIF(F38:HQ38,"F") -> 0 | F5: =SUM(O5,-A5,-C5) -> 0 | L5: =COUNTIF(E37:HQ37,"N") -> 1 | M5: =COUNTIF(E37:HQ37,"A") -> 1 | N5: =COUNTIF(E37:HQ37,"B") -> 0 | O5: =COUNTA(E7:HT7) -> 2
F7: UTCID01 | G7: UTCID02
A8: Condition | B8: Precondition
D9: Can connect with server
B12: OrderId
D13: null | F13: O
D14: 1 | G14: O
B15: OrderStatus
D16: PENDING | G16: O
A29: Confirm | B29: Return
D30: Order Accepted | G30: O
D31: Cannot accept order | F31: O
B32: Exception
B34: Log message
D35: "success"
D36: "input1 is null"
A37: Result | B37: Type(N : Normal, A : Abnormal, B : Boundary) | F37: A | G37: N
B38: Passed/Failed | F38: P | G38: P
B39: Executed Date | F39: 39139 | G39: 39139
B40: Defect ID

Sheet Change Order Status (Shopkeeper
A1: Code Module | C1: ModuleName1 | F1: Method | L1: methodName1
A2: Created By | C2: <Developer Name> | F2: Executed By
A3: Test requirement | C3: <Brief description about requirements which are tested in this function>
A4: Passed | C4: Failed | F4: Untested | L4: N/A/B | O4: Total Test Cases
A5: =COUNTIF(F38:HQ38,"P") -> 3 | C5: =COUNTIF(F38:HQ38,"F") -> 0 | F5: =SUM(O5,-A5,-C5) -> 0 | L5: =COUNTIF(E37:HQ37,"N") -> 1 | M5: =COUNTIF(E37:HQ37,"A") -> 2 | N5: =COUNTIF(E37:HQ37,"B") -> 0 | O5: =COUNTA(E7:HT7) -> 3
F7: UTCID01 | G7: UTCID02 | H7: UTCID03
A8: Condition | B8: Precondition
D9: Can connect with server
B12: OrderId
D13: null | F13: O
D14: 1 | G14: O | H14: O
B15: OrderStatus
D16: PREPARING | G16: O
D17: PENDING | H17: O
A29: Confirm | B29: Return
D30: Change OrderStatus Successfull | G30: O
D31: Cannot change Order Status | F31: O | H31: O
B32: Exception
B34: Log message
D35: "success"
D36: "input1 is null"
A37: Result | B37: Type(N : Normal, A : Abnormal, B : Boundary) | F37: A | G37: N | H37: A
B38: Passed/Failed | F38: P | G38: P | H38: P
B39: Executed Date | F39: 39139 | G39: 39139 | H39: 39140
B40: Defect ID

Sheet Resolve Order Return Request
A1: Code Module | C1: ModuleName1 | F1: Method | L1: methodName1
A2: Created By | C2: <Developer Name> | F2: Executed By
A3: Test requirement | C3: <Brief description about requirements which are tested in this function>
A4: Passed | C4: Failed | F4: Untested | L4: N/A/B | O4: Total Test Cases
A5: =COUNTIF(F38:HQ38,"P") -> 15 | C5: =COUNTIF(F38:HQ38,"F") -> 0 | F5: =SUM(O5,-A5,-C5) -> 0 | L5: =COUNTIF(E37:HQ37,"N") -> 11 | M5: =COUNTIF(E37:HQ37,"A") -> 3 | N5: =COUNTIF(E37:HQ37,"B") -> 1 | O5: =COUNTA(E7:HT7) -> 15
F7: UTCID01 | G7: UTCID02 | H7: UTCID03 | I7: UTCID04 | J7: UTCID05 | K7: UTCID06 | L7: UTCID07 | M7: UTCID08 | N7: UTCID09 | O7: UTCID10 | P7: UTCID11 | Q7: UTCID12 | R7: UTCID13 | S7: UTCID14 | T7: UTCID15
A8: Condition | B8: Precondition
D9: Can connect with server
A29: Confirm | B29: Return
D30: T | F30: O | G30: O
D31: F
B32: Exception
B34: Log message
D35: "success"
D36: "input1 is null"
A37: Result | B37: Type(N : Normal, A : Abnormal, B : Boundary) | F37: A | G37: N | H37: N | I37: N | J37: N | K37: B | L37: A | M37: N | N37: N | O37: N | P37: N | Q37: N | R37: A | S37: N | T37: N
B38: Passed/Failed | F38: P | G38: P | H38: P | I38: P | J38: P | K38: P | L38: P | M38: P | N38: P | O38: P | P38: P | Q38: P | R38: P | S38: P | T38: P
B39: Executed Date | F39: 39139 | G39: 39139 | H39: 39140 | I39: 39141 | J39: 39142 | K39: 39143 | L39: 39144 | M39: 39145 | N39: 39146 | O39: 39147 | P39: 39148 | Q39: 39149 | R39: 39150 | S39: 39151 | T39: 39152
B40: Defect ID | K40: DFID002 | L40: DFID004 | M40: DFID005 | N40: DFID006 | O40: DFID007 | P40: DFID008 | Q40: DFID009 | R40: DFID010 | S40: DFID011 | T40: DFID012

Sheet View Order Detail (Shipper)
A1: Code Module | C1: ModuleName1 | F1: Method | L1: methodName1
A2: Created By | C2: <Developer Name> | F2: Executed By
A3: Test requirement | C3: <Brief description about requirements which are tested in this function>
A4: Passed | C4: Failed | F4: Untested | L4: N/A/B | O4: Total Test Cases
A5: =COUNTIF(F38:HQ38,"P") -> 4 | C5: =COUNTIF(F38:HQ38,"F") -> 0 | F5: =SUM(O5,-A5,-C5) -> 0 | L5: =COUNTIF(E37:HQ37,"N") -> 3 | M5: =COUNTIF(E37:HQ37,"A") -> 1 | N5: =COUNTIF(E37:HQ37,"B") -> 0 | O5: =COUNTA(E7:HT7) -> 4
F7: UTCID01 | G7: UTCID02 | H7: UTCID03 | I7: UTCID04
A8: Condition | B8: Precondition
D9: Can connect with server
B12: OrderId
D13: null | F13: O
D14: 1 | G14: O | H14: O | I14: O
B15: OrderStatus
D16: SHIP_PENDING | G16: O
D17: SHIPPING | H17: O
D18: DELIVERED | I18: O
A29: Confirm | B29: Return
D30: View OrderDetail | G30: O | H30: O | I30: O
D31: Cannot view Order Detail | F31: O
B32: Exception
B34: Log message
D35: "success"
D36: "input1 is null"
A37: Result | B37: Type(N : Normal, A : Abnormal, B : Boundary) | F37: A | G37: N | H37: N | I37: N
B38: Passed/Failed | F38: P | G38: P | H38: P | I38: P
B39: Executed Date | F39: 39139 | G39: 39139 | H39: 39140 | I39: 39141
B40: Defect ID

Sheet Change Order Status (Shipper)
A1: Code Module | C1: ModuleName1 | F1: Method | L1: methodName1
A2: Created By | C2: <Developer Name> | F2: Executed By
A3: Test requirement | C3: <Brief description about requirements which are tested in this function>
A4: Passed | C4: Failed | F4: Untested | L4: N/A/B | O4: Total Test Cases
A5: =COUNTIF(F38:HQ38,"P") -> 4 | C5: =COUNTIF(F38:HQ38,"F") -> 0 | F5: =SUM(O5,-A5,-C5) -> 0 | L5: =COUNTIF(E37:HQ37,"N") -> 1 | M5: =COUNTIF(E37:HQ37,"A") -> 3 | N5: =COUNTIF(E37:HQ37,"B") -> 0 | O5: =COUNTA(E7:HT7) -> 4
F7: UTCID01 | G7: UTCID02 | H7: UTCID03 | I7: UTCID04
A8: Condition | B8: Precondition
D9: Can connect with server
B12: OrderId
D13: null | F13: O
D14: 1 | G14: O | H14: O | I14: O
B15: OrderStatus
D16: SHIP_PENDING | G16: O
D17: SHIPPING | H17: O
D18: DELIVERED | I18: O
A29: Confirm | B29: Return
D30: Change Order Status Successfull | H30: O
D31: Cannot change Order Status | F31: O | G31: O | I31: O
B32: Exception
B34: Log message
D35: "success"
D36: "input1 is null"
A37: Result | B37: Type(N : Normal, A : Abnormal, B : Boundary) | F37: A | G37: A | H37: N | I37: A
B38: Passed/Failed | F38: P | G38: P | H38: P | I38: P
B39: Executed Date | F39: 39139 | G39: 39139 | H39: 39140 | I39: 39141
B40: Defect ID

Sheet Confirm Order Receive(Customer)
A1: Code Module | C1: ModuleName1 | F1: Method | L1: methodName1
A2: Created By | C2: <Developer Name> | F2: Executed By
A3: Test requirement | C3: <Brief description about requirements which are tested in this function>
A4: Passed | C4: Failed | F4: Untested | L4: N/A/B | O4: Total Test Cases
A5: =COUNTIF(F38:HQ38,"P") -> 3 | C5: =COUNTIF(F38:HQ38,"F") -> 0 | F5: =SUM(O5,-A5,-C5) -> 0 | L5: =COUNTIF(E37:HQ37,"N") -> 1 | M5: =COUNTIF(E37:HQ37,"A") -> 2 | N5: =COUNTIF(E37:HQ37,"B") -> 0 | O5: =COUNTA(E7:HT7) -> 3
F7: UTCID01 | G7: UTCID02 | H7: UTCID03
A8: Condition | B8: Precondition
D9: Can connect with server
B12: OrderId
D13: null | F13: O
D14: 1 | G14: O | H14: O
B15: OrderStatus
D16: SHIPPING | G16: O
D17: DELIVERED | H17: O
A29: Confirm | B29: Return
D30: Confirm Order Successfull | H30: O
D31: Cannot confirm order | F31: O | G31: O
B32: Exception
B34: Log message
D35: "success"
D36: "input1 is null"
A37: Result | B37: Type(N : Normal, A : Abnormal, B : Boundary) | F37: A | G37: A | H37: N
B38: Passed/Failed | F38: P | G38: P | H38: P
B39: Executed Date | F39: 39139 | G39: 39139 | H39: 39140
B40: Defect ID

Sheet Check Out
A1: Code Module | C1: ModuleName1 | F1: Method | L1: methodName1
A2: Created By | C2: <Developer Name> | F2: Executed By
A3: Test requirement | C3: <Brief description about requirements which are tested in this function>
A4: Passed | C4: Failed | F4: Untested | L4: N/A/B | O4: Total Test Cases
A5: =COUNTIF(F41:HQ41,"P") -> 5 | C5: =COUNTIF(F41:HQ41,"F") -> 0 | F5: =SUM(O5,-A5,-C5) -> 0 | L5: =COUNTIF(E40:HQ40,"N") -> 2 | M5: =COUNTIF(E40:HQ40,"A") -> 2 | N5: =COUNTIF(E40:HQ40,"B") -> 1 | O5: =COUNTA(E7:HT7) -> 5
F7: UTCID01 | G7: UTCID02 | H7: UTCID03 | I7: UTCID04 | J7: UTCID05
A8: Condition | B8: Precondition
D9: Can connect with server
B12: ProductId
D13: null | F13: O
D14: 1 | H14: O | I14: O | J14: O
B15: FoodOptionId
D16: null | G16: O
D17: 1 | H17: O | I17: O | J17: O
B18: Quantity
D19: 0 | H19: O
D20: 1 | I20: O
D21: 1000 | J21: O
A30: Confirm | B30: Return
D31: OrderId | H31: O | I31: O
D32: Null | F32: O | G32: O | J32: O
B33: Exception
B35: Log message
D36: Số lượng không đủ | J36: O
D37: Lỗi khi tạo order | F37: O | G37: O
D38: Tạo order thành công | H38: O | I38: O
A40: Result | B40: Type(N : Normal, A : Abnormal, B : Boundary) | F40: A | G40: A | H40: N | I40: N | J40: B
B41: Passed/Failed | F41: P | G41: P | H41: P | I41: P | J41: P
B42: Executed Date | F42: 39139 | G42: 39139 | H42: 39140 | I42: 39141 | J42: 39142
B43: Defect ID

Sheet Choose Payment Method
A1: Code Module | C1: ModuleName1 | F1: Method | L1: methodName1
A2: Created By | C2: <Developer Name> | F2: Executed By
A3: Test requirement | C3: <Brief description about requirements which are tested in this function>
A4: Passed | C4: Failed | F4: Untested | L4: N/A/B | O4: Total Test Cases
A5: =COUNTIF(F38:HQ38,"P") -> 3 | C5: =COUNTIF(F38:HQ38,"F") -> 0 | F5: =SUM(O5,-A5,-C5) -> 0 | L5: =COUNTIF(E37:HQ37,"N") -> 1 | M5: =COUNTIF(E37:HQ37,"A") -> 2 | N5: =COUNTIF(E37:HQ37,"B") -> 0 | O5: =COUNTA(E7:HT7) -> 3
F7: UTCID01 | G7: UTCID02 | H7: UTCID03
A8: Condition | B8: Precondition
D9: Can connect with server
B12: PaymentMethodId
D13: null | F13: O
D14: 1 | G14: O | H14: O
D15: 2 | H15: O
A29: Confirm | B29: Return
D30: T | G30: O
D31: F | F31: O | H31: O
B32: Exception
B34: Log message
D35: "success"
D36: "input1 is null"
A37: Result | B37: Type(N : Normal, A : Abnormal, B : Boundary) | F37: A | G37: N | H37: A
B38: Passed/Failed | F38: P | G38: P | H38: P
B39: Executed Date | F39: 39139 | G39: 39139 | H39: 39140
B40: Defect ID

Sheet Choose Shipping Method
A1: Code Module | C1: ModuleName1 | F1: Method | L1: methodName1
A2: Created By | C2: <Developer Name> | F2: Executed By
A3: Test requirement | C3: <Brief description about requirements which are tested in this function>
A4: Passed | C4: Failed | F4: Untested | L4: N/A/B | O4: Total Test Cases
A5: =COUNTIF(F38:HQ38,"P") -> 3 | C5: =COUNTIF(F38:HQ38,"F") -> 0 | F5: =SUM(O5,-A5,-C5) -> 0 | L5: =COUNTIF(E37:HQ37,"N") -> 1 | M5: =COUNTIF(E37:HQ37,"A") -> 2 | N5: =COUNTIF(E37:HQ37,"B") -> 0 | O5: =COUNTA(E7:HT7) -> 3
F7: UTCID01 | G7: UTCID02 | H7: UTCID03
A8: Condition | B8: Precondition
D9: Can connect with server
B12: DeliveryMethodId
D13: null | F13: O
D14: 1 | G14: O | H14: O
D15: 2 | H15: O
A29: Confirm | B29: Return
D30: T | G30: O
D31: F | F31: O | H31: O
B32: Exception
B34: Log message
D35: "success"
D36: "input1 is null"
A37: Result | B37: Type(N : Normal, A : Abnormal, B : Boundary) | F37: A | G37: N | H37: A
B38: Passed/Failed | F38: P | G38: P | H38: P
B39: Executed Date | F39: 39139 | G39: 39139 | H39: 39140
B40: Defect ID

Sheet View Voucher List
A1: Code Module | C1: ModuleName1 | F1: Method | L1: methodName1
A2: Created By | C2: <Developer Name> | F2: Executed By
A3: Test requirement | C3: <Brief description about requirements which are tested in this function>
A4: Passed | C4: Failed | F4: Untested | L4: N/A/B | O4: Total Test Cases
A5: =COUNTIF(F38:HQ38,"P") -> 3 | C5: =COUNTIF(F38:HQ38,"F") -> 0 | F5: =SUM(O5,-A5,-C5) -> 0 | L5: =COUNTIF(E37:HQ37,"N") -> 2 | M5: =COUNTIF(E37:HQ37,"A") -> 1 | N5: =COUNTIF(E37:HQ37,"B") -> 0 | O5: =COUNTA(E7:HT7) -> 3
F7: UTCID01 | G7: UTCID02 | H7: UTCID03
A8: Condition | B8: Precondition
D9: Can connect with server
B12: ShopId
D13: null | F13: O
D14: 1 | G14: O | H14: O
B15: VoucherId
D16: null | G16: O
D17: 1 | H17: O
A29: Confirm | B29: Return
D30: T | G30: O | H30: O
D31: F | F31: O
B32: Exception
B34: Log message
D35: "success"
D36: "input1 is null"
A37: Result | B37: Type(N : Normal, A : Abnormal, B : Boundary) | F37: A | G37: N | H37: N
B38: Passed/Failed | F38: P | G38: P | H38: P
B39: Executed Date | F39: 39139 | G39: 39139 | H39: 39140
B40: Defect ID

Sheet Create Voucher
A1: Code Module | C1: ModuleName1 | F1: Method | L1: methodName1
A2: Created By | C2: <Developer Name> | F2: Executed By
A3: Test requirement | C3: <Brief description about requirements which are tested in this function>
A4: Passed | C4: Failed | F4: Untested | L4: N/A/B | O4: Total Test Cases
A5: =COUNTIF(F40:HK40,"P") -> 10 | C5: =COUNTIF(F40:HK40,"F") -> 0 | F5: =SUM(O5,-A5,-C5) -> 0 | L5: =COUNTIF(E39:HK39,"N") -> 1 | M5: =COUNTIF(E39:HK39,"A") -> 3 | N5: =COUNTIF(E39:HK39,"B") -> 6 | O5: =COUNTA(E7:HN7) -> 10
F7: UTCID01 | G7: UTCID02 | H7: UTCID03 | I7: UTCID04 | J7: UTCID05 | K7: UTCID06 | L7: UTCID07 | M7: UTCID08 | N7: UTCID09 | O7: UTCID10
A8: Condition | B8: Precondition
D9: Can connect with server
B12: Value
D13: -1 | F13: O
D14: 0 | G14: O
D15: 0.3 | H15: O | K15: O | L15: O | M15: O | N15: O | O15: O
D16: 1 | I16: O
D17: 2 | J17: O
B18: minOrderValue
D19: 0 | F19: O | G19: O | H19: O | I19: O | J19: O
D20: 100 | K20: O | L20: O | M20: O | N20: O | O20: O
B21: totalVoucher
D22: 0 | K22: O
D23: 10 | L23: O | M23: O | N23: O | O23: O
B24: startDate
D25: 36545 | L25: O
D26: 45797 | M26: O | N26: O | O26: O
B27: endDate
D28: 36545 | M28: O
D29: 45796 | N29: O
D30: 45799 | O30: O
A31: Confirm | B31: Return
D32: Tạo voucher thành công | O32: O
D33: Lỗi khi tạo voucher | F33: O | G33: O | H33: O | I33: O | J33: O | K33: O | L33: O | M33: O | N33: O
B34: Exception
B36: Log message
D37: "success"
D38: "input1 is null"
A39: Result | B39: Type(N : Normal, A : Abnormal, B : Boundary) | F39: B | G39: B | H39: B | I39: B | J39: B | K39: B | L39: A | M39: A | N39: A | O39: N
B40: Passed/Failed | F40: P | G40: P | H40: P | I40: P | J40: P | K40: P | L40: P | M40: P | N40: P | O40: P
B41: Executed Date | F41: 39139 | G41: 39139 | H41: 39140 | I41: 39141 | J41: 39142 | K41: 39143 | L41: 39144 | M41: 39145 | N41: 39146 | O41: 39147
B42: Defect ID

Sheet Apply Voucher
A1: Code Module | C1: ModuleName1 | F1: Method | L1: methodName1
A2: Created By | C2: <Developer Name> | F2: Executed By
A3: Test requirement | C3: <Brief description about requirements which are tested in this function>
A4: Passed | C4: Failed | F4: Untested | L4: N/A/B | O4: Total Test Cases
A5: =COUNTIF(F38:HQ38,"P") -> 6 | C5: =COUNTIF(F38:HQ38,"F") -> 0 | F5: =SUM(O5,-A5,-C5) -> 0 | L5: =COUNTIF(E37:HQ37,"N") -> 1 | M5: =COUNTIF(E37:HQ37,"A") -> 2 | N5: =COUNTIF(E37:HQ37,"B") -> 3 | O5: =COUNTA(E7:HT7) -> 6
F7: UTCID01 | G7: UTCID02 | H7: UTCID03 | I7: UTCID04 | J7: UTCID05 | K7: UTCID06
A8: Condition | B8: Precondition
D9: Can connect with server
B11: VoucherId
D12: null | F12: O
D13: 1 | G13: O
B14: Order Value
D15: 100 | G15: O
D16: 10 | K16: O
B17: User's voucher usage count
D18: 0 | G18: O
D19: 1 | H19: O
B20: Endate
D21: 45797 | G21: O
D22: 36666 | I22: O
B23: Voucher count left
D24: 0 | J24: O
D25: 20 | G25: O
A29: Confirm | B29: Return
D30: T | F30: O | G30: O
D31: F
B32: Exception
B34: Log message
D35: "success"
D36: "input1 is null"
A37: Result | B37: Type(N : Normal, A : Abnormal, B : Boundary) | F37: A | G37: N | H37: B | I37: A | J37: B | K37: B
B38: Passed/Failed | F38: P | G38: P | H38: P | I38: P | J38: P | K38: P
B39: Executed Date | F39: 39139 | G39: 39139 | H39: 39140 | I39: 39141 | J39: 39142 | K39: 39143
B40: Defect ID

Sheet Disable Voucher
A1: Code Module | C1: ModuleName1 | F1: Method | L1: methodName1
A2: Created By | C2: <Developer Name> | F2: Executed By
A3: Test requirement | C3: <Brief description about requirements which are tested in this function>
A4: Passed | C4: Failed | F4: Untested | L4: N/A/B | O4: Total Test Cases
A5: =COUNTIF(F38:HQ38,"P") -> 2 | C5: =COUNTIF(F38:HQ38,"F") -> 0 | F5: =SUM(O5,-A5,-C5) -> 0 | L5: =COUNTIF(E37:HQ37,"N") -> 1 | M5: =COUNTIF(E37:HQ37,"A") -> 1 | N5: =COUNTIF(E37:HQ37,"B") -> 0 | O5: =COUNTA(E7:HT7) -> 2
F7: UTCID01 | G7: UTCID02
A8: Condition | B8: Precondition
D9: Can connect with server
B13: EndDate
D14: 45797 | F14: O
D15: 36545 | G15: O
A29: Confirm | B29: Return
D30: T | F30: O
D31: F | G31: O
B32: Exception
B34: Log message
D35: "success"
D36: "input1 is null"
A37: Result | B37: Type(N : Normal, A : Abnormal, B : Boundary) | F37: N | G37: A
B38: Passed/Failed | F38: P | G38: P
B39: Executed Date | F39: 39139 | G39: 39139
B40: Defect ID

Sheet Create Discount
A1: Code Module | C1: ModuleName1 | F1: Method | L1: methodName1
A2: Created By | C2: <Developer Name> | F2: Executed By
A3: Test requirement | C3: <Brief description about requirements which are tested in this function>
A4: Passed | C4: Failed | F4: Untested | L4: N/A/B | O4: Total Test Cases
A5: =COUNTIF(F41:HQ41,"P") -> 7 | C5: =COUNTIF(F41:HQ41,"F") -> 0 | F5: =SUM(O5,-A5,-C5) -> 0 | L5: =COUNTIF(E40:HQ40,"N") -> 1 | M5: =COUNTIF(E40:HQ40,"A") -> 5 | N5: =COUNTIF(E40:HQ40,"B") -> 1 | O5: =COUNTA(E7:HT7) -> 7
F7: UTCID01 | G7: UTCID02 | H7: UTCID03 | I7: UTCID04 | J7: UTCID05 | K7: UTCID06 | L7: UTCID07
A8: Condition | B8: Precondition
D9: Can connect with server
B12: ProductId
D13: null | F13: O
D14: 1 | G14: O | H14: O | I14: O | J14: O | K14: O | L14: O
B15: Amount
D16: 0 | G16: O
D17: -1 | H17: O
D18: 0.5 | J18: O | K18: O | L18: O
D19: 2 | I19: O
B20: StartDate
D21: 45677 | J21: O
D22: 45767 | K22: O | L22: O
B23: EndDate
D24: 45677 | K24: O
D25: 45797 | L25: O
A32: Confirm | B32: Return
D33: T | L33: O
D34: F | F34: O | G34: O | H34: O | I34: O | J34: O | K34: O
B35: Exception
B37: Log message
D38: "success"
D39: "input1 is null"
A40: Result | B40: Type(N : Normal, A : Abnormal, B : Boundary) | F40: A | G40: B | H40: A | I40: A | J40: A | K40: A | L40: N
B41: Passed/Failed | F41: P | G41: P | H41: P | I41: P | J41: P | K41: P | L41: P
B42: Executed Date | F42: 39139 | G42: 39139 | H42: 39140 | I42: 39141 | J42: 39142 | K42: 39143 | L42: 39144
B43: Defect ID

Sheet View Discount List
A1: Code Module | C1: ModuleName1 | F1: Method | L1: methodName1
A2: Created By | C2: <Developer Name> | F2: Executed By
A3: Test requirement | C3: <Brief description about requirements which are tested in this function>
A4: Passed | C4: Failed | F4: Untested | L4: N/A/B | O4: Total Test Cases
A5: =COUNTIF(F38:HQ38,"P") -> 2 | C5: =COUNTIF(F38:HQ38,"F") -> 0 | F5: =SUM(O5,-A5,-C5) -> 0 | L5: =COUNTIF(E37:HQ37,"N") -> 1 | M5: =COUNTIF(E37:HQ37,"A") -> 1 | N5: =COUNTIF(E37:HQ37,"B") -> 0 | O5: =COUNTA(E7:HT7) -> 2
F7: UTCID01 | G7: UTCID02
A8: Condition | B8: Precondition
D9: Can connect with server
B12: DiscountList
D13: null
D14: not null
B15: Status
D16: active
A29: Confirm | B29: Return
D30: T | F30: O | G30: O
D31: F
B32: Exception
B34: Log message
D35: "success"
D36: "input1 is null"
A37: Result | B37: Type(N : Normal, A : Abnormal, B : Boundary) | F37: A | G37: N
B38: Passed/Failed | F38: P | G38: P
B39: Executed Date | F39: 39139 | G39: 39139
B40: Defect ID

Sheet Disable Discount
A1: Code Module | C1: ModuleName1 | F1: Method | L1: methodName1
A2: Created By | C2: <Developer Name> | F2: Executed By
A3: Test requirement | C3: <Brief description about requirements which are tested in this function>
A4: Passed | C4: Failed | F4: Untested | L4: N/A/B | O4: Total Test Cases
A5: =COUNTIF(F38:HQ38,"P") -> 2 | C5: =COUNTIF(F38:HQ38,"F") -> 0 | F5: =SUM(O5,-A5,-C5) -> 0 | L5: =COUNTIF(E37:HQ37,"N") -> 1 | M5: =COUNTIF(E37:HQ37,"A") -> 1 | N5: =COUNTIF(E37:HQ37,"B") -> 0 | O5: =COUNTA(E7:HT7) -> 2
F7: UTCID01 | G7: UTCID02
A8: Condition | B8: Precondition
D9: Can connect with server
B13: EndDate
D14: 45797 | F14: O
D15: 36545 | G15: O
A29: Confirm | B29: Return
D30: T | F30: O
D31: F | G31: O
B32: Exception
B34: Log message
D35: "success"
D36: "input1 is null"
A37: Result | B37: Type(N : Normal, A : Abnormal, B : Boundary) | F37: N | G37: A
B38: Passed/Failed | F38: P | G38: P
B39: Executed Date | F39: 39139 | G39: 39139
B40: Defect ID
